Workbook

Sheet Dashboard
A1: AYA DATA — CRM | U1: All Time
A2: Live view across Inbound, Pipeline & Revenue. All data pulls from Tabs 1-3. Use the ⏱ PERIOD toggle (right) to filter by time. | U2: 2025
A3: 📊 KEY METRICS AT A GLANCE | O3: ⏱ PERIOD ▸ | P3: 2026 | U3: 2026
A4: =COUNTIFS('1. Inbound Leads'!B8:B1000, ">="&U10, '1. Inbound Leads'!B8:B1000, "<="&U12) -> 63 | C4: =COUNTIFS('1. Inbound Leads'!AC8:AC396,"Move to Scoping",'1. Inbound Leads'!B8:B396,">="&U10,'1. Inbound Leads'!B8:B396,"<="&U12) -> 1 | E4: =IFERROR(C4/A4,0) -> 0.015873016 | G4: =COUNTIFS('2. Scoping & PoC'!Y7:Y183,"Scoping",'2. Scoping & PoC'!E7:E183,">="&U10,'2. Scoping & PoC'!E7:E183,"<="&U12)+COUNTIFS('2. Scoping & PoC'!Y7:Y183,"PoC In Progress",'2. Scoping & PoC'!E7:E183,">="&U10,'2. Scoping & PoC'!E7:E183,"<="&U12)+COUNTIFS('2. Scoping & PoC'!Y7:Y183,"PoC Complete",'2. Scoping & PoC'!E7:E183,">="&U10,'2. Scoping & PoC'!E7:E183,"<="&U12) -> 5 | I4: =COUNTIFS('2. Scoping & PoC'!Y7:Y183,"PoC In Progress",'2. Scoping & PoC'!E7:E183,">="&U10,'2. Scoping & PoC'!E7:E183,"<="&U12) -> 0 | K4: =COUNTIFS('2. Scoping & PoC'!Y7:Y183,"Won*",'2. Scoping & PoC'!E7:E183,">="&U10,'2. Scoping & PoC'!E7:E183,"<="&U12) -> 4 | M4: =COUNTIFS('2. Scoping & PoC'!Y7:Y183,"Lost",'2. Scoping & PoC'!E7:E183,">="&U10,'2. Scoping & PoC'!E7:E183,"<="&U12) -> 4 | O4: =IFERROR(K4/(K4+M4),0) -> 0.5 | Q4: {=IFERROR(SUMPRODUCT(('2. Scoping & PoC'!AA6:AA1996<>"")*IF(ISNUMBER('2. Scoping & PoC'!AA6:AA1996),'2. Scoping & PoC'!AA6:AA1996,0)),0)} -> 24000 | S4: =IFERROR(AVERAGE('2. Scoping & PoC'!Z7:Z183),0) -> 0.34 | U4: Last 3 months
A5: Total Inbound Leads | C5: Moved to Scoping | E5: Lead → Scoping % | G5: Active in Scoping | I5: PoCs Running | K5: Deals Won | M5: Deals Lost | O5: Win Rate | Q5: Weighted Pipeline ($) | S5: Avg. Days in Scoping | U5: Last 6 months
U6: YTD 2025
A7: 1 │ INBOUND LEAD VOLUME
A8: Month | B8: Leads | U8: Period Helpers
A9: 2025-01 | B9: =COUNTIFS('1. Inbound Leads'!B8:B203,">="&DATE(2025,1,1),'1. Inbound Leads'!B8:B203,"<"&DATE(2025,2,1)) -> 9 | U9: Start Date
A10: 2025-02 | B10: =COUNTIFS('1. Inbound Leads'!B8:B203,">="&DATE(2025,2,1),'1. Inbound Leads'!B8:B203,"<"&DATE(2025,3,1)) -> 15 | U10: =IF(P3="All Time",DATE(2000,1,1),IF(P3&""="2025",DATE(2025,1,1),IF(P3&""="2026",DATE(2026,1,1),IF(P3="Last 3 months",EDATE(TODAY(),-3),IF(P3="Last 6 months",EDATE(TODAY(),-6),IF(P3="YTD 2025",DATE(2025,1,1),DATE(2000,1,1))))))) -> 46023
A11: 2025-03 | B11: =COUNTIFS('1. Inbound Leads'!B8:B203,">="&DATE(2025,3,1),'1. Inbound Leads'!B8:B203,"<"&DATE(2025,4,1)) -> 9 | U11: End Date
A12: 2025-04 | B12: =COUNTIFS('1. Inbound Leads'!B8:B203,">="&DATE(2025,4,1),'1. Inbound Leads'!B8:B203,"<"&DATE(2025,5,1)) -> 11 | U12: =IF(P3="All Time",DATE(2030,12,31),IF(P3&""="2025",DATE(2025,12,31),IF(P3&""="2026",DATE(2026,12,31),IF(P3="Last 3 months",TODAY(),IF(P3="Last 6 months",TODAY(),IF(P3="YTD 2025",TODAY(),DATE(2030,12,31))))))) -> 46387
A13: 2025-05 | B13: =COUNTIFS('1. Inbound Leads'!B8:B203,">="&DATE(2025,5,1),'1. Inbound Leads'!B8:B203,"<"&DATE(2025,6,1)) -> 17 | U13: Period Label
A14: 2025-06 | B14: =COUNTIFS('1. Inbound Leads'!B8:B203,">="&DATE(2025,6,1),'1. Inbound Leads'!B8:B203,"<"&DATE(2025,7,1)) -> 13 | U14: =P3 -> 2026
A15: 2025-07 | B15: =COUNTIFS('1. Inbound Leads'!B8:B203,">="&DATE(2025,7,1),'1. Inbound Leads'!B8:B203,"<"&DATE(2025,8,1)) -> 14
A16: 2025-08 | B16: =COUNTIFS('1. Inbound Leads'!B8:B203,">="&DATE(2025,8,1),'1. Inbound Leads'!B8:B203,"<"&DATE(2025,9,1)) -> 15
A17: 2025-09 | B17: =COUNTIFS('1. Inbound Leads'!B8:B203,">="&DATE(2025,9,1),'1. Inbound Leads'!B8:B203,"<"&DATE(2025,10,1)) -> 16
A18: 2025-10 | B18: =COUNTIFS('1. Inbound Leads'!B8:B203,">="&DATE(2025,10,1),'1. Inbound Leads'!B8:B203,"<"&DATE(2025,11,1)) -> 23
A19: 2025-11 | B19: =COUNTIFS('1. Inbound Leads'!B8:B203,">="&DATE(2025,11,1),'1. Inbound Leads'!B8:B203,"<"&DATE(2025,12,1)) -> 13
A20: 2025-12 | B20: =COUNTIFS('1. Inbound Leads'!B8:B203,">="&DATE(2025,12,1),'1. Inbound Leads'!B8:B203,"<"&DATE(2026,1,1)) -> 10
A21: 2026-01 | B21: =COUNTIFS('1. Inbound Leads'!B8:B203,">="&DATE(2026,1,1),'1. Inbound Leads'!B8:B203,"<"&DATE(2026,2,1)) -> 15
A22: 2026-02 | B22: =COUNTIFS('1. Inbound Leads'!B8:B396,">="&DATE(2026,2,1),'1. Inbound Leads'!B8:B396,"<"&DATE(2026,3,1)) -> 19
A23: 2026-03 | B23: =COUNTIFS('1. Inbound Leads'!B8:B396,">="&DATE(2026,3,1),'1. Inbound Leads'!B8:B396,"<"&DATE(2026,4,1)) -> 24
A24: 2026-04 | B24: =COUNTIFS('1. Inbound Leads'!B8:B396,">="&DATE(2026,4,1),'1. Inbound Leads'!B8:B396,"<"&DATE(2026,5,1)) -> 5
A25: 2026-05 | B25: =COUNTIFS('1. Inbound Leads'!B8:B203,">="&DATE(2026,5,1),'1. Inbound Leads'!B8:B203,"<"&DATE(2026,6,1)) -> 0
A26: 2026-06 | B26: =COUNTIFS('1. Inbound Leads'!B8:B203,">="&DATE(2026,6,1),'1. Inbound Leads'!B8:B203,"<"&DATE(2026,7,1)) -> 0
A27: 2026-07 | B27: =COUNTIFS('1. Inbound Leads'!B8:B203,">="&DATE(2026,7,1),'1. Inbound Leads'!B8:B203,"<"&DATE(2026,8,1)) -> 0
A28: 2026-08 | B28: =COUNTIFS('1. Inbound Leads'!B8:B203,">="&DATE(2026,8,1),'1. Inbound Leads'!B8:B203,"<"&DATE(2026,9,1)) -> 0
A29: 2026-09 | B29: =COUNTIFS('1. Inbound Leads'!B8:B203,">="&DATE(2026,9,1),'1. Inbound Leads'!B8:B203,"<"&DATE(2026,10,1)) -> 0
A30: 2026-10 | B30: =COUNTIFS('1. Inbound Leads'!B8:B203,">="&DATE(2026,10,1),'1. Inbound Leads'!B8:B203,"<"&DATE(2026,11,1)) -> 0
A31: 2026-11 | B31: =COUNTIFS('1. Inbound Leads'!B8:B203,">="&DATE(2026,11,1),'1. Inbound Leads'!B8:B203,"<"&DATE(2026,12,1)) -> 0
A32: 2026-12 | B32: =COUNTIFS('1. Inbound Leads'!B8:B203,">="&DATE(2026,12,1),'1. Inbound Leads'!B8:B203,"<"&DATE(2027,1,1)) -> 0
A34: 1b │ LEADS BY BUSINESS UNIT
A35: Business Unit | B35: Count | C35: % Share
A36: Annotation | B36: =COUNTIF('1. Inbound Leads'!O8:O451,"Data Annotation") -> 170 | C36: =IFERROR(B36/SUM(B36:B38),0) -> 0.75555556
A37: Solutions | B37: =COUNTIF('1. Inbound Leads'!O8:O451,"AI Solutions") -> 43 | C37: =IFERROR(B37/SUM(B36:B38),0) -> 0.19111111
A38: Partnerships | B38: =COUNTIF('1. Inbound Leads'!O8:O450,"Partnerships") -> 12 | C38: =IFERROR(B38/SUM(B36:B38),0) -> 0.053333333
A40: 1c │ LEADS BY INDUSTRY VERTICAL
A41: Vertical | B41: Count | C41: % Share
A42: Healthcare/Medical | B42: =COUNTIF('1. Inbound Leads'!X8:X396,"Healthcare/Medical") -> 21 | C42: =IFERROR(B42/SUM(B$42:B$51),0) -> 0.27631579
A43: Automotive/AV | B43: =COUNTIF('1. Inbound Leads'!X8:X396,"Automotive/AV") -> 29 | C43: =IFERROR(B43/SUM(B$42:B$51),0) -> 0.38157895
A44: Agriculture/Geo | B44: =COUNTIF('1. Inbound Leads'!X8:X396,"Agriculture/Geo") -> 0 | C44: =IFERROR(B44/SUM(B$42:B$51),0) -> 0
A45: Finance | B45: =COUNTIF('1. Inbound Leads'!X8:X396,"Finance") -> 0 | C45: =IFERROR(B45/SUM(B$42:B$51),0) -> 0
A46: Retail/E-commerce | B46: =COUNTIF('1. Inbound Leads'!X8:X396,"Retail/E-commerce") -> 2 | C46: =IFERROR(B46/SUM(B$42:B$51),0) -> 0.026315789
A47: Robotics | B47: =COUNTIF('1. Inbound Leads'!X8:X203,"Robotics") -> 0 | C47: =IFERROR(B47/SUM(B$42:B$51),0) -> 0
A48: Government/Defence | B48: =COUNTIF('1. Inbound Leads'!X8:X400,"Government/Defence") -> 0 | C48: =IFERROR(B48/SUM(B$42:B$51),0) -> 0
A49: Education | B49: =COUNTIF('1. Inbound Leads'!X8:X2396,"Education") -> 2 | C49: =IFERROR(B49/SUM(B$42:B$51),0) -> 0.026315789
A50: Tech/SaaS | B50: =COUNTIF('1. Inbound Leads'!X8:X396,"Tech/SaaS") -> 11 | C50: =IFERROR(B50/SUM(B$42:B$51),0) -> 0.14473684
A51: Other | B51: =COUNTIF('1. Inbound Leads'!X8:X396,"Other") -> 11 | C51: =IFERROR(B51/SUM(B$42:B$51),0) -> 0.14473684
A53: 1d │ LEADS BY COUNTRY (Top 15)
A54: Country | B54: Count | C54: % Share
A55: United States | B55: =COUNTIF('1. Inbound Leads'!I8:I950,"*USA*") -> 19 | C55: =IFERROR(B55/SUM(B$55:B$72),0) -> 0.19791667
A56: United Kingdom | B56: =COUNTIF('1. Inbound Leads'!I8:I996,"*UK*") -> 13 | C56: =IFERROR(B56/SUM(B$55:B$72),0) -> 0.13541667
A57: India | B57: =COUNTIF('1. Inbound Leads'!I8:I996,"*India*") -> 11 | C57: =IFERROR(B57/SUM(B$55:B$72),0) -> 0.11458333
A58: Nigeria | B58: =COUNTIF('1. Inbound Leads'!I8:I996,"*Nigeria*") -> 0 | C58: =IFERROR(B58/SUM(B$55:B$72),0) -> 0
A59: Ghana | B59: =COUNTIF('1. Inbound Leads'!I8:I396,"*Ghana*") -> 18 | C59: =IFERROR(B59/SUM(B$55:B$72),0) -> 0.1875
A60: Kenya | B60: =COUNTIF('1. Inbound Leads'!I8:I996,"*Kenya*") -> 0 | C60: =IFERROR(B60/SUM(B$55:B$72),0) -> 0
A61: South Africa | B61: =COUNTIF('1. Inbound Leads'!I8:I960,"*South Africa*") -> 0 | C61: =IFERROR(B61/SUM(B$55:B$72),0) -> 0
A62: Germany | B62: =COUNTIF('1. Inbound Leads'!I8:I950,"*Germany*") -> 2 | C62: =IFERROR(B62/SUM(B$55:B$72),0) -> 0.020833333
A63: Australia | B63: =COUNTIF('1. Inbound Leads'!I8:I950,"*Australia*") -> 2 | C63: =IFERROR(B63/SUM(B$55:B$72),0) -> 0.020833333
A64: Canada | B64: =COUNTIF('1. Inbound Leads'!I8:I950,"*Canada*") -> 1 | C64: =IFERROR(B64/SUM(B$55:B$72),0) -> 0.010416667
A65: France | B65: =COUNTIF('1. Inbound Leads'!I8:I996,"*France*") -> 1 | C65: =IFERROR(B65/SUM(B$55:B$72),0) -> 0.010416667
A66: Cameroon | B66: =COUNTIF('1. Inbound Leads'!I8:I996,"*Cameroon*") -> 1 | C66: =IFERROR(B66/SUM(B$55:B$72),0) -> 0.010416667
A67: Japan | B67: =COUNTIF('1. Inbound Leads'!I8:I996,"*Japan*") -> 1 | C67: =IFERROR(B67/SUM(B$55:B$72),0) -> 0.010416667
A68: Malaysia | B68: =COUNTIF('1. Inbound Leads'!I8:I996,"*Malaysia*") -> 1 | C68: =IFERROR(B68/SUM(B$55:B$72),0) -> 0.010416667
A69: Rwanda | B69: =COUNTIF('1. Inbound Leads'!I8:I996,"*Rwanda*") -> 1 | C69: =IFERROR(B69/SUM(B$55:B$72),0) -> 0.010416667
A70: Isreal | B70: =COUNTIF('1. Inbound Leads'!I9:I997,"*Isreal*") -> 1 | C70: =IFERROR(B70/SUM(B$55:B$72),0) -> 0.010416667
A71: Netherlands | B71: =COUNTIF('1. Inbound Leads'!I8:I996,"*Netherlands*") -> 1 | C71: =IFERROR(B71/SUM(B$55:B$72),0) -> 0.010416667
A72: Other | B72: =COUNTA('1. Inbound Leads'!I8:I450)-SUM(B55:B71) -> 23 | C72: =IFERROR(B72/SUM(B$55:B$72),0) -> 0.23958333
A75: 2 │ MONTHLY FUNNEL CONVERSION RATES
A76: Month | B76: Inbound | C76: To Scoping | D76: Lead→Scope % | E76: PoC Started | F76: Scope→PoC % | G76: Won | H76: PoC→Won % | I76: Lost | J76: Dead (No Resp)
A77: 2025-01 | B77: =COUNTIFS('1. Inbound Leads'!B8:B203,">="&DATE(2025,1,1),'1. Inbound Leads'!B8:B203,"<"&DATE(2025,2,1)) -> 9 | C77: =COUNTIFS('1. Inbound Leads'!AE8:AE203,">="&DATE(2025,1,1),'1. Inbound Leads'!AE8:AE203,"<"&DATE(2025,2,1)) -> 0 | D77: =IFERROR(C77/B77,0) -> 0 | E77: =COUNTIFS('2. Scoping & PoC'!M7:M183,">="&DATE(2025,1,1),'2. Scoping & PoC'!M7:M183,"<"&DATE(2025,2,1)) -> 0 | F77: =IFERROR(E77/C77,0) -> 0 | G77: =COUNTIFS('2. Scoping & PoC'!AH7:AH450,">="&DATE(2025,1,1),'2. Scoping & PoC'!AH7:AH450,"<"&DATE(2025,2,1)) -> 0 | H77: =IFERROR(G77/E77,0) -> 0 | I77: =COUNTIFS('2. Scoping & PoC'!Y7:Y183,"Lost",'2. Scoping & PoC'!E7:E183,">="&DATE(2025,1,1),'2. Scoping & PoC'!E7:E183,"<"&DATE(2025,2,1)) -> 1 | J77: =COUNTIFS('1. Inbound Leads'!AC8:AC203,"Dead — No Response",'1. Inbound Leads'!B8:B203,">="&DATE(2025,1,1),'1. Inbound Leads'!B8:B203,"<"&DATE(2025,2,1)) -> 6
A78: 2025-02 | B78: =COUNTIFS('1. Inbound Leads'!B8:B203,">="&DATE(2025,2,1),'1. Inbound Leads'!B8:B203,"<"&DATE(2025,3,1)) -> 15 | C78: =COUNTIFS('1. Inbound Leads'!AE8:AE203,">="&DATE(2025,2,1),'1. Inbound Leads'!AE8:AE203,"<"&DATE(2025,3,1)) -> 0 | D78: =IFERROR(C78/B78,0) -> 0 | E78: =COUNTIFS('2. Scoping & PoC'!M7:M183,">="&DATE(2025,2,1),'2. Scoping & PoC'!M7:M183,"<"&DATE(2025,3,1)) -> 0 | F78: =IFERROR(E78/C78,0) -> 0 | G78: =COUNTIFS('2. Scoping & PoC'!AH7:AH183,">="&DATE(2025,2,1),'2. Scoping & PoC'!AH7:AH183,"<"&DATE(2025,3,1)) -> 0 | H78: =IFERROR(G78/E78,0) -> 0 | I78: =COUNTIFS('2. Scoping & PoC'!Y7:Y183,"Lost",'2. Scoping & PoC'!E7:E183,">="&DATE(2025,2,1),'2. Scoping & PoC'!E7:E183,"<"&DATE(2025,3,1)) -> 3 | J78: =COUNTIFS('1. Inbound Leads'!AC8:AC203,"Dead — No Response",'1. Inbound Leads'!B8:B203,">="&DATE(2025,2,1),'1. Inbound Leads'!B8:B203,"<"&DATE(2025,3,1)) -> 7
A79: 2025-03 | B79: =COUNTIFS('1. Inbound Leads'!B8:B203,">="&DATE(2025,3,1),'1. Inbound Leads'!B8:B203,"<"&DATE(2025,4,1)) -> 9 | C79: =COUNTIFS('1. Inbound Leads'!AE8:AE203,">="&DATE(2025,3,1),'1. Inbound Leads'!AE8:AE203,"<"&DATE(2025,4,1)) -> 0 | D79: =IFERROR(C79/B79,0) -> 0 | E79: =COUNTIFS('2. Scoping & PoC'!M7:M183,">="&DATE(2025,3,1),'2. Scoping & PoC'!M7:M183,"<"&DATE(2025,4,1)) -> 0 | F79: =IFERROR(E79/C79,0) -> 0 | G79: =COUNTIFS('2. Scoping & PoC'!AH7:AH183,">="&DATE(2025,3,1),'2. Scoping & PoC'!AH7:AH183,"<"&DATE(2025,4,1)) -> 0 | H79: =IFERROR(G79/E79,0) -> 0 | I79: =COUNTIFS('2. Scoping & PoC'!Y7:Y183,"Lost",'2. Scoping & PoC'!E7:E183,">="&DATE(2025,3,1),'2. Scoping & PoC'!E7:E183,"<"&DATE(2025,4,1)) -> 6 | J79: =COUNTIFS('1. Inbound Leads'!AC8:AC203,"Dead — No Response",'1. Inbound Leads'!B8:B203,">="&DATE(2025,3,1),'1. Inbound Leads'!B8:B203,"<"&DATE(2025,4,1)) -> 1
A80: 2025-04 | B80: =COUNTIFS('1. Inbound Leads'!B8:B203,">="&DATE(2025,4,1),'1. Inbound Leads'!B8:B203,"<"&DATE(2025,5,1)) -> 11 | C80: =COUNTIFS('1. Inbound Leads'!AE8:AE203,">="&DATE(2025,4,1),'1. Inbound Leads'!AE8:AE203,"<"&DATE(2025,5,1)) -> 0 | D80: =IFERROR(C80/B80,0) -> 0 | E80: =COUNTIFS('2. Scoping & PoC'!M7:M183,">="&DATE(2025,4,1),'2. Scoping & PoC'!M7:M183,"<"&DATE(2025,5,1)) -> 0 | F80: =IFERROR(E80/C80,0) -> 0 | G80: =COUNTIFS('2. Scoping & PoC'!AH7:AH183,">="&DATE(2025,4,1),'2. Scoping & PoC'!AH7:AH183,"<"&DATE(2025,5,1)) -> 0 | H80: =IFERROR(G80/E80,0) -> 0 | I80: =COUNTIFS('2. Scoping & PoC'!Y7:Y183,"Lost",'2. Scoping & PoC'!E7:E183,">="&DATE(2025,4,1),'2. Scoping & PoC'!E7:E183,"<"&DATE(2025,5,1)) -> 5 | J80: =COUNTIFS('1. Inbound Leads'!AC8:AC203,"Dead — No Response",'1. Inbound Leads'!B8:B203,">="&DATE(2025,4,1),'1. Inbound Leads'!B8:B203,"<"&DATE(2025,5,1)) -> 1
A81: 2025-05 | B81: =COUNTIFS('1. Inbound Leads'!B8:B203,">="&DATE(2025,5,1),'1. Inbound Leads'!B8:B203,"<"&DATE(2025,6,1)) -> 17 | C81: =COUNTIFS('1. Inbound Leads'!AE8:AE203,">="&DATE(2025,5,1),'1. Inbound Leads'!AE8:AE203,"<"&DATE(2025,6,1)) -> 0 | D81: =IFERROR(C81/B81,0) -> 0 | E81: =COUNTIFS('2. Scoping & PoC'!M7:M183,">="&DATE(2025,5,1),'2. Scoping & PoC'!M7:M183,"<"&DATE(2025,6,1)) -> 0 | F81: =IFERROR(E81/C81,0) -> 0 | G81: =COUNTIFS('2. Scoping & PoC'!AH7:AH183,">="&DATE(2025,5,1),'2. Scoping & PoC'!AH7:AH183,"<"&DATE(2025,6,1)) -> 0 | H81: =IFERROR(G81/E81,0) -> 0 | I81: =COUNTIFS('2. Scoping & PoC'!Y7:Y183,"Lost",'2. Scoping & PoC'!E7:E183,">="&DATE(2025,5,1),'2. Scoping & PoC'!E7:E183,"<"&DATE(2025,6,1)) -> 6 | J81: =COUNTIFS('1. Inbound Leads'!AC8:AC203,"Dead — No Response",'1. Inbound Leads'!B8:B203,">="&DATE(2025,5,1),'1. Inbound Leads'!B8:B203,"<"&DATE(2025,6,1)) -> 4
A82: 2025-06 | B82: =COUNTIFS('1. Inbound Leads'!B8:B203,">="&DATE(2025,6,1),'1. Inbound Leads'!B8:B203,"<"&DATE(2025,7,1)) -> 13 | C82: =COUNTIFS('1. Inbound Leads'!AE8:AE203,">="&DATE(2025,6,1),'1. Inbound Leads'!AE8:AE203,"<"&DATE(2025,7,1)) -> 0 | D82: =IFERROR(C82/B82,0) -> 0 | E82: =COUNTIFS('2. Scoping & PoC'!M7:M183,">="&DATE(2025,6,1),'2. Scoping & PoC'!M7:M183,"<"&DATE(2025,7,1)) -> 0 | F82: =IFERROR(E82/C82,0) -> 0 | G82: =COUNTIFS('2. Scoping & PoC'!AH7:AH183,">="&DATE(2025,6,1),'2. Scoping & PoC'!AH7:AH183,"<"&DATE(2025,7,1)) -> 0 | H82: =IFERROR(G82/E82,0) -> 0 | I82: =COUNTIFS('2. Scoping & PoC'!Y7:Y183,"Lost",'2. Scoping & PoC'!E7:E183,">="&DATE(2025,6,1),'2. Scoping & PoC'!E7:E183,"<"&DATE(2025,7,1)) -> 2 | J82: =COUNTIFS('1. Inbound Leads'!AC8:AC203,"Dead — No Response",'1. Inbound Leads'!B8:B203,">="&DATE(2025,6,1),'1. Inbound Leads'!B8:B203,"<"&DATE(2025,7,1)) -> 1
A83: 2025-07 | B83: =COUNTIFS('1. Inbound Leads'!B8:B203,">="&DATE(2025,7,1),'1. Inbound Leads'!B8:B203,"<"&DATE(2025,8,1)) -> 14 | C83: =COUNTIFS('1. Inbound Leads'!AE8:AE203,">="&DATE(2025,7,1),'1. Inbound Leads'!AE8:AE203,"<"&DATE(2025,8,1)) -> 0 | D83: =IFERROR(C83/B83,0) -> 0 | E83: =COUNTIFS('2. Scoping & PoC'!M7:M183,">="&DATE(2025,7,1),'2. Scoping & PoC'!M7:M183,"<"&DATE(2025,8,1)) -> 0 | F83: =IFERROR(E83/C83,0) -> 0 | G83: =COUNTIFS('2. Scoping & PoC'!AH7:AH183,">="&DATE(2025,7,1),'2. Scoping & PoC'!AH7:AH183,"<"&DATE(2025,8,1)) -> 0 | H83: =IFERROR(G83/E83,0) -> 0 | I83: =COUNTIFS('2. Scoping & PoC'!Y7:Y183,"Lost",'2. Scoping & PoC'!E7:E183,">="&DATE(2025,7,1),'2. Scoping & PoC'!E7:E183,"<"&DATE(2025,8,1)) -> 5 | J83: =COUNTIFS('1. Inbound Leads'!AC8:AC203,"Dead — No Response",'1. Inbound Leads'!B8:B203,">="&DATE(2025,7,1),'1. Inbound Leads'!B8:B203,"<"&DATE(2025,8,1)) -> 0
A84: 2025-08 | B84: =COUNTIFS('1. Inbound Leads'!B8:B203,">="&DATE(2025,8,1),'1. Inbound Leads'!B8:B203,"<"&DATE(2025,9,1)) -> 15 | C84: =COUNTIFS('1. Inbound Leads'!AE8:AE203,">="&DATE(2025,8,1),'1. Inbound Leads'!AE8:AE203,"<"&DATE(2025,9,1)) -> 0 | D84: =IFERROR(C84/B84,0) -> 0 | E84: =COUNTIFS('2. Scoping & PoC'!M7:M183,">="&DATE(2025,8,1),'2. Scoping & PoC'!M7:M183,"<"&DATE(2025,9,1)) -> 0 | F84: =IFERROR(E84/C84,0) -> 0 | G84: =COUNTIFS('2. Scoping & PoC'!AH7:AH183,">="&DATE(2025,8,1),'2. Scoping & PoC'!AH7:AH183,"<"&DATE(2025,9,1)) -> 0 | H84: =IFERROR(G84/E84,0) -> 0 | I84: =COUNTIFS('2. Scoping & PoC'!Y7:Y183,"Lost",'2. Scoping & PoC'!E7:E183,">="&DATE(2025,8,1),'2. Scoping & PoC'!E7:E183,"<"&DATE(2025,9,1)) -> 2 | J84: =COUNTIFS('1. Inbound Leads'!AC8:AC203,"Dead — No Response",'1. Inbound Leads'!B8:B203,">="&DATE(2025,8,1),'1. Inbound Leads'!B8:B203,"<"&DATE(2025,9,1)) -> 0
A85: 2025-09 | B85: =COUNTIFS('1. Inbound Leads'!B8:B203,">="&DATE(2025,9,1),'1. Inbound Leads'!B8:B203,"<"&DATE(2025,10,1)) -> 16 | C85: =COUNTIFS('1. Inbound Leads'!AE8:AE203,">="&DATE(2025,9,1),'1. Inbound Leads'!AE8:AE203,"<"&DATE(2025,10,1)) -> 0 | D85: =IFERROR(C85/B85,0) -> 0 | E85: =COUNTIFS('2. Scoping & PoC'!M7:M183,">="&DATE(2025,9,1),'2. Scoping & PoC'!M7:M183,"<"&DATE(2025,10,1)) -> 0 | F85: =IFERROR(E85/C85,0) -> 0 | G85: =COUNTIFS('2. Scoping & PoC'!AH7:AH183,">="&DATE(2025,9,1),'2. Scoping & PoC'!AH7:AH183,"<"&DATE(2025,10,1)) -> 0 | H85: =IFERROR(G85/E85,0) -> 0 | I85: =COUNTIFS('2. Scoping & PoC'!Y7:Y183,"Lost",'2. Scoping & PoC'!E7:E183,">="&DATE(2025,9,1),'2. Scoping & PoC'!E7:E183,"<"&DATE(2025,10,1)) -> 9 | J85: =COUNTIFS('1. Inbound Leads'!AC8:AC203,"Dead — No Response",'1. Inbound Leads'!B8:B203,">="&DATE(2025,9,1),'1. Inbound Leads'!B8:B203,"<"&DATE(2025,10,1)) -> 0
A86: 2025-10 | B86: =COUNTIFS('1. Inbound Leads'!B8:B203,">="&DATE(2025,10,1),'1. Inbound Leads'!B8:B203,"<"&DATE(2025,11,1)) -> 23 | C86: =COUNTIFS('1. Inbound Leads'!AE8:AE203,">="&DATE(2025,10,1),'1. Inbound Leads'!AE8:AE203,"<"&DATE(2025,11,1)) -> 0 | D86: =IFERROR(C86/B86,0) -> 0 | E86: =COUNTIFS('2. Scoping & PoC'!M7:M183,">="&DATE(2025,10,1),'2. Scoping & PoC'!M7:M183,"<"&DATE(2025,11,1)) -> 0 | F86: =IFERROR(E86/C86,0) -> 0 | G86: =COUNTIFS('2. Scoping & PoC'!AH7:AH183,">="&DATE(2025,10,1),'2. Scoping & PoC'!AH7:AH183,"<"&DATE(2025,11,1)) -> 0 | H86: =IFERROR(G86/E86,0) -> 0 | I86: =COUNTIFS('2. Scoping & PoC'!Y7:Y183,"Lost",'2. Scoping & PoC'!E7:E183,">="&DATE(2025,10,1),'2. Scoping & PoC'!E7:E183,"<"&DATE(2025,11,1)) -> 0 | J86: =COUNTIFS('1. Inbound Leads'!AC8:AC203,"Dead — No Response",'1. Inbound Leads'!B8:B203,">="&DATE(2025,10,1),'1. Inbound Leads'!B8:B203,"<"&DATE(2025,11,1)) -> 1
A87: 2025-11 | B87: =COUNTIFS('1. Inbound Leads'!B8:B203,">="&DATE(2025,11,1),'1. Inbound Leads'!B8:B203,"<"&DATE(2025,12,1)) -> 13 | C87: =COUNTIFS('1. Inbound Leads'!AE8:AE203,">="&DATE(2025,11,1),'1. Inbound Leads'!AE8:AE203,"<"&DATE(2025,12,1)) -> 0 | D87: =IFERROR(C87/B87,0) -> 0 | E87: =COUNTIFS('2. Scoping & PoC'!M7:M183,">="&DATE(2025,11,1),'2. Scoping & PoC'!M7:M183,"<"&DATE(2025,12,1)) -> 0 | F87: =IFERROR(E87/C87,0) -> 0 | G87: =COUNTIFS('2. Scoping & PoC'!AH7:AH183,">="&DATE(2025,11,1),'2. Scoping & PoC'!AH7:AH183,"<"&DATE(2025,12,1)) -> 0 | H87: =IFERROR(G87/E87,0) -> 0 | I87: =COUNTIFS('2. Scoping & PoC'!Y7:Y183,"Lost",'2. Scoping & PoC'!E7:E183,">="&DATE(2025,11,1),'2. Scoping & PoC'!E7:E183,"<"&DATE(2025,12,1)) -> 0 | J87: =COUNTIFS('1. Inbound Leads'!AC8:AC203,"Dead — No Response",'1. Inbound Leads'!B8:B203,">="&DATE(2025,11,1),'1. Inbound Leads'!B8:B203,"<"&DATE(2025,12,1)) -> 0
A88: 2025-12 | B88: =COUNTIFS('1. Inbound Leads'!B8:B203,">="&DATE(2025,12,1),'1. Inbound Leads'!B8:B203,"<"&DATE(2026,1,1)) -> 10 | C88: =COUNTIFS('1. Inbound Leads'!AE8:AE203,">="&DATE(2025,12,1),'1. Inbound Leads'!AE8:AE203,"<"&DATE(2026,1,1)) -> 0 | D88: =IFERROR(C88/B88,0) -> 0 | E88: =COUNTIFS('2. Scoping & PoC'!M7:M183,">="&DATE(2025,12,1),'2. Scoping & PoC'!M7:M183,"<"&DATE(2026,1,1)) -> 0 | F88: =IFERROR(E88/C88,0) -> 0 | G88: =COUNTIFS('2. Scoping & PoC'!AH7:AH183,">="&DATE(2025,12,1),'2. Scoping & PoC'!AH7:AH183,"<"&DATE(2026,1,1)) -> 0 | H88: =IFERROR(G88/E88,0) -> 0 | I88: =COUNTIFS('2. Scoping & PoC'!Y7:Y183,"Lost",'2. Scoping & PoC'!E7:E183,">="&DATE(2025,12,1),'2. Scoping & PoC'!E7:E183,"<"&DATE(2026,1,1)) -> 4 | J88: =COUNTIFS('1. Inbound Leads'!AC8:AC203,"Dead — No Response",'1. Inbound Leads'!B8:B203,">="&DATE(2025,12,1),'1. Inbound Leads'!B8:B203,"<"&DATE(2026,1,1)) -> 0
A89: 2026-01 | B89: =COUNTIFS('1. Inbound Leads'!B8:B203,">="&DATE(2026,1,1),'1. Inbound Leads'!B8:B203,"<"&DATE(2026,2,1)) -> 15 | C89: =COUNTIFS('1. Inbound Leads'!AE8:AE450,">="&DATE(2026,1,1),'1. Inbound Leads'!AE8:AE450,"<"&DATE(2026,2,1)) -> 0 | D89: =IFERROR(C89/B89,0) -> 0 | E89: =COUNTIFS('2. Scoping & PoC'!M7:M183,">="&DATE(2026,1,1),'2. Scoping & PoC'!M7:M183,"<"&DATE(2026,2,1)) -> 0 | F89: =IFERROR(E89/C89,0) -> 0 | G89: =COUNTIFS('2. Scoping & PoC'!AH7:AH183,">="&DATE(2026,1,1),'2. Scoping & PoC'!AH7:AH183,"<"&DATE(2026,2,1)) -> 0 | H89: =IFERROR(G89/E89,0) -> 0 | I89: =COUNTIFS('2. Scoping & PoC'!Y7:Y183,"Lost",'2. Scoping & PoC'!E7:E183,">="&DATE(2026,1,1),'2. Scoping & PoC'!E7:E183,"<"&DATE(2026,2,1)) -> 1 | J89: =COUNTIFS('1. Inbound Leads'!AC8:AC203,"Dead — No Response",'1. Inbound Leads'!B8:B203,">="&DATE(2026,1,1),'1. Inbound Leads'!B8:B203,"<"&DATE(2026,2,1)) -> 0
A90: 2026-02 | B90: =COUNTIFS('1. Inbound Leads'!B8:B396,">="&DATE(2026,2,1),'1. Inbound Leads'!B8:B396,"<"&DATE(2026,3,1)) -> 19 | C90: =COUNTIFS('1. Inbound Leads'!AE9:AE451,">="&DATE(2026,1,1),'1. Inbound Leads'!AE9:AE451,"<"&DATE(2026,2,1)) -> 0 | D90: =IFERROR(C90/B90,0) -> 0 | E90: =COUNTIFS('2. Scoping & PoC'!M7:M183,">="&DATE(2026,2,1),'2. Scoping & PoC'!M7:M183,"<"&DATE(2026,3,1)) -> 0 | F90: =IFERROR(E90/C90,0) -> 0 | G90: =COUNTIFS('2. Scoping & PoC'!AH7:AH183,">="&DATE(2026,2,1),'2. Scoping & PoC'!AH7:AH183,"<"&DATE(2026,3,1)) -> 0 | H90: =IFERROR(G90/E90,0) -> 0 | I90: =COUNTIFS('2. Scoping & PoC'!Y7:Y183,"Lost",'2. Scoping & PoC'!E7:E183,">="&DATE(2026,2,1),'2. Scoping & PoC'!E7:E183,"<"&DATE(2026,3,1)) -> 3 | J90: =COUNTIFS('1. Inbound Leads'!AC8:AC203,"Dead — No Response",'1. Inbound Leads'!B8:B203,">="&DATE(2026,2,1),'1. Inbound Leads'!B8:B203,"<"&DATE(2026,3,1)) -> 0
A91: 2026-03 | B91: =COUNTIFS('1. Inbound Leads'!B8:B395,">="&DATE(2026,3,1),'1. Inbound Leads'!B8:B395,"<"&DATE(2026,4,1)) -> 24 | C91: =COUNTIFS('1. Inbound Leads'!AE8:AE951,">="&DATE(2026,3,1),'1. Inbound Leads'!AE8:AE951,"<"&DATE(2026,4,1)) -> 0 | D91: =IFERROR(C91/B91,0) -> 0 | E91: =COUNTIFS('2. Scoping & PoC'!M7:M183,">="&DATE(2026,3,1),'2. Scoping & PoC'!M7:M183,"<"&DATE(2026,4,1)) -> 0 | F91: =IFERROR(E91/C91,0) -> 0 | G91: =COUNTIFS('2. Scoping & PoC'!AH7:AH183,">="&DATE(2026,3,1),'2. Scoping & PoC'!AH7:AH183,"<"&DATE(2026,4,1)) -> 0 | H91: =IFERROR(G91/E91,0) -> 0 | I91: =COUNTIFS('2. Scoping & PoC'!Y7:Y183,"Lost",'2. Scoping & PoC'!E7:E183,">="&DATE(2026,3,1),'2. Scoping & PoC'!E7:E183,"<"&DATE(2026,4,1)) -> 0 | J91: =COUNTIFS('1. Inbound Leads'!AC8:AC203,"Dead — No Response",'1. Inbound Leads'!B8:B203,">="&DATE(2026,3,1),'1. Inbound Leads'!B8:B203,"<"&DATE(2026,4,1)) -> 0
A92: 2026-04 | B92: =COUNTIFS('1. Inbound Leads'!B8:B451,">="&DATE(2026,4,1),'1. Inbound Leads'!B8:B451,"<"&DATE(2026,5,1)) -> 5 | C92: =COUNTIFS('1. Inbound Leads'!AE8:AE951,">="&DATE(2026,4,1),'1. Inbound Leads'!AE8:AE951,"<"&DATE(2026,5,1)) -> 0 | D92: =IFERROR(C92/B92,0) -> 0 | E92: =COUNTIFS('2. Scoping & PoC'!M7:M183,">="&DATE(2026,4,1),'2. Scoping & PoC'!M7:M183,"<"&DATE(2026,5,1)) -> 0 | F92: =IFERROR(E92/C92,0) -> 0 | G92: =COUNTIFS('2. Scoping & PoC'!AH7:AH183,">="&DATE(2026,4,1),'2. Scoping & PoC'!AH7:AH183,"<"&DATE(2026,5,1)) -> 0 | H92: =IFERROR(G92/E92,0) -> 0 | I92: =COUNTIFS('2. Scoping & PoC'!Y7:Y183,"Lost",'2. Scoping & PoC'!E7:E183,">="&DATE(2026,4,1),'2. Scoping & PoC'!E7:E183,"<"&DATE(2026,5,1)) -> 0 | J92: =COUNTIFS('1. Inbound Leads'!AC8:AC203,"Dead — No Response",'1. Inbound Leads'!B8:B203,">="&DATE(2026,4,1),'1. Inbound Leads'!B8:B203,"<"&DATE(2026,5,1)) -> 0
A93: 2026-05 | B93: =COUNTIFS('1. Inbound Leads'!B8:B451,">="&DATE(2026,5,1),'1. Inbound Leads'!B8:B451,"<"&DATE(2026,6,1)) -> 0 | C93: =COUNTIFS('1. Inbound Leads'!AE8:AE203,">="&DATE(2026,5,1),'1. Inbound Leads'!AE8:AE203,"<"&DATE(2026,6,1)) -> 0 | D93: =IFERROR(C93/B93,0) -> 0 | E93: =COUNTIFS('2. Scoping & PoC'!M7:M183,">="&DATE(2026,5,1),'2. Scoping & PoC'!M7:M183,"<"&DATE(2026,6,1)) -> 0 | F93: =IFERROR(E93/C93,0) -> 0 | G93: =COUNTIFS('2. Scoping & PoC'!AH7:AH183,">="&DATE(2026,5,1),'2. Scoping & PoC'!AH7:AH183,"<"&DATE(2026,6,1)) -> 0 | H93: =IFERROR(G93/E93,0) -> 0 | I93: =COUNTIFS('2. Scoping & PoC'!Y7:Y183,"Lost",'2. Scoping & PoC'!E7:E183,">="&DATE(2026,5,1),'2. Scoping & PoC'!E7:E183,"<"&DATE(2026,6,1)) -> 0 | J93: =COUNTIFS('1. Inbound Leads'!AC8:AC203,"Dead — No Response",'1. Inbound Leads'!B8:B203,">="&DATE(2026,5,1),'1. Inbound Leads'!B8:B203,"<"&DATE(2026,6,1)) -> 0
A94: 2026-06 | B94: =COUNTIFS('1. Inbound Leads'!B8:B451,">="&DATE(2026,6,1),'1. Inbound Leads'!B8:B451,"<"&DATE(2026,7,1)) -> 0 | C94: =COUNTIFS('1. Inbound Leads'!AE8:AE203,">="&DATE(2026,6,1),'1. Inbound Leads'!AE8:AE203,"<"&DATE(2026,7,1)) -> 0 | D94: =IFERROR(C94/B94,0) -> 0 | E94: =COUNTIFS('2. Scoping & PoC'!M7:M183,">="&DATE(2026,6,1),'2. Scoping & PoC'!M7:M183,"<"&DATE(2026,7,1)) -> 0 | F94: =IFERROR(E94/C94,0) -> 0 | G94: =COUNTIFS('2. Scoping & PoC'!AH7:AH183,">="&DATE(2026,6,1),'2. Scoping & PoC'!AH7:AH183,"<"&DATE(2026,7,1)) -> 0 | H94: =IFERROR(G94/E94,0) -> 0 | I94: =COUNTIFS('2. Scoping & PoC'!Y7:Y183,"Lost",'2. Scoping & PoC'!E7:E183,">="&DATE(2026,6,1),'2. Scoping & PoC'!E7:E183,"<"&DATE(2026,7,1)) -> 0 | J94: =COUNTIFS('1. Inbound Leads'!AC8:AC203,"Dead — No Response",'1. Inbound Leads'!B8:B203,">="&DATE(2026,6,1),'1. Inbound Leads'!B8:B203,"<"&DATE(2026,7,1)) -> 0
A95: 2026-07 | B95: =COUNTIFS('1. Inbound Leads'!B8:B203,">="&DATE(2026,7,1),'1. Inbound Leads'!B8:B203,"<"&DATE(2026,8,1)) -> 0 | C95: =COUNTIFS('1. Inbound Leads'!AE8:AE203,">="&DATE(2026,7,1),'1. Inbound Leads'!AE8:AE203,"<"&DATE(2026,8,1)) -> 0 | D95: =IFERROR(C95/B95,0) -> 0 | E95: =COUNTIFS('2. Scoping & PoC'!M7:M183,">="&DATE(2026,7,1),'2. Scoping & PoC'!M7:M183,"<"&DATE(2026,8,1)) -> 0 | F95: =IFERROR(E95/C95,0) -> 0 | G95: =COUNTIFS('2. Scoping & PoC'!AH7:AH183,">="&DATE(2026,7,1),'2. Scoping & PoC'!AH7:AH183,"<"&DATE(2026,8,1)) -> 0 | H95: =IFERROR(G95/E95,0) -> 0 | I95: =COUNTIFS('2. Scoping & PoC'!Y7:Y183,"Lost",'2. Scoping & PoC'!E7:E183,">="&DATE(2026,7,1),'2. Scoping & PoC'!E7:E183,"<"&DATE(2026,8,1)) -> 0 | J95: =COUNTIFS('1. Inbound Leads'!AC8:AC203,"Dead — No Response",'1. Inbound Leads'!B8:B203,">="&DATE(2026,7,1),'1. Inbound Leads'!B8:B203,"<"&DATE(2026,8,1)) -> 0
A96: 2026-08 | B96: =COUNTIFS('1. Inbound Leads'!B8:B203,">="&DATE(2026,8,1),'1. Inbound Leads'!B8:B203,"<"&DATE(2026,9,1)) -> 0 | C96: =COUNTIFS('1. Inbound Leads'!AE8:AE203,">="&DATE(2026,8,1),'1. Inbound Leads'!AE8:AE203,"<"&DATE(2026,9,1)) -> 0 | D96: =IFERROR(C96/B96,0) -> 0 | E96: =COUNTIFS('2. Scoping & PoC'!M7:M183,">="&DATE(2026,8,1),'2. Scoping & PoC'!M7:M183,"<"&DATE(2026,9,1)) -> 0 | F96: =IFERROR(E96/C96,0) -> 0 | G96: =COUNTIFS('2. Scoping & PoC'!AH7:AH183,">="&DATE(2026,8,1),'2. Scoping & PoC'!AH7:AH183,"<"&DATE(2026,9,1)) -> 0 | H96: =IFERROR(G96/E96,0) -> 0 | I96: =COUNTIFS('2. Scoping & PoC'!Y7:Y183,"Lost",'2. Scoping & PoC'!E7:E183,">="&DATE(2026,8,1),'2. Scoping & PoC'!E7:E183,"<"&DATE(2026,9,1)) -> 0 | J96: =COUNTIFS('1. Inbound Leads'!AC8:AC203,"Dead — No Response",'1. Inbound Leads'!B8:B203,">="&DATE(2026,8,1),'1. Inbound Leads'!B8:B203,"<"&DATE(2026,9,1)) -> 0
A97: 2026-09 | B97: =COUNTIFS('1. Inbound Leads'!B8:B203,">="&DATE(2026,9,1),'1. Inbound Leads'!B8:B203,"<"&DATE(2026,10,1)) -> 0 | C97: =COUNTIFS('1. Inbound Leads'!AE8:AE203,">="&DATE(2026,9,1),'1. Inbound Leads'!AE8:AE203,"<"&DATE(2026,10,1)) -> 0 | D97: =IFERROR(C97/B97,0) -> 0 | E97: =COUNTIFS('2. Scoping & PoC'!M7:M183,">="&DATE(2026,9,1),'2. Scoping & PoC'!M7:M183,"<"&DATE(2026,10,1)) -> 0 | F97: =IFERROR(E97/C97,0) -> 0 | G97: =COUNTIFS('2. Scoping & PoC'!AH7:AH183,">="&DATE(2026,9,1),'2. Scoping & PoC'!AH7:AH183,"<"&DATE(2026,10,1)) -> 0 | H97: =IFERROR(G97/E97,0) -> 0 | I97: =COUNTIFS('2. Scoping & PoC'!Y7:Y183,"Lost",'2. Scoping & PoC'!E7:E183,">="&DATE(2026,9,1),'2. Scoping & PoC'!E7:E183,"<"&DATE(2026,10,1)) -> 0 | J97: =COUNTIFS('1. Inbound Leads'!AC8:AC203,"Dead — No Response",'1. Inbound Leads'!B8:B203,">="&DATE(2026,9,1),'1. Inbound Leads'!B8:B203,"<"&DATE(2026,10,1)) -> 0
A98: 2026-10 | B98: =COUNTIFS('1. Inbound Leads'!B8:B203,">="&DATE(2026,10,1),'1. Inbound Leads'!B8:B203,"<"&DATE(2026,11,1)) -> 0 | C98: =COUNTIFS('1. Inbound Leads'!AE8:AE203,">="&DATE(2026,10,1),'1. Inbound Leads'!AE8:AE203,"<"&DATE(2026,11,1)) -> 0 | D98: =IFERROR(C98/B98,0) -> 0 | E98: =COUNTIFS('2. Scoping & PoC'!M7:M183,">="&DATE(2026,10,1),'2. Scoping & PoC'!M7:M183,"<"&DATE(2026,11,1)) -> 0 | F98: =IFERROR(E98/C98,0) -> 0 | G98: =COUNTIFS('2. Scoping & PoC'!AH7:AH183,">="&DATE(2026,10,1),'2. Scoping & PoC'!AH7:AH183,"<"&DATE(2026,11,1)) -> 0 | H98: =IFERROR(G98/E98,0) -> 0 | I98: =COUNTIFS('2. Scoping & PoC'!Y7:Y183,"Lost",'2. Scoping & PoC'!E7:E183,">="&DATE(2026,10,1),'2. Scoping & PoC'!E7:E183,"<"&DATE(2026,11,1)) -> 0 | J98: =COUNTIFS('1. Inbound Leads'!AC8:AC203,"Dead — No Response",'1. Inbound Leads'!B8:B203,">="&DATE(2026,10,1),'1. Inbound Leads'!B8:B203,"<"&DATE(2026,11,1)) -> 0
A99: 2026-11 | B99: =COUNTIFS('1. Inbound Leads'!B8:B203,">="&DATE(2026,11,1),'1. Inbound Leads'!B8:B203,"<"&DATE(2026,12,1)) -> 0 | C99: =COUNTIFS('1. Inbound Leads'!AE8:AE203,">="&DATE(2026,11,1),'1. Inbound Leads'!AE8:AE203,"<"&DATE(2026,12,1)) -> 0 | D99: =IFERROR(C99/B99,0) -> 0 | E99: =COUNTIFS('2. Scoping & PoC'!M7:M183,">="&DATE(2026,11,1),'2. Scoping & PoC'!M7:M183,"<"&DATE(2026,12,1)) -> 0 | F99: =IFERROR(E99/C99,0) -> 0 | G99: =COUNTIFS('2. Scoping & PoC'!AH7:AH183,">="&DATE(2026,11,1),'2. Scoping & PoC'!AH7:AH183,"<"&DATE(2026,12,1)) -> 0 | H99: =IFERROR(G99/E99,0) -> 0 | I99: =COUNTIFS('2. Scoping & PoC'!Y7:Y183,"Lost",'2. Scoping & PoC'!E7:E183,">="&DATE(2026,11,1),'2. Scoping & PoC'!E7:E183,"<"&DATE(2026,12,1)) -> 0 | J99: =COUNTIFS('1. Inbound Leads'!AC8:AC203,"Dead — No Response",'1. Inbound Leads'!B8:B203,">="&DATE(2026,11,1),'1. Inbound Leads'!B8:B203,"<"&DATE(2026,12,1)) -> 0
A100: 2026-12 | B100: =COUNTIFS('1. Inbound Leads'!B8:B203,">="&DATE(2026,12,1),'1. Inbound Leads'!B8:B203,"<"&DATE(2027,1,1)) -> 0 | C100: =COUNTIFS('1. Inbound Leads'!AE8:AE203,">="&DATE(2026,12,1),'1. Inbound Leads'!AE8:AE203,"<"&DATE(2027,1,1)) -> 0 | D100: =IFERROR(C100/B100,0) -> 0 | E100: =COUNTIFS('2. Scoping & PoC'!M7:M183,">="&DATE(2026,12,1),'2. Scoping & PoC'!M7:M183,"<"&DATE(2027,1,1)) -> 0 | F100: =IFERROR(E100/C100,0) -> 0 | G100: =COUNTIFS('2. Scoping & PoC'!AH7:AH183,">="&DATE(2026,12,1),'2. Scoping & PoC'!AH7:AH183,"<"&DATE(2027,1,1)) -> 0 | H100: =IFERROR(G100/E100,0) -> 0 | I100: =COUNTIFS('2. Scoping & PoC'!Y7:Y183,"Lost",'2. Scoping & PoC'!E7:E183,">="&DATE(2026,12,1),'2. Scoping & PoC'!E7:E183,"<"&DATE(2027,1,1)) -> 0 | J100: =COUNTIFS('1. Inbound Leads'!AC8:AC203,"Dead — No Response",'1. Inbound Leads'!B8:B203,">="&DATE(2026,12,1),'1. Inbound Leads'!B8:B203,"<"&DATE(2027,1,1)) -> 0
A103: 3 │ CURRENT FUNNEL SNAPSHOT (Leads at Each Stage)
A104: Funnel Stage | B104: Count | C104: % of Total
A105: New Lead | B105: =COUNTIF('1. Inbound Leads'!AC8:AC451,"New Lead") -> 95 | C105: =IFERROR(B105/SUM(B$105:B$116),0) -> 0.33807829
A106: Contacted | B106: =COUNTIF('1. Inbound Leads'!AC8:AC451,"Contacted") -> 27 | C106: =IFERROR(B106/SUM(B$105:B$116),0) -> 0.096085409
A107: Discovery Scheduled | B107: =COUNTIF('1. Inbound Leads'!AC8:AC451,"Discovery Scheduled") -> 1 | C107: =IFERROR(B107/SUM(B$105:B$116),0) -> 0.0035587189
...

Sheet 1. Inbound Leads
A2: All inbound leads are logged here. Fields 1-10 from form. Fields 11-16 after first contact. Fields 17-24 after discovery call. Score auto-calculates. When Stage = "Move to Scoping", copy Lead ID to Pipeline tab.
A3: FROM INBOUND FORM | L3: FIRST TOUCH / TRIAGE | R3: DISCOVERY CALL OUTPUTS | Z3: STAGE GATE & ROUTING | AE3: VELOCITY
A5: Lead ID | B5: Date Received | C5: First Name | D5: Last Name | E5: Phone Number | F5: Email | G5: Company | H5: Role / Title | I5: Country | J5: How They Found Aya | K5: Project Description (from form) | L5: Assigned To | M5: Date First Contacted | N5: Response Status | O5: Business Unit | P5: Service Line | Q5: Partner or Direct | R5: Discovery Call Date | S5: Data Modality | T5: Est. Volume | U5: Budget Range | V5: Timeline / Urgency | W5: Decision Maker? | X5: Industry Vertical | Y5: Discovery Notes | Z5: Lead Score | AA5: Lead Grade | AB5: Discovery Complete? | AC5: Stage | AD5: Outcome / Reason if Lost | AE5: Date Moved to Scoping
A6: Auto: AYA-001 | B6: Auto/Manual | C6: Required | D6: Required | F6: Required | G6: Required | H6: Required | I6: Required | J6: Required | K6: Required | L6: Select team member | M6: Date of 1st email/call | N6: Select status | O6: Data Annotation / AI Solutions | P6: Select service | Q6: Partner / Direct | R6: Date of call | S6: Image/Text/Audio/Video/LiDAR | T6: e.g. 10,000 images | U6: Select range | V6: Select urgency | W6: Yes/No | X6: Select vertical | Y6: Free text notes | Z6: AUTO (0-100) | AA6: AUTO (A-D) | AB6: AUTO flag | AC6: Select stage | AD6: Required if Lost/Dead | AE6: Date or blank
A7: =IF(C7<>"","AYA-"&TEXT(ROW()-5,"000"),"") -> AYA-002 | B7: 37444.931 | C7: Onyekachi | D7: Opara | F7: oparaonyekachi1999@gmail.com | G7: Chibuzor | J7: Google Ads | K7: Play | M7: 37444.931 | N7: No Response | Q7: Direct | Y7: Awaiting feedback - No response | Z7: =IF(C7="","",(IF(OR(P7="Data Annotation",P7="GenAI / LLM Eval",P7="Medical Annotation"),25,IF(OR(P7="AI Consulting",P7="Data Collection"),18,IF(P7<>"",10,0)))+IF(AND(K7<>"",LEN(K7)>50,T7<>""),20,IF(AND(K7<>"",LEN(K7)>20),12,IF(K7<>"",5,0)))+IF(OR(U7="$100k–$500k",U7="$500k+"),20,IF(OR(U7="$25k–$100k"),15,IF(OR(U7="$5k–$25k"),10,IF(U7="$1k–$5k",5,0))))+IF(AND(G7<>"",G7<>"-"),15,IF(G7<>"",8,0))+IF(V7="Immediate (this month)",10,IF(V7="Short-term (1–3 months)",7,IF(V7="Medium (3–6 months)",4,0)))+IF(W7="Yes",10,IF(W7="Unclear",5,0)))) -> 20 | AA7: =IF(Z7="","",IF(Z7>=75,"A",IF(Z7>=50,"B",IF(Z7>=25,"C","D")))) -> D | AB7: =IF(C7="","",IF(AND(R7<>"",S7<>"",U7<>"",V7<>"",W7<>""),"✓ Complete","⚠ MISSING: "&IF(R7="","Call Date, ","")&IF(S7="","Modality, ","")&IF(U7="","Budget, ","")&IF(V7="","Timeline, ","")&IF(W7="","Decision Maker",""))) -> ⚠ MISSING: Call Date, Modality, Budget, Timeline, Decision Maker | AC7: Dead — No Response | AD7: No Response
A8: =IF(C8<>"","AYA-"&TEXT(ROW()-5,"000"),"") -> AYA-003 | B8: 45069 | C8: Emmanuel | D8: Irumva | F8: emmanuelirumva@huzalabs.com | G8: Huzalabs | H8: Lead, Software Projects Management and Acquisition | J8: Website Form | K8: Hello Team, My name is Emmanuel a Lead software project management and the acquisition, and I represent Huzalabs (www.huzalabs.com), a 4IR consultancy firm operating across Rwanda, Kenya, Ethiopia, and the USA. I’m reaching out to explore potential collaboration opportunities with AYA Company in the field of Artificial Intelligence. I will be traveling to Ghana soon and would love to arrange an in-person meeting to discuss how we might work together. At Huzalabs, we’ve delivered large-scale AI a | L8: Seyram | M8: 45069 | N8: Responded — Interested | O8: Data Annotation | Q8: Direct | Y8: Meeting booked via Hachly for Monday, May 26, 2025 at 9:30am GMT | Z8: =IF(C8="","",(IF(OR(P8="Data Annotation",P8="GenAI / LLM Eval",P8="Medical Annotation"),25,IF(OR(P8="AI Consulting",P8="Data Collection"),18,IF(P8<>"",10,0)))+IF(AND(K8<>"",LEN(K8)>50,T8<>""),20,IF(AND(K8<>"",LEN(K8)>20),12,IF(K8<>"",5,0)))+IF(OR(U8="$100k–$500k",U8="$500k+"),20,IF(OR(U8="$25k–$100k"),15,IF(OR(U8="$5k–$25k"),10,IF(U8="$1k–$5k",5,0))))+IF(AND(G8<>"",G8<>"-"),15,IF(G8<>"",8,0))+IF(V8="Immediate (this month)",10,IF(V8="Short-term (1–3 months)",7,IF(V8="Medium (3–6 months)",4,0)))+IF(W8="Yes",10,IF(W8="Unclear",5,0)))) -> 27 | AA8: =IF(Z8="","",IF(Z8>=75,"A",IF(Z8>=50,"B",IF(Z8>=25,"C","D")))) -> C | AB8: =IF(C8="","",IF(AND(R8<>"",S8<>"",U8<>"",V8<>"",W8<>""),"✓ Complete","⚠ MISSING: "&IF(R8="","Call Date, ","")&IF(S8="","Modality, ","")&IF(U8="","Budget, ","")&IF(V8="","Timeline, ","")&IF(W8="","Decision Maker",""))) -> ⚠ MISSING: Call Date, Modality, Budget, Timeline, Decision Maker | AC8: Discovery Complete
A9: =IF(C9<>"","AYA-"&TEXT(ROW()-5,"000"),"") -> AYA-004 | B9: 45101 | C9: Rudraksh | D9: Parmar | F9: rudraksh.parmar@fivesdigital.com | G9: Fives Digital | J9: Referral | K9: Hi Rocco, Rudy here again. Below is a summary of the project and its requirements. We would need you to come back to us with any queries and confirm whether you can support the project as per the outlined needs. In case you can support, we would request you to share your hourly rates for QA resources. ****Project Use case - Behavioral Competency project and to provide a key update.**** The client has emphasized the need for local experts/drivers based in the UK, US, and Germany for the annotatio | L9: Akhil | M9: 45101 | N9: Responded — Interested | O9: Data Annotation | P9: Other Solutions | Q9: Direct | X9: Automotive/AV | Y9: Called Rudy on 24/06 - He was busy and we planeed to reconnect on 25th June. Spoken to Rudy (25/6) - Will share our Questions to Rudy via email. | Z9: =IF(C9="","",(IF(OR(P9="Data Annotation",P9="GenAI / LLM Eval",P9="Medical Annotation"),25,IF(OR(P9="AI Consulting",P9="Data Collection"),18,IF(P9<>"",10,0)))+IF(AND(K9<>"",LEN(K9)>50,T9<>""),20,IF(AND(K9<>"",LEN(K9)>20),12,IF(K9<>"",5,0)))+IF(OR(U9="$100k–$500k",U9="$500k+"),20,IF(OR(U9="$25k–$100k"),15,IF(OR(U9="$5k–$25k"),10,IF(U9="$1k–$5k",5,0))))+IF(AND(G9<>"",G9<>"-"),15,IF(G9<>"",8,0))+IF(V9="Immediate (this month)",10,IF(V9="Short-term (1–3 months)",7,IF(V9="Medium (3–6 months)",4,0)))+IF(W9="Yes",10,IF(W9="Unclear",5,0)))) -> 37 | AA9: =IF(Z9="","",IF(Z9>=75,"A",IF(Z9>=50,"B",IF(Z9>=25,"C","D")))) -> C | AB9: =IF(C9="","",IF(AND(R9<>"",S9<>"",U9<>"",V9<>"",W9<>""),"✓ Complete","⚠ MISSING: "&IF(R9="","Call Date, ","")&IF(S9="","Modality, ","")&IF(U9="","Budget, ","")&IF(V9="","Timeline, ","")&IF(W9="","Decision Maker",""))) -> ⚠ MISSING: Call Date, Modality, Budget, Timeline, Decision Maker | AC9: Contacted
A10: =IF(C10<>"","AYA-"&TEXT(ROW()-5,"000"),"") -> AYA-005 | B10: 45436 | C10: Korede | D10: Bashir | F10: samebashirkorede@gmail.com | G10: People are requesting projects related to product demonstrations and exploring how Aya Grow can assist them. | J10: Website Form | K10: Book A Demo: Interested in reviewing how Aya grow can help me | L10: Other | O10: Data Annotation | P10: CV Annotation | Q10: Direct | Z10: =IF(C10="","",(IF(OR(P10="Data Annotation",P10="GenAI / LLM Eval",P10="Medical Annotation"),25,IF(OR(P10="AI Consulting",P10="Data Collection"),18,IF(P10<>"",10,0)))+IF(AND(K10<>"",LEN(K10)>50,T10<>""),20,IF(AND(K10<>"",LEN(K10)>20),12,IF(K10<>"",5,0)))+IF(OR(U10="$100k–$500k",U10="$500k+"),20,IF(OR(U10="$25k–$100k"),15,IF(OR(U10="$5k–$25k"),10,IF(U10="$1k–$5k",5,0))))+IF(AND(G10<>"",G10<>"-"),15,IF(G10<>"",8,0))+IF(V10="Immediate (this month)",10,IF(V10="Short-term (1–3 months)",7,IF(V10="Medium (3–6 months)",4,0)))+IF(W10="Yes",10,IF(W10="Unclear",5,0)))) -> 37 | AA10: =IF(Z10="","",IF(Z10>=75,"A",IF(Z10>=50,"B",IF(Z10>=25,"C","D")))) -> C | AB10: =IF(C10="","",IF(AND(R10<>"",S10<>"",U10<>"",V10<>"",W10<>""),"✓ Complete","⚠ MISSING: "&IF(R10="","Call Date, ","")&IF(S10="","Modality, ","")&IF(U10="","Budget, ","")&IF(V10="","Timeline, ","")&IF(W10="","Decision Maker",""))) -> ⚠ MISSING: Call Date, Modality, Budget, Timeline, Decision Maker | AC10: New Lead
A11: =IF(C11<>"","AYA-"&TEXT(ROW()-5,"000"),"") -> AYA-006 | B11: 45608 | C11: Abrar | D11: Bilakhiya | F11: abrar@content-whale.com | G11: Content Whale | K11: Live photo collection (images of curved signs, storefronts, logos, documents, posters, etc.), data annotation with labelling (business cards, invoices, flight information, food packaging, etc.): https://docs.google.com/document/d/1mWR6IydQoLnu430JTzUSlbWwbhofHQAo2Cw0BHzCoCs/edit?tab=t.0 | L11: Michael | O11: Data Annotation | P11: Grow Solutions | Q11: Direct | Z11: =IF(C11="","",(IF(OR(P11="Data Annotation",P11="GenAI / LLM Eval",P11="Medical Annotation"),25,IF(OR(P11="AI Consulting",P11="Data Collection"),18,IF(P11<>"",10,0)))+IF(AND(K11<>"",LEN(K11)>50,T11<>""),20,IF(AND(K11<>"",LEN(K11)>20),12,IF(K11<>"",5,0)))+IF(OR(U11="$100k–$500k",U11="$500k+"),20,IF(OR(U11="$25k–$100k"),15,IF(OR(U11="$5k–$25k"),10,IF(U11="$1k–$5k",5,0))))+IF(AND(G11<>"",G11<>"-"),15,IF(G11<>"",8,0))+IF(V11="Immediate (this month)",10,IF(V11="Short-term (1–3 months)",7,IF(V11="Medium (3–6 months)",4,0)))+IF(W11="Yes",10,IF(W11="Unclear",5,0)))) -> 37 | AA11: =IF(Z11="","",IF(Z11>=75,"A",IF(Z11>=50,"B",IF(Z11>=25,"C","D")))) -> C | AB11: =IF(C11="","",IF(AND(R11<>"",S11<>"",U11<>"",V11<>"",W11<>""),"✓ Complete","⚠ MISSING: "&IF(R11="","Call Date, ","")&IF(S11="","Modality, ","")&IF(U11="","Budget, ","")&IF(V11="","Timeline, ","")&IF(W11="","Decision Maker",""))) -> ⚠ MISSING: Call Date, Modality, Budget, Timeline, Decision Maker | AC11: New Lead
A12: =IF(C12<>"","AYA-"&TEXT(ROW()-5,"000"),"") -> AYA-007 | B12: 45608 | C12: Siraj | D12: Damanhouri | F12: Siraj@hopecells.net | G12: HopeCells | K12: Data acquisition (building an AI symptoms checker and a chatbot in Arabic) | L12: Michael | O12: Data Annotation | P12: CV Annotation | Q12: Direct | Z12: =IF(C12="","",(IF(OR(P12="Data Annotation",P12="GenAI / LLM Eval",P12="Medical Annotation"),25,IF(OR(P12="AI Consulting",P12="Data Collection"),18,IF(P12<>"",10,0)))+IF(AND(K12<>"",LEN(K12)>50,T12<>""),20,IF(AND(K12<>"",LEN(K12)>20),12,IF(K12<>"",5,0)))+IF(OR(U12="$100k–$500k",U12="$500k+"),20,IF(OR(U12="$25k–$100k"),15,IF(OR(U12="$5k–$25k"),10,IF(U12="$1k–$5k",5,0))))+IF(AND(G12<>"",G12<>"-"),15,IF(G12<>"",8,0))+IF(V12="Immediate (this month)",10,IF(V12="Short-term (1–3 months)",7,IF(V12="Medium (3–6 months)",4,0)))+IF(W12="Yes",10,IF(W12="Unclear",5,0)))) -> 37 | AA12: =IF(Z12="","",IF(Z12>=75,"A",IF(Z12>=50,"B",IF(Z12>=25,"C","D")))) -> C | AB12: =IF(C12="","",IF(AND(R12<>"",S12<>"",U12<>"",V12<>"",W12<>""),"✓ Complete","⚠ MISSING: "&IF(R12="","Call Date, ","")&IF(S12="","Modality, ","")&IF(U12="","Budget, ","")&IF(V12="","Timeline, ","")&IF(W12="","Decision Maker",""))) -> ⚠ MISSING: Call Date, Modality, Budget, Timeline, Decision Maker | AC12: New Lead
A13: =IF(C13<>"","AYA-"&TEXT(ROW()-5,"000"),"") -> AYA-008 | B13: 45608 | C13: Baffour | D13: Gyawu | F13: baffourthe3rd@gmail.com | K13: Pricing structure for AyaSpeech + availability of API | L13: Olivia | O13: AI Solutions | Q13: Direct | Z13: =IF(C13="","",(IF(OR(P13="Data Annotation",P13="GenAI / LLM Eval",P13="Medical Annotation"),25,IF(OR(P13="AI Consulting",P13="Data Collection"),18,IF(P13<>"",10,0)))+IF(AND(K13<>"",LEN(K13)>50,T13<>""),20,IF(AND(K13<>"",LEN(K13)>20),12,IF(K13<>"",5,0)))+IF(OR(U13="$100k–$500k",U13="$500k+"),20,IF(OR(U13="$25k–$100k"),15,IF(OR(U13="$5k–$25k"),10,IF(U13="$1k–$5k",5,0))))+IF(AND(G13<>"",G13<>"-"),15,IF(G13<>"",8,0))+IF(V13="Immediate (this month)",10,IF(V13="Short-term (1–3 months)",7,IF(V13="Medium (3–6 months)",4,0)))+IF(W13="Yes",10,IF(W13="Unclear",5,0)))) -> 12 | AA13: =IF(Z13="","",IF(Z13>=75,"A",IF(Z13>=50,"B",IF(Z13>=25,"C","D")))) -> D | AB13: =IF(C13="","",IF(AND(R13<>"",S13<>"",U13<>"",V13<>"",W13<>""),"✓ Complete","⚠ MISSING: "&IF(R13="","Call Date, ","")&IF(S13="","Modality, ","")&IF(U13="","Budget, ","")&IF(V13="","Timeline, ","")&IF(W13="","Decision Maker",""))) -> ⚠ MISSING: Call Date, Modality, Budget, Timeline, Decision Maker | AC13: New Lead
A14: =IF(C14<>"","AYA-"&TEXT(ROW()-5,"000"),"") -> AYA-009 | B14: 45615 | C14: Peter | D14: Tokor | F14: peter@phundit.app | G14: Phundit (Peter Tokor) | K14: Fintech startup wanting to leverage AI to build a financial advisor and financial health score - client scheduled meeting for Tue, Nov 19 at 11:30am | L14: Michael | O14: AI Solutions | P14: Speech Solutions | Q14: Direct | Z14: =IF(C14="","",(IF(OR(P14="Data Annotation",P14="GenAI / LLM Eval",P14="Medical Annotation"),25,IF(OR(P14="AI Consulting",P14="Data Collection"),18,IF(P14<>"",10,0)))+IF(AND(K14<>"",LEN(K14)>50,T14<>""),20,IF(AND(K14<>"",LEN(K14)>20),12,IF(K14<>"",5,0)))+IF(OR(U14="$100k–$500k",U14="$500k+"),20,IF(OR(U14="$25k–$100k"),15,IF(OR(U14="$5k–$25k"),10,IF(U14="$1k–$5k",5,0))))+IF(AND(G14<>"",G14<>"-"),15,IF(G14<>"",8,0))+IF(V14="Immediate (this month)",10,IF(V14="Short-term (1–3 months)",7,IF(V14="Medium (3–6 months)",4,0)))+IF(W14="Yes",10,IF(W14="Unclear",5,0)))) -> 37 | AA14: =IF(Z14="","",IF(Z14>=75,"A",IF(Z14>=50,"B",IF(Z14>=25,"C","D")))) -> C | AB14: =IF(C14="","",IF(AND(R14<>"",S14<>"",U14<>"",V14<>"",W14<>""),"✓ Complete","⚠ MISSING: "&IF(R14="","Call Date, ","")&IF(S14="","Modality, ","")&IF(U14="","Budget, ","")&IF(V14="","Timeline, ","")&IF(W14="","Decision Maker",""))) -> ⚠ MISSING: Call Date, Modality, Budget, Timeline, Decision Maker | AC14: New Lead
A15: =IF(C15<>"","AYA-"&TEXT(ROW()-5,"000"),"") -> AYA-010 | B15: 45617.924 | C15: Austine | D15: Mark | F15: austinemark292@gmail.com | G15: Tech company - Austine Mark | J15: Google Ads | K15: Story | M15: 45617.924 | N15: No Response | P15: Other Solutions | Q15: Direct | Y15: Awaiting feedback - No response | Z15: =IF(C15="","",(IF(OR(P15="Data Annotation",P15="GenAI / LLM Eval",P15="Medical Annotation"),25,IF(OR(P15="AI Consulting",P15="Data Collection"),18,IF(P15<>"",10,0)))+IF(AND(K15<>"",LEN(K15)>50,T15<>""),20,IF(AND(K15<>"",LEN(K15)>20),12,IF(K15<>"",5,0)))+IF(OR(U15="$100k–$500k",U15="$500k+"),20,IF(OR(U15="$25k–$100k"),15,IF(OR(U15="$5k–$25k"),10,IF(U15="$1k–$5k",5,0))))+IF(AND(G15<>"",G15<>"-"),15,IF(G15<>"",8,0))+IF(V15="Immediate (this month)",10,IF(V15="Short-term (1–3 months)",7,IF(V15="Medium (3–6 months)",4,0)))+IF(W15="Yes",10,IF(W15="Unclear",5,0)))) -> 30 | AA15: =IF(Z15="","",IF(Z15>=75,"A",IF(Z15>=50,"B",IF(Z15>=25,"C","D")))) -> C | AB15: =IF(C15="","",IF(AND(R15<>"",S15<>"",U15<>"",V15<>"",W15<>""),"✓ Complete","⚠ MISSING: "&IF(R15="","Call Date, ","")&IF(S15="","Modality, ","")&IF(U15="","Budget, ","")&IF(V15="","Timeline, ","")&IF(W15="","Decision Maker",""))) -> ⚠ MISSING: Call Date, Modality, Budget, Timeline, Decision Maker | AC15: Dead — No Response | AD15: No Response
A16: =IF(C16<>"","AYA-"&TEXT(ROW()-5,"000"),"") -> AYA-011 | B16: 45628.296 | C16: Morryna | D16: Sianipar | F16: morrynasianipar@gmail.com | G16: None mo | J16: Google Ads | K16: none | M16: 45628.296 | N16: No Response | Q16: Direct | Y16: Awaiting feedback - No response | Z16: =IF(C16="","",(IF(OR(P16="Data Annotation",P16="GenAI / LLM Eval",P16="Medical Annotation"),25,IF(OR(P16="AI Consulting",P16="Data Collection"),18,IF(P16<>"",10,0)))+IF(AND(K16<>"",LEN(K16)>50,T16<>""),20,IF(AND(K16<>"",LEN(K16)>20),12,IF(K16<>"",5,0)))+IF(OR(U16="$100k–$500k",U16="$500k+"),20,IF(OR(U16="$25k–$100k"),15,IF(OR(U16="$5k–$25k"),10,IF(U16="$1k–$5k",5,0))))+IF(AND(G16<>"",G16<>"-"),15,IF(G16<>"",8,0))+IF(V16="Immediate (this month)",10,IF(V16="Short-term (1–3 months)",7,IF(V16="Medium (3–6 months)",4,0)))+IF(W16="Yes",10,IF(W16="Unclear",5,0)))) -> 20 | AA16: =IF(Z16="","",IF(Z16>=75,"A",IF(Z16>=50,"B",IF(Z16>=25,"C","D")))) -> D | AB16: =IF(C16="","",IF(AND(R16<>"",S16<>"",U16<>"",V16<>"",W16<>""),"✓ Complete","⚠ MISSING: "&IF(R16="","Call Date, ","")&IF(S16="","Modality, ","")&IF(U16="","Budget, ","")&IF(V16="","Timeline, ","")&IF(W16="","Decision Maker",""))) -> ⚠ MISSING: Call Date, Modality, Budget, Timeline, Decision Maker | AC16: Dead — No Response | AD16: No Response
A17: =IF(C17<>"","AYA-"&TEXT(ROW()-5,"000"),"") -> AYA-012 | B17: 45630 | C17: UWAMARIYA | D17: Mediatrice | F17: izeremedia@gmail.com | K17: Free Discovery Session: is to discover essential reason related to geospatial analysis a | L17: Michael | O17: AI Solutions | Q17: Direct | Z17: =IF(C17="","",(IF(OR(P17="Data Annotation",P17="GenAI / LLM Eval",P17="Medical Annotation"),25,IF(OR(P17="AI Consulting",P17="Data Collection"),18,IF(P17<>"",10,0)))+IF(AND(K17<>"",LEN(K17)>50,T17<>""),20,IF(AND(K17<>"",LEN(K17)>20),12,IF(K17<>"",5,0)))+IF(OR(U17="$100k–$500k",U17="$500k+"),20,IF(OR(U17="$25k–$100k"),15,IF(OR(U17="$5k–$25k"),10,IF(U17="$1k–$5k",5,0))))+IF(AND(G17<>"",G17<>"-"),15,IF(G17<>"",8,0))+IF(V17="Immediate (this month)",10,IF(V17="Short-term (1–3 months)",7,IF(V17="Medium (3–6 months)",4,0)))+IF(W17="Yes",10,IF(W17="Unclear",5,0)))) -> 12 | AA17: =IF(Z17="","",IF(Z17>=75,"A",IF(Z17>=50,"B",IF(Z17>=25,"C","D")))) -> D | AB17: =IF(C17="","",IF(AND(R17<>"",S17<>"",U17<>"",V17<>"",W17<>""),"✓ Complete","⚠ MISSING: "&IF(R17="","Call Date, ","")&IF(S17="","Modality, ","")&IF(U17="","Budget, ","")&IF(V17="","Timeline, ","")&IF(W17="","Decision Maker",""))) -> ⚠ MISSING: Call Date, Modality, Budget, Timeline, Decision Maker | AC17: New Lead
A18: =IF(C18<>"","AYA-"&TEXT(ROW()-5,"000"),"") -> AYA-013 | B18: 45644 | C18: Kawya | D18: Jayakody | F18: kawya@orelit.com | G18: Orel IT | K18: Please connect me with someone responsible for partnerships. | L18: Michael | O18: Data Annotation | P18: Other Solutions | Q18: Direct | Z18: =IF(C18="","",(IF(OR(P18="Data Annotation",P18="GenAI / LLM Eval",P18="Medical Annotation"),25,IF(OR(P18="AI Consulting",P18="Data Collection"),18,IF(P18<>"",10,0)))+IF(AND(K18<>"",LEN(K18)>50,T18<>""),20,IF(AND(K18<>"",LEN(K18)>20),12,IF(K18<>"",5,0)))+IF(OR(U18="$100k–$500k",U18="$500k+"),20,IF(OR(U18="$25k–$100k"),15,IF(OR(U18="$5k–$25k"),10,IF(U18="$1k–$5k",5,0))))+IF(AND(G18<>"",G18<>"-"),15,IF(G18<>"",8,0))+IF(V18="Immediate (this month)",10,IF(V18="Short-term (1–3 months)",7,IF(V18="Medium (3–6 months)",4,0)))+IF(W18="Yes",10,IF(W18="Unclear",5,0)))) -> 37 | AA18: =IF(Z18="","",IF(Z18>=75,"A",IF(Z18>=50,"B",IF(Z18>=25,"C","D")))) -> C | AB18: =IF(C18="","",IF(AND(R18<>"",S18<>"",U18<>"",V18<>"",W18<>""),"✓ Complete","⚠ MISSING: "&IF(R18="","Call Date, ","")&IF(S18="","Modality, ","")&IF(U18="","Budget, ","")&IF(V18="","Timeline, ","")&IF(W18="","Decision Maker",""))) -> ⚠ MISSING: Call Date, Modality, Budget, Timeline, Decision Maker | AC18: New Lead
A19: =IF(C19<>"","AYA-"&TEXT(ROW()-5,"000"),"") -> AYA-014 | B19: 45664.612 | C19: Private Hospital | D19: Casablanca | F19: Communication@akdital.ma | G19: Private Hospital Of Casablanca, Aîn Sebaâ. | J19: Google Ads | M19: 45664.612 | N19: No Response | P19: CV Annotation | Q19: Direct | Y19: Awaiting feedback - No response | Z19: =IF(C19="","",(IF(OR(P19="Data Annotation",P19="GenAI / LLM Eval",P19="Medical Annotation"),25,IF(OR(P19="AI Consulting",P19="Data Collection"),18,IF(P19<>"",10,0)))+IF(AND(K19<>"",LEN(K19)>50,T19<>""),20,IF(AND(K19<>"",LEN(K19)>20),12,IF(K19<>"",5,0)))+IF(OR(U19="$100k–$500k",U19="$500k+"),20,IF(OR(U19="$25k–$100k"),15,IF(OR(U19="$5k–$25k"),10,IF(U19="$1k–$5k",5,0))))+IF(AND(G19<>"",G19<>"-"),15,IF(G19<>"",8,0))+IF(V19="Immediate (this month)",10,IF(V19="Short-term (1–3 months)",7,IF(V19="Medium (3–6 months)",4,0)))+IF(W19="Yes",10,IF(W19="Unclear",5,0)))) -> 25 | AA19: =IF(Z19="","",IF(Z19>=75,"A",IF(Z19>=50,"B",IF(Z19>=25,"C","D")))) -> C | AB19: =IF(C19="","",IF(AND(R19<>"",S19<>"",U19<>"",V19<>"",W19<>""),"✓ Complete","⚠ MISSING: "&IF(R19="","Call Date, ","")&IF(S19="","Modality, ","")&IF(U19="","Budget, ","")&IF(V19="","Timeline, ","")&IF(W19="","Decision Maker",""))) -> ⚠ MISSING: Call Date, Modality, Budget, Timeline, Decision Maker | AC19: Dead — No Response | AD19: No Response
A20: =IF(C20<>"","AYA-"&TEXT(ROW()-5,"000"),"") -> AYA-015 | B20: 45666 | C20: Cindy | D20: Abramson | F20: cabramson@lcaconsultancy.com | G20: People are requesting projects related to machine learning data annotation using specific platforms. For AyaData's contact information to direct the RFP, please visit their official website or contact their sales or support team directly through the contact details provided there. | K20: I am assisting a client with their RFP process for a ML data annotation project using their own platform and we would like to invite AyaData to respond. Please provide the contact information where can direct the RFP. | L20: Akhil | M20: 45666 | O20: Data Annotation | Q20: Direct | X20: Automotive/AV | Y20: Reached final selection round with Safely You, but another vendor was chosen. | Z20: =IF(C20="","",(IF(OR(P20="Data Annotation",P20="GenAI / LLM Eval",P20="Medical Annotation"),25,IF(OR(P20="AI Consulting",P20="Data Collection"),18,IF(P20<>"",10,0)))+IF(AND(K20<>"",LEN(K20)>50,T20<>""),20,IF(AND(K20<>"",LEN(K20)>20),12,IF(K20<>"",5,0)))+IF(OR(U20="$100k–$500k",U20="$500k+"),20,IF(OR(U20="$25k–$100k"),15,IF(OR(U20="$5k–$25k"),10,IF(U20="$1k–$5k",5,0))))+IF(AND(G20<>"",G20<>"-"),15,IF(G20<>"",8,0))+IF(V20="Immediate (this month)",10,IF(V20="Short-term (1–3 months)",7,IF(V20="Medium (3–6 months)",4,0)))+IF(W20="Yes",10,IF(W20="Unclear",5,0)))) -> 27 | AA20: =IF(Z20="","",IF(Z20>=75,"A",IF(Z20>=50,"B",IF(Z20>=25,"C","D")))) -> C | AB20: =IF(C20="","",IF(AND(R20<>"",S20<>"",U20<>"",V20<>"",W20<>""),"✓ Complete","⚠ MISSING: "&IF(R20="","Call Date, ","")&IF(S20="","Modality, ","")&IF(U20="","Budget, ","")&IF(V20="","Timeline, ","")&IF(W20="","Decision Maker",""))) -> ⚠ MISSING: Call Date, Modality, Budget, Timeline, Decision Maker | AC20: Dead — Lost to Competitor | AD20: Lost to Competitor
A21: =IF(C21<>"","AYA-"&TEXT(ROW()-5,"000"),"") -> AYA-016 | B21: 45666.235 | C21: Sachin | D21: Kumar | F21: sachin8235kr@gmail.com | G21: Tukan | J21: Google Ads | M21: 45666.235 | N21: No Response | P21: CV Annotation | Q21: Direct | Y21: Awaiting feedback - No response | Z21: =IF(C21="","",(IF(OR(P21="Data Annotation",P21="GenAI / LLM Eval",P21="Medical Annotation"),25,IF(OR(P21="AI Consulting",P21="Data Collection"),18,IF(P21<>"",10,0)))+IF(AND(K21<>"",LEN(K21)>50,T21<>""),20,IF(AND(K21<>"",LEN(K21)>20),12,IF(K21<>"",5,0)))+IF(OR(U21="$100k–$500k",U21="$500k+"),20,IF(OR(U21="$25k–$100k"),15,IF(OR(U21="$5k–$25k"),10,IF(U21="$1k–$5k",5,0))))+IF(AND(G21<>"",G21<>"-"),15,IF(G21<>"",8,0))+IF(V21="Immediate (this month)",10,IF(V21="Short-term (1–3 months)",7,IF(V21="Medium (3–6 months)",4,0)))+IF(W21="Yes",10,IF(W21="Unclear",5,0)))) -> 25 | AA21: =IF(Z21="","",IF(Z21>=75,"A",IF(Z21>=50,"B",IF(Z21>=25,"C","D")))) -> C | AB21: =IF(C21="","",IF(AND(R21<>"",S21<>"",U21<>"",V21<>"",W21<>""),"✓ Complete","⚠ MISSING: "&IF(R21="","Call Date, ","")&IF(S21="","Modality, ","")&IF(U21="","Budget, ","")&IF(V21="","Timeline, ","")&IF(W21="","Decision Maker",""))) -> ⚠ MISSING: Call Date, Modality, Budget, Timeline, Decision Maker | AC21: Dead — No Response | AD21: No Response
A22: =IF(C22<>"","AYA-"&TEXT(ROW()-5,"000"),"") -> AYA-017 | B22: 45669.667 | C22: Stevens | D22: Nolan | F22: 5gt6@packiu.com | G22: Stevens Nolan | J22: Google Ads | M22: 45669.667 | N22: Responded — Not a Fit | Q22: Direct | Y22: Bad Email address/Spam | Z22: =IF(C22="","",(IF(OR(P22="Data Annotation",P22="GenAI / LLM Eval",P22="Medical Annotation"),25,IF(OR(P22="AI Consulting",P22="Data Collection"),18,IF(P22<>"",10,0)))+IF(AND(K22<>"",LEN(K22)>50,T22<>""),20,IF(AND(K22<>"",LEN(K22)>20),12,IF(K22<>"",5,0)))+IF(OR(U22="$100k–$500k",U22="$500k+"),20,IF(OR(U22="$25k–$100k"),15,IF(OR(U22="$5k–$25k"),10,IF(U22="$1k–$5k",5,0))))+IF(AND(G22<>"",G22<>"-"),15,IF(G22<>"",8,0))+IF(V22="Immediate (this month)",10,IF(V22="Short-term (1–3 months)",7,IF(V22="Medium (3–6 months)",4,0)))+IF(W22="Yes",10,IF(W22="Unclear",5,0)))) -> 15 | AA22: =IF(Z22="","",IF(Z22>=75,"A",IF(Z22>=50,"B",IF(Z22>=25,"C","D")))) -> D | AB22: =IF(C22="","",IF(AND(R22<>"",S22<>"",U22<>"",V22<>"",W22<>""),"✓ Complete","⚠ MISSING: "&IF(R22="","Call Date, ","")&IF(S22="","Modality, ","")&IF(U22="","Budget, ","")&IF(V22="","Timeline, ","")&IF(W22="","Decision Maker",""))) -> ⚠ MISSING: Call Date, Modality, Budget, Timeline, Decision Maker | AC22: Dead — Not a Fit | AD22: Spam / Bad Email
A23: =IF(C23<>"","AYA-"&TEXT(ROW()-5,"000"),"") -> AYA-018 | B23: 45670 | C23: Qing | D23: Yang | F23: qing.yang@liangdao.de | G23: I'm unable to access external content, including specific links or messages. Please provide the text or details you need summarized. | K23: Message link: https://chat.google.com/room/AAAAw0s3JqE/kn9IFdVv2u4/kn9IFdVv2u4?cls=10 | L23: Seyram | M23: 45670 | O23: Data Annotation | Q23: Direct | Y23: Partnership Opp - Lost because of Quality Concern and our TPT being the highest | Z23: =IF(C23="","",(IF(OR(P23="Data Annotation",P23="GenAI / LLM Eval",P23="Medical Annotation"),25,IF(OR(P23="AI Consulting",P23="Data Collection"),18,IF(P23<>"",10,0)))+IF(AND(K23<>"",LEN(K23)>50,T23<>""),20,IF(AND(K23<>"",LEN(K23)>20),12,IF(K23<>"",5,0)))+IF(OR(U23="$100k–$500k",U23="$500k+"),20,IF(OR(U23="$25k–$100k"),15,IF(OR(U23="$5k–$25k"),10,IF(U23="$1k–$5k",5,0))))+IF(AND(G23<>"",G23<>"-"),15,IF(G23<>"",8,0))+IF(V23="Immediate (this month)",10,IF(V23="Short-term (1–3 months)",7,IF(V23="Medium (3–6 months)",4,0)))+IF(W23="Yes",10,IF(W23="Unclear",5,0)))) -> 27 | AA23: =IF(Z23="","",IF(Z23>=75,"A",IF(Z23>=50,"B",IF(Z23>=25,"C","D")))) -> C | AB23: =IF(C23="","",IF(AND(R23<>"",S23<>"",U23<>"",V23<>"",W23<>""),"✓ Complete","⚠ MISSING: "&IF(R23="","Call Date, ","")&IF(S23="","Modality, ","")&IF(U23="","Budget, ","")&IF(V23="","Timeline, ","")&IF(W23="","Decision Maker",""))) -> ⚠ MISSING: Call Date, Modality, Budget, Timeline, Decision Maker | AC23: Dead — Lost to Competitor | AD23: Lost to Competitor
A24: =IF(C24<>"","AYA-"&TEXT(ROW()-5,"000"),"") -> AYA-019 | B24: 45670.375 | C24: Henry | D24: Achille | F24: lbsite321@p-store.cc | G24: P Store | J24: Google Ads | M24: 45670.375 | N24: No Response | P24: CV Annotation | Q24: Direct | Y24: Awaiting feedback - No response | Z24: =IF(C24="","",(IF(OR(P24="Data Annotation",P24="GenAI / LLM Eval",P24="Medical Annotation"),25,IF(OR(P24="AI Consulting",P24="Data Collection"),18,IF(P24<>"",10,0)))+IF(AND(K24<>"",LEN(K24)>50,T24<>""),20,IF(AND(K24<>"",LEN(K24)>20),12,IF(K24<>"",5,0)))+IF(OR(U24="$100k–$500k",U24="$500k+"),20,IF(OR(U24="$25k–$100k"),15,IF(OR(U24="$5k–$25k"),10,IF(U24="$1k–$5k",5,0))))+IF(AND(G24<>"",G24<>"-"),15,IF(G24<>"",8,0))+IF(V24="Immediate (this month)",10,IF(V24="Short-term (1–3 months)",7,IF(V24="Medium (3–6 months)",4,0)))+IF(W24="Yes",10,IF(W24="Unclear",5,0)))) -> 25 | AA24: =IF(Z24="","",IF(Z24>=75,"A",IF(Z24>=50,"B",IF(Z24>=25,"C","D")))) -> C | AB24: =IF(C24="","",IF(AND(R24<>"",S24<>"",U24<>"",V24<>"",W24<>""),"✓ Complete","⚠ MISSING: "&IF(R24="","Call Date, ","")&IF(S24="","Modality, ","")&IF(U24="","Budget, ","")&IF(V24="","Timeline, ","")&IF(W24="","Decision Maker",""))) -> ⚠ MISSING: Call Date, Modality, Budget, Timeline, Decision Maker | AC24: Dead — No Response | AD24: No Response
A25: =IF(C25<>"","AYA-"&TEXT(ROW()-5,"000"),"") -> AYA-020 | B25: 45682 | C25: Madhan PM | F25: madhan.p.m.56@gmail.com | G25: People are requesting annotated food image data for an image detection and segmentation project focused on Indian food items. They are inquiring about the availability and cost of existing annotated data, as well as the time and cost for annotating 100-150 food classes with a minimum of 500 images per class. | J25: Search Engine | K25: I am handling a project for a healthcare company and we are working on a image detection and segmentation project for indian based food items. For the above requirement I need annotated food data. Based on this requirement: a) Do you have already annotated data , and what would be the cost? b) If annotating for 100-150 food classes with minimum 500 images for each class, how much time will it take and what would be the cost? | L25: Michael | M25: 45682 | N25: No Response | O25: Data Annotation | P25: Data Collection | Q25: Direct | X25: Healthcare/Medical | Y25: Data Sourcing - Food Data. After 4 follow ups, went quiet on us. | Z25: =IF(C25="","",(IF(OR(P25="Data Annotation",P25="GenAI / LLM Eval",P25="Medical Annotation"),25,IF(OR(P25="AI Consulting",P25="Data Collection"),18,IF(P25<>"",10,0)))+IF(AND(K25<>"",LEN(K25)>50,T25<>""),20,IF(AND(K25<>"",LEN(K25)>20),12,IF(K25<>"",5,0)))+IF(OR(U25="$100k–$500k",U25="$500k+"),20,IF(OR(U25="$25k–$100k"),15,IF(OR(U25="$5k–$25k"),10,IF(U25="$1k–$5k",5,0))))+IF(AND(G25<>"",G25<>"-"),15,IF(G25<>"",8,0))+IF(V25="Immediate (this month)",10,IF(V25="Short-term (1–3 months)",7,IF(V25="Medium (3–6 months)",4,0)))+IF(W25="Yes",10,IF(W25="Unclear",5,0)))) -> 45 | AA25: =IF(Z25="","",IF(Z25>=75,"A",IF(Z25>=50,"B",IF(Z25>=25,"C","D")))) -> C | AB25: =IF(C25="","",IF(AND(R25<>"",S25<>"",U25<>"",V25<>"",W25<>""),"✓ Complete","⚠ MISSING: "&IF(R25="","Call Date, ","")&IF(S25="","Modality, ","")&IF(U25="","Budget, ","")&IF(V25="","Timeline, ","")&IF(W25="","Decision Maker",""))) -> ⚠ MISSING: Call Date, Modality, Budget, Timeline, Decision Maker | AC25: Dead — No Response | AD25: No Response
A26: =IF(C26<>"","AYA-"&TEXT(ROW()-5,"000"),"") -> AYA-021 | B26: 45682 | C26: Andy | D26: Westlake | F26: amwestlake@gmail.com | G26: British Airways | J26: LinkedIn | L26: Michael | M26: 45682 | N26: No Response | O26: Data Annotation | P26: CV Annotation | Q26: Direct | Y26: No Response! | Z26: =IF(C26="","",(IF(OR(P26="Data Annotation",P26="GenAI / LLM Eval",P26="Medical Annotation"),25,IF(OR(P26="AI Consulting",P26="Data Collection"),18,IF(P26<>"",10,0)))+IF(AND(K26<>"",LEN(K26)>50,T26<>""),20,IF(AND(K26<>"",LEN(K26)>20),12,IF(K26<>"",5,0)))+IF(OR(U26="$100k–$500k",U26="$500k+"),20,IF(OR(U26="$25k–$100k"),15,IF(OR(U26="$5k–$25k"),10,IF(U26="$1k–$5k",5,0))))+IF(AND(G26<>"",G26<>"-"),15,IF(G26<>"",8,0))+IF(V26="Immediate (this month)",10,IF(V26="Short-term (1–3 months)",7,IF(V26="Medium (3–6 months)",4,0)))+IF(W26="Yes",10,IF(W26="Unclear",5,0)))) -> 25 | AA26: =IF(Z26="","",IF(Z26>=75,"A",IF(Z26>=50,"B",IF(Z26>=25,"C","D")))) -> C | AB26: =IF(C26="","",IF(AND(R26<>"",S26<>"",U26<>"",V26<>"",W26<>""),"✓ Complete","⚠ MISSING: "&IF(R26="","Call Date, ","")&IF(S26="","Modality, ","")&IF(U26="","Budget, ","")&IF(V26="","Timeline, ","")&IF(W26="","Decision Maker",""))) -> ⚠ MISSING: Call Date, Modality, Budget, Timeline, Decision Maker | AC26: Dead — No Response | AD26: No Response
A27: =IF(C27<>"","AYA-"&TEXT(ROW()-5,"000"),"") -> AYA-022 | B27: 45687.674 | C27: Kevin | D27: Smoot | F27: ksmoot@adhealthcare.com | G27: Advanced Diagnostics Healthcare System | J27: Google Ads | M27: 45687.674 | N27: No Response | Q27: Direct | Y27: Awaiting feedback - No response | Z27: =IF(C27="","",(IF(OR(P27="Data Annotation",P27="GenAI / LLM Eval",P27="Medical Annotation"),25,IF(OR(P27="AI Consulting",P27="Data Collection"),18,IF(P27<>"",10,0)))+IF(AND(K27<>"",LEN(K27)>50,T27<>""),20,IF(AND(K27<>"",LEN(K27)>20),12,IF(K27<>"",5,0)))+IF(OR(U27="$100k–$500k",U27="$500k+"),20,IF(OR(U27="$25k–$100k"),15,IF(OR(U27="$5k–$25k"),10,IF(U27="$1k–$5k",5,0))))+IF(AND(G27<>"",G27<>"-"),15,IF(G27<>"",8,0))+IF(V27="Immediate (this month)",10,IF(V27="Short-term (1–3 months)",7,IF(V27="Medium (3–6 months)",4,0)))+IF(W27="Yes",10,IF(W27="Unclear",5,0)))) -> 15 | AA27: =IF(Z27="","",IF(Z27>=75,"A",IF(Z27>=50,"B",IF(Z27>=25,"C","D")))) -> D | AB27: =IF(C27="","",IF(AND(R27<>"",S27<>"",U27<>"",V27<>"",W27<>""),"✓ Complete","⚠ MISSING: "&IF(R27="","Call Date, ","")&IF(S27="","Modality, ","")&IF(U27="","Budget, ","")&IF(V27="","Timeline, ","")&IF(W27="","Decision Maker",""))) -> ⚠ MISSING: Call Date, Modality, Budget, Timeline, Decision Maker | AC27: Dead — No Response | AD27: No Response
A28: =IF(C28<>"","AYA-"&TEXT(ROW()-5,"000"),"") -> AYA-023 | B28: 45689 | C28: Abdulaziz | F28: alnassar7@hotmail.com | G28: Thakaa Med.ai | J28: LinkedIn | K28: I am currently working on annotating chest x-ray images through segmentation methods. i would like support on providing experts that can annotate these images and segment the findings within these x-rays. my goal is annotating roughly 3000 images with various chest x-ray findings within a 1 month period. I also want to know if you can provide finding-specific datasets for various chest conditions such as consolidation, nodules, pneumothorax etc. I am kindly requesting for the pricing of these se | L28: Michael | M28: 45689 | O28: Data Annotation | P28: Medical AI Annotation | Q28: Direct | X28: Healthcare/Medical | Y28: Data Annotaiton - POC Completed. Client decided to put the project on hold. | Z28: =IF(C28="","",(IF(OR(P28="Data Annotation",P28="GenAI / LLM Eval",P28="Medical Annotation"),25,IF(OR(P28="AI Consulting",P28="Data Collection"),18,IF(P28<>"",10,0)))+IF(AND(K28<>"",LEN(K28)>50,T28<>""),20,IF(AND(K28<>"",LEN(K28)>20),12,IF(K28<>"",5,0)))+IF(OR(U28="$100k–$500k",U28="$500k+"),20,IF(OR(U28="$25k–$100k"),15,IF(OR(U28="$5k–$25k"),10,IF(U28="$1k–$5k",5,0))))+IF(AND(G28<>"",G28<>"-"),15,IF(G28<>"",8,0))+IF(V28="Immediate (this month)",10,IF(V28="Short-term (1–3 months)",7,IF(V28="Medium (3–6 months)",4,0)))+IF(W28="Yes",10,IF(W28="Unclear",5,0)))) -> 37 | AA28: =IF(Z28="","",IF(Z28>=75,"A",IF(Z28>=50,"B",IF(Z28>=25,"C","D")))) -> C | AB28: =IF(C28="","",IF(AND(R28<>"",S28<>"",U28<>"",V28<>"",W28<>""),"✓ Complete","⚠ MISSING: "&IF(R28="","Call Date, ","")&IF(S28="","Modality, ","")&IF(U28="","Budget, ","")&IF(V28="","Timeline, ","")&IF(W28="","Decision Maker",""))) -> ⚠ MISSING: Call Date, Modality, Budget, Timeline, Decision Maker | AC28: Dead — No Budget | AD28: Project on Hold
A29: =IF(C29<>"","AYA-"&TEXT(ROW()-5,"000"),"") -> AYA-024 | B29: 45691.593 | C29: Luminis | D29: Health | F29: info@luminishealth.org | G29: Luminis Health Anne Arundel Medical Center | J29: Google Ads | M29: 45691.593 | N29: Responded — Not a Fit | Q29: Direct | Y29: Bad Email address/Spam | Z29: =IF(C29="","",(IF(OR(P29="Data Annotation",P29="GenAI / LLM Eval",P29="Medical Annotation"),25,IF(OR(P29="AI Consulting",P29="Data Collection"),18,IF(P29<>"",10,0)))+IF(AND(K29<>"",LEN(K29)>50,T29<>""),20,IF(AND(K29<>"",LEN(K29)>20),12,IF(K29<>"",5,0)))+IF(OR(U29="$100k–$500k",U29="$500k+"),20,IF(OR(U29="$25k–$100k"),15,IF(OR(U29="$5k–$25k"),10,IF(U29="$1k–$5k",5,0))))+IF(AND(G29<>"",G29<>"-"),15,IF(G29<>"",8,0))+IF(V29="Immediate (this month)",10,IF(V29="Short-term (1–3 months)",7,IF(V29="Medium (3–6 months)",4,0)))+IF(W29="Yes",10,IF(W29="Unclear",5,0)))) -> 15 | AA29: =IF(Z29="","",IF(Z29>=75,"A",IF(Z29>=50,"B",IF(Z29>=25,"C","D")))) -> D | AB29: =IF(C29="","",IF(AND(R29<>"",S29<>"",U29<>"",V29<>"",W29<>""),"✓ Complete","⚠ MISSING: "&IF(R29="","Call Date, ","")&IF(S29="","Modality, ","")&IF(U29="","Budget, ","")&IF(V29="","Timeline, ","")&IF(W29="","Decision Maker",""))) -> ⚠ MISSING: Call Date, Modality, Budget, Timeline, Decision Maker | AC29: Dead — Not a Fit | AD29: Spam / Bad Email
A30: =IF(C30<>"","AYA-"&TEXT(ROW()-5,"000"),"") -> AYA-025 | B30: 45693.542 | C30: Upper hill | D30: Medical | F30: admin@uhmc.co.ke | G30: Upper hill Medical Center | J30: Google Ads | K30: We are looking at ways to make our data more fluid | M30: 45693.542 | N30: No Response | Q30: Direct | Y30: Awaiting feedback - No response | Z30: =IF(C30="","",(IF(OR(P30="Data Annotation",P30="GenAI / LLM Eval",P30="Medical Annotation"),25,IF(OR(P30="AI Consulting",P30="Data Collection"),18,IF(P30<>"",10,0)))+IF(AND(K30<>"",LEN(K30)>50,T30<>""),20,IF(AND(K30<>"",LEN(K30)>20),12,IF(K30<>"",5,0)))+IF(OR(U30="$100k–$500k",U30="$500k+"),20,IF(OR(U30="$25k–$100k"),15,IF(OR(U30="$5k–$25k"),10,IF(U30="$1k–$5k",5,0))))+IF(AND(G30<>"",G30<>"-"),15,IF(G30<>"",8,0))+IF(V30="Immediate (this month)",10,IF(V30="Short-term (1–3 months)",7,IF(V30="Medium (3–6 months)",4,0)))+IF(W30="Yes",10,IF(W30="Unclear",5,0)))) -> 27 | AA30: =IF(Z30="","",IF(Z30>=75,"A",IF(Z30>=50,"B",IF(Z30>=25,"C","D")))) -> C | AB30: =IF(C30="","",IF(AND(R30<>"",S30<>"",U30<>"",V30<>"",W30<>""),"✓ Complete","⚠ MISSING: "&IF(R30="","Call Date, ","")&IF(S30="","Modality, ","")&IF(U30="","Budget, ","")&IF(V30="","Timeline, ","")&IF(W30="","Decision Maker",""))) -> ⚠ MISSING: Call Date, Modality, Budget, Timeline, Decision Maker | AC30: Dead — No Response | AD30: No Response
A31: =IF(C31<>"","AYA-"&TEXT(ROW()-5,"000"),"") -> AYA-026 | B31: 45694 | C31: Thuy | F31: thuyvt@hikaribpo.com.vn | G31: Hikari BPO Solutions | J31: Cold Outreach | K31: Our company is a Japanese-invested enterprise that located in Danang city, Vietnam. We now process around 20 projects every day. Annually, from January to March, our team can expand to over 250 members. Our client list includes the reputed organizations in Japan, US, UK, China, India, Korea, Vietnam, etc. We not only provide data entry services, but also data annotation, ITO, RPA, and HR services. We are eager to explore how we can work together to achieve mutual success. | L31: Seyram | M31: 45694 | N31: Responded — Not a Fit | O31: Data Annotation | P31: CV Annotation | Q31: Direct | Y31: Not a fit! | Z31: =IF(C31="","",(IF(OR(P31="Data Annotation",P31="GenAI / LLM Eval",P31="Medical Annotation"),25,IF(OR(P31="AI Consulting",P31="Data Collection"),18,IF(P31<>"",10,0)))+IF(AND(K31<>"",LEN(K31)>50,T31<>""),20,IF(AND(K31<>"",LEN(K31)>20),12,IF(K31<>"",5,0)))+IF(OR(U31="$100k–$500k",U31="$500k+"),20,IF(OR(U31="$25k–$100k"),15,IF(OR(U31="$5k–$25k"),10,IF(U31="$1k–$5k",5,0))))+IF(AND(G31<>"",G31<>"-"),15,IF(G31<>"",8,0))+IF(V31="Immediate (this month)",10,IF(V31="Short-term (1–3 months)",7,IF(V31="Medium (3–6 months)",4,0)))+IF(W31="Yes",10,IF(W31="Unclear",5,0)))) -> 37 | AA31: =IF(Z31="","",IF(Z31>=75,"A",IF(Z31>=50,"B",IF(Z31>=25,"C","D")))) -> C | AB31: =IF(C31="","",IF(AND(R31<>"",S31<>"",U31<>"",V31<>"",W31<>""),"✓ Complete","⚠ MISSING: "&IF(R31="","Call Date, ","")&IF(S31="","Modality, ","")&IF(U31="","Budget, ","")&IF(V31="","Timeline, ","")&IF(W31="","Decision Maker",""))) -> ⚠ MISSING: Call Date, Modality, Budget, Timeline, Decision Maker | AC31: Dead — Not a Fit | AD31: Not a Fit
A32: =IF(C32<>"","AYA-"&TEXT(ROW()-5,"000"),"") -> AYA-027 | B32: 45695 | C32: Balram | D32: Dave | F32: balram@cohortdata.com | G32: Cohort Data | J32: LinkedIn | K32: We need OTS audio data collection for 34 different languages. | M32: 45695 | N32: Responded — Not a Fit | O32: Data Annotation | P32: Data Collection | Q32: Direct | X32: Other | Y32: Not a fit! | Z32: =IF(C32="","",(IF(OR(P32="Data Annotation",P32="GenAI / LLM Eval",P32="Medical Annotation"),25,IF(OR(P32="AI Consulting",P32="Data Collection"),18,IF(P32<>"",10,0)))+IF(AND(K32<>"",LEN(K32)>50,T32<>""),20,IF(AND(K32<>"",LEN(K32)>20),12,IF(K32<>"",5,0)))+IF(OR(U32="$100k–$500k",U32="$500k+"),20,IF(OR(U32="$25k–$100k"),15,IF(OR(U32="$5k–$25k"),10,IF(U32="$1k–$5k",5,0))))+IF(AND(G32<>"",G32<>"-"),15,IF(G32<>"",8,0))+IF(V32="Immediate (this month)",10,IF(V32="Short-term (1–3 months)",7,IF(V32="Medium (3–6 months)",4,0)))+IF(W32="Yes",10,IF(W32="Unclear",5,0)))) -> 45 | AA32: =IF(Z32="","",IF(Z32>=75,"A",IF(Z32>=50,"B",IF(Z32>=25,"C","D")))) -> C | AB32: =IF(C32="","",IF(AND(R32<>"",S32<>"",U32<>"",V32<>"",W32<>""),"✓ Complete","⚠ MISSING: "&IF(R32="","Call Date, ","")&IF(S32="","Modality, ","")&IF(U32="","Budget, ","")&IF(V32="","Timeline, ","")&IF(W32="","Decision Maker",""))) -> ⚠ MISSING: Call Date, Modality, Budget, Timeline, Decision Maker | AC32: Dead — Not a Fit | AD32: Not a Fit
A33: =IF(C33<>"","AYA-"&TEXT(ROW()-5,"000"),"") -> AYA-028 | B33: 45695.678 | C33: Prudence | D33: Persson | F33: prudence.persson@manjehealth.com | G33: Manje Health | J33: Google Ads | K33: Tell me more. | M33: 45695.678 | N33: No Response | Q33: Direct | Y33: Awaiting feedback - No response | Z33: =IF(C33="","",(IF(OR(P33="Data Annotation",P33="GenAI / LLM Eval",P33="Medical Annotation"),25,IF(OR(P33="AI Consulting",P33="Data Collection"),18,IF(P33<>"",10,0)))+IF(AND(K33<>"",LEN(K33)>50,T33<>""),20,IF(AND(K33<>"",LEN(K33)>20),12,IF(K33<>"",5,0)))+IF(OR(U33="$100k–$500k",U33="$500k+"),20,IF(OR(U33="$25k–$100k"),15,IF(OR(U33="$5k–$25k"),10,IF(U33="$1k–$5k",5,0))))+IF(AND(G33<>"",G33<>"-"),15,IF(G33<>"",8,0))+IF(V33="Immediate (this month)",10,IF(V33="Short-term (1–3 months)",7,IF(V33="Medium (3–6 months)",4,0)))+IF(W33="Yes",10,IF(W33="Unclear",5,0)))) -> 20 | AA33: =IF(Z33="","",IF(Z33>=75,"A",IF(Z33>=50,"B",IF(Z33>=25,"C","D")))) -> D | AB33: =IF(C33="","",IF(AND(R33<>"",S33<>"",U33<>"",V33<>"",W33<>""),"✓ Complete","⚠ MISSING: "&IF(R33="","Call Date, ","")&IF(S33="","Modality, ","")&IF(U33="","Budget, ","")&IF(V33="","Timeline, ","")&IF(W33="","Decision Maker",""))) -> ⚠ MISSING: Call Date, Modality, Budget, Timeline, Decision Maker | AC33: Dead — No Response | AD33: No Response
A34: =IF(C34<>"","AYA-"&TEXT(ROW()-5,"000"),"") -> AYA-029 | B34: 45698 | C34: Mayukh | D34: Kundu | F34: mayukh@quantigo.ai | G34: Quantigo | J34: Search Engine | K34: We are interested in collaborating with you on our current and upcoming projects in the areas of GenAI, LLM, NLP, data collection, transcription, and translation. To help us handle some of the prestigious projects, we are searching for a reliable partner. Additionally, I sent an email with the information and requested you to complete the Google form in order to obtain all the necessary information. After you submit the Google Form, our concerned team will review it and take the necessary action | L34: Seyram | M34: 45698 | N34: Responded — Interested | O34: Data Annotation | P34: Medical AI Annotation | Q34: Direct | Y34: Signed an NDA - Partnership Opp for GenAI projects | Z34: =IF(C34="","",(IF(OR(P34="Data Annotation",P34="GenAI / LLM Eval",P34="Medical Annotation"),25,IF(OR(P34="AI Consulting",P34="Data Collection"),18,IF(P34<>"",10,0)))+IF(AND(K34<>"",LEN(K34)>50,T34<>""),20,IF(AND(K34<>"",LEN(K34)>20),12,IF(K34<>"",5,0)))+IF(OR(U34="$100k–$500k",U34="$500k+"),20,IF(OR(U34="$25k–$100k"),15,IF(OR(U34="$5k–$25k"),10,IF(U34="$1k–$5k",5,0))))+IF(AND(G34<>"",G34<>"-"),15,IF(G34<>"",8,0))+IF(V34="Immediate (this month)",10,IF(V34="Short-term (1–3 months)",7,IF(V34="Medium (3–6 months)",4,0)))+IF(W34="Yes",10,IF(W34="Unclear",5,0)))) -> 37 | AA34: =IF(Z34="","",IF(Z34>=75,"A",IF(Z34>=50,"B",IF(Z34>=25,"C","D")))) -> C | AB34: =IF(C34="","",IF(AND(R34<>"",S34<>"",U34<>"",V34<>"",W34<>""),"✓ Complete","⚠ MISSING: "&IF(R34="","Call Date, ","")&IF(S34="","Modality, ","")&IF(U34="","Budget, ","")&IF(V34="","Timeline, ","")&IF(W34="","Decision Maker",""))) -> ⚠ MISSING: Call Date, Modality, Budget, Timeline, Decision Maker | AC34: Move to Scoping
A35: =IF(C35<>"","AYA-"&TEXT(ROW()-5,"000"),"") -> AYA-030 | B35: 45698 | C35: Liesbet | D35: Conings | F35: liesbet.conings@xenomatix.com | G35: Xenomatix | J35: Search Engine | K35: We are a Belgium based lidar company (www.xenomatix.com). We are in search of a data annotation company to help us progress our AI applications. Our AI application is taillored to detecting cracks in road pavements. I am interested to understand your data annotation services and how they can support us in accelerating our development. Best regards, Liesbet, Dir of Engineering | L35: Michael | M35: 45698 | N35: No Response | O35: Data Annotation | P35: Other Solutions | Q35: Direct | X35: Automotive/AV | Y35: Good Fit! 4 Follow Ups - Went Quiet! | Z35: =IF(C35="","",(IF(OR(P35="Data Annotation",P35="GenAI / LLM Eval",P35="Medical Annotation"),25,IF(OR(P35="AI Consulting",P35="Data Collection"),18,IF(P35<>"",10,0)))+IF(AND(K35<>"",LEN(K35)>50,T35<>""),20,IF(AND(K35<>"",LEN(K35)>20),12,IF(K35<>"",5,0)))+IF(OR(U35="$100k–$500k",U35="$500k+"),20,IF(OR(U35="$25k–$100k"),15,IF(OR(U35="$5k–$25k"),10,IF(U35="$1k–$5k",5,0))))+IF(AND(G35<>"",G35<>"-"),15,IF(G35<>"",8,0))+IF(V35="Immediate (this month)",10,IF(V35="Short-term (1–3 months)",7,IF(V35="Medium (3–6 months)",4,0)))+IF(W35="Yes",10,IF(W35="Unclear",5,0)))) -> 37 | AA35: =IF(Z35="","",IF(Z35>=75,"A",IF(Z35>=50,"B",IF(Z35>=25,"C","D")))) -> C | AB35: =IF(C35="","",IF(AND(R35<>"",S35<>"",U35<>"",V35<>"",W35<>""),"✓ Complete","⚠ MISSING: "&IF(R35="","Call Date, ","")&IF(S35="","Modality, ","")&IF(U35="","Budget, ","")&IF(V35="","Timeline, ","")&IF(W35="","Decision Maker",""))) -> ⚠ MISSING: Call Date, Modality, Budget, Timeline, Decision Maker | AC35: Dead — No Response | AD35: No Response
A36: =IF(C36<>"","AYA-"&TEXT(ROW()-5,"000"),"") -> AYA-031 | B36: 45698.486 | C36: Hetka | D36: Adrien | F36: hetka@foxnew.info | G36: FOX News | J36: Google Ads | M36: 45698.486 | N36: No Response | P36: Speech Solutions | Q36: Direct | Y36: Awaiting feedback - No response | Z36: =IF(C36="","",(IF(OR(P36="Data Annotation",P36="GenAI / LLM Eval",P36="Medical Annotation"),25,IF(OR(P36="AI Consulting",P36="Data Collection"),18,IF(P36<>"",10,0)))+IF(AND(K36<>"",LEN(K36)>50,T36<>""),20,IF(AND(K36<>"",LEN(K36)>20),12,IF(K36<>"",5,0)))+IF(OR(U36="$100k–$500k",U36="$500k+"),20,IF(OR(U36="$25k–$100k"),15,IF(OR(U36="$5k–$25k"),10,IF(U36="$1k–$5k",5,0))))+IF(AND(G36<>"",G36<>"-"),15,IF(G36<>"",8,0))+IF(V36="Immediate (this month)",10,IF(V36="Short-term (1–3 months)",7,IF(V36="Medium (3–6 months)",4,0)))+IF(W36="Yes",10,IF(W36="Unclear",5,0)))) -> 25 | AA36: =IF(Z36="","",IF(Z36>=75,"A",IF(Z36>=50,"B",IF(Z36>=25,"C","D")))) -> C | AB36: =IF(C36="","",IF(AND(R36<>"",S36<>"",U36<>"",V36<>"",W36<>""),"✓ Complete","⚠ MISSING: "&IF(R36="","Call Date, ","")&IF(S36="","Modality, ","")&IF(U36="","Budget, ","")&IF(V36="","Timeline, ","")&IF(W36="","Decision Maker",""))) -> ⚠ MISSING: Call Date, Modality, Budget, Timeline, Decision Maker | AC36: Dead — No Response | AD36: No Response
A37: =IF(C37<>"","AYA-"&TEXT(ROW()-5,"000"),"") -> AYA-032 | B37: 45699.423 | C37: Chapel | D37: Medical | F37: chapelmpooh.berks@nhs.net | G37: The Chapel Medical Centre | J37: Google Ads | M37: 45699.423 | N37: No Response | P37: Other Solutions | Q37: Direct | Y37: Awaiting feedback - No response | Z37: =IF(C37="","",(IF(OR(P37="Data Annotation",P37="GenAI / LLM Eval",P37="Medical Annotation"),25,IF(OR(P37="AI Consulting",P37="Data Collection"),18,IF(P37<>"",10,0)))+IF(AND(K37<>"",LEN(K37)>50,T37<>""),20,IF(AND(K37<>"",LEN(K37)>20),12,IF(K37<>"",5,0)))+IF(OR(U37="$100k–$500k",U37="$500k+"),20,IF(OR(U37="$25k–$100k"),15,IF(OR(U37="$5k–$25k"),10,IF(U37="$1k–$5k",5,0))))+IF(AND(G37<>"",G37<>"-"),15,IF(G37<>"",8,0))+IF(V37="Immediate (this month)",10,IF(V37="Short-term (1–3 months)",7,IF(V37="Medium (3–6 months)",4,0)))+IF(W37="Yes",10,IF(W37="Unclear",5,0)))) -> 25 | AA37: =IF(Z37="","",IF(Z37>=75,"A",IF(Z37>=50,"B",IF(Z37>=25,"C","D")))) -> C | AB37: =IF(C37="","",IF(AND(R37<>"",S37<>"",U37<>"",V37<>"",W37<>""),"✓ Complete","⚠ MISSING: "&IF(R37="","Call Date, ","")&IF(S37="","Modality, ","")&IF(U37="","Budget, ","")&IF(V37="","Timeline, ","")&IF(W37="","Decision Maker",""))) -> ⚠ MISSING: Call Date, Modality, Budget, Timeline, Decision Maker | AC37: Dead — No Response | AD37: No Response
A38: =IF(C38<>"","AYA-"&TEXT(ROW()-5,"000"),"") -> AYA-033 | B38: 45700 | C38: Mahir | D38: Shariyer | F38: mahirshariyer03@gmail.com | G38: Quantum Label AI | J38: LinkedIn | K38: we are interested to collaborate with Aya Data's team | L38: Seyram | M38: 45700 | N38: No Response | O38: Data Annotation | P38: LiDAR Annotation | Q38: Direct | Y38: No Update! | Z38: =IF(C38="","",(IF(OR(P38="Data Annotation",P38="GenAI / LLM Eval",P38="Medical Annotation"),25,IF(OR(P38="AI Consulting",P38="Data Collection"),18,IF(P38<>"",10,0)))+IF(AND(K38<>"",LEN(K38)>50,T38<>""),20,IF(AND(K38<>"",LEN(K38)>20),12,IF(K38<>"",5,0)))+IF(OR(U38="$100k–$500k",U38="$500k+"),20,IF(OR(U38="$25k–$100k"),15,IF(OR(U38="$5k–$25k"),10,IF(U38="$1k–$5k",5,0))))+IF(AND(G38<>"",G38<>"-"),15,IF(G38<>"",8,0))+IF(V38="Immediate (this month)",10,IF(V38="Short-term (1–3 months)",7,IF(V38="Medium (3–6 months)",4,0)))+IF(W38="Yes",10,IF(W38="Unclear",5,0)))) -> 37 | AA38: =IF(Z38="","",IF(Z38>=75,"A",IF(Z38>=50,"B",IF(Z38>=25,"C","D")))) -> C | AB38: =IF(C38="","",IF(AND(R38<>"",S38<>"",U38<>"",V38<>"",W38<>""),"✓ Complete","⚠ MISSING: "&IF(R38="","Call Date, ","")&IF(S38="","Modality, ","")&IF(U38="","Budget, ","")&IF(V38="","Timeline, ","")&IF(W38="","Decision Maker",""))) -> ⚠ MISSING: Call Date, Modality, Budget, Timeline, Decision Maker | AC38: Dead — No Response | AD38: No Response
A39: =IF(C39<>"","AYA-"&TEXT(ROW()-5,"000"),"") -> AYA-034 | B39: 45708 | C39: Rachel | D39: Kim | F39: dahyun.kim@flitto.com | G39: Flitto | J39: Search Engine | K39: We are reaching out to you about an opportunity to participate in our new project: Voice Recording Project. This task involves recording of daily utterances in a specific language and providing the corresponding transcript for each utterance. [full description in marketing chat] | L39: Akhil | M39: 45708 | N39: Responded — Not a Fit | O39: Data Annotation | P39: Medical AI Annotation | Q39: Direct | X39: Other | Y39: Not a fit! 20 Odd languages! | Z39: =IF(C39="","",(IF(OR(P39="Data Annotation",P39="GenAI / LLM Eval",P39="Medical Annotation"),25,IF(OR(P39="AI Consulting",P39="Data Collection"),18,IF(P39<>"",10,0)))+IF(AND(K39<>"",LEN(K39)>50,T39<>""),20,IF(AND(K39<>"",LEN(K39)>20),12,IF(K39<>"",5,0)))+IF(OR(U39="$100k–$500k",U39="$500k+"),20,IF(OR(U39="$25k–$100k"),15,IF(OR(U39="$5k–$25k"),10,IF(U39="$1k–$5k",5,0))))+IF(AND(G39<>"",G39<>"-"),15,IF(G39<>"",8,0))+IF(V39="Immediate (this month)",10,IF(V39="Short-term (1–3 months)",7,IF(V39="Medium (3–6 months)",4,0)))+IF(W39="Yes",10,IF(W39="Unclear",5,0)))) -> 37 | AA39: =IF(Z39="","",IF(Z39>=75,"A",IF(Z39>=50,"B",IF(Z39>=25,"C","D")))) -> C | AB39: =IF(C39="","",IF(AND(R39<>"",S39<>"",U39<>"",V39<>"",W39<>""),"✓ Complete","⚠ MISSING: "&IF(R39="","Call Date, ","")&IF(S39="","Modality, ","")&IF(U39="","Budget, ","")&IF(V39="","Timeline, ","")&IF(W39="","Decision Maker",""))) -> ⚠ MISSING: Call Date, Modality, Budget, Timeline, Decision Maker | AC39: Dead — Not a Fit | AD39: Not a Fit
A40: =IF(C40<>"","AYA-"&TEXT(ROW()-5,"000"),"") -> AYA-035 | B40: 45708.476 | C40: University | D40: Hospital | F40: marketing@uhnj.org | G40: University Hospital | J40: Google Ads | M40: 45708.476 | N40: No Response | P40: LiDAR Annotation | Q40: Direct | Y40: Awaiting feedback - No response | Z40: =IF(C40="","",(IF(OR(P40="Data Annotation",P40="GenAI / LLM Eval",P40="Medical Annotation"),25,IF(OR(P40="AI Consulting",P40="Data Collection"),18,IF(P40<>"",10,0)))+IF(AND(K40<>"",LEN(K40)>50,T40<>""),20,IF(AND(K40<>"",LEN(K40)>20),12,IF(K40<>"",5,0)))+IF(OR(U40="$100k–$500k",U40="$500k+"),20,IF(OR(U40="$25k–$100k"),15,IF(OR(U40="$5k–$25k"),10,IF(U40="$1k–$5k",5,0))))+IF(AND(G40<>"",G40<>"-"),15,IF(G40<>"",8,0))+IF(V40="Immediate (this month)",10,IF(V40="Short-term (1–3 months)",7,IF(V40="Medium (3–6 months)",4,0)))+IF(W40="Yes",10,IF(W40="Unclear",5,0)))) -> 25 | AA40: =IF(Z40="","",IF(Z40>=75,"A",IF(Z40>=50,"B",IF(Z40>=25,"C","D")))) -> C | AB40: =IF(C40="","",IF(AND(R40<>"",S40<>"",U40<>"",V40<>"",W40<>""),"✓ Complete","⚠ MISSING: "&IF(R40="","Call Date, ","")&IF(S40="","Modality, ","")&IF(U40="","Budget, ","")&IF(V40="","Timeline, ","")&IF(W40="","Decision Maker",""))) -> ⚠ MISSING: Call Date, Modality, Budget, Timeline, Decision Maker | AC40: Dead — No Response | AD40: No Response
A41: =IF(C41<>"","AYA-"&TEXT(ROW()-5,"000"),"") -> AYA-036 | B41: 45709 | C41: Sofia | D41: Ovejero | F41: sofia.ovejero@dedalus.com | G41: Dedalus | J41: Search Engine | K41: I am writing to request a quote for clinical labelling/data annotation project support based on the following requirements [see Marketing chat for more details] | L41: Akhil | M41: 45709 | O41: Data Annotation | Q41: Direct | X41: Healthcare/Medical | Y41: Client put the project on hold! | Z41: =IF(C41="","",(IF(OR(P41="Data Annotation",P41="GenAI / LLM Eval",P41="Medical Annotation"),25,IF(OR(P41="AI Consulting",P41="Data Collection"),18,IF(P41<>"",10,0)))+IF(AND(K41<>"",LEN(K41)>50,T41<>""),20,IF(AND(K41<>"",LEN(K41)>20),12,IF(K41<>"",5,0)))+IF(OR(U41="$100k–$500k",U41="$500k+"),20,IF(OR(U41="$25k–$100k"),15,IF(OR(U41="$5k–$25k"),10,IF(U41="$1k–$5k",5,0))))+IF(AND(G41<>"",G41<>"-"),15,IF(G41<>"",8,0))+IF(V41="Immediate (this month)",10,IF(V41="Short-term (1–3 months)",7,IF(V41="Medium (3–6 months)",4,0)))+IF(W41="Yes",10,IF(W41="Unclear",5,0)))) -> 27 | AA41: =IF(Z41="","",IF(Z41>=75,"A",IF(Z41>=50,"B",IF(Z41>=25,"C","D")))) -> C | AB41: =IF(C41="","",IF(AND(R41<>"",S41<>"",U41<>"",V41<>"",W41<>""),"✓ Complete","⚠ MISSING: "&IF(R41="","Call Date, ","")&IF(S41="","Modality, ","")&IF(U41="","Budget, ","")&IF(V41="","Timeline, ","")&IF(W41="","Decision Maker",""))) -> ⚠ MISSING: Call Date, Modality, Budget, Timeline, Decision Maker | AC41: Dead — No Budget | AD41: Project on Hold
A42: =IF(C42<>"","AYA-"&TEXT(ROW()-5,"000"),"") -> AYA-037 | B42: 45716 | C42: Mohamed | D42: Unais | F42: reintenspark@gmail.com | G42: Reintenspark Technology | H42: CEO | J42: Cold Outreach | K42: At Reintenspark Technology, we offer a comprehensive range of products and services, including Data Annotation,Data capturing ,Labeling, AI models | L42: Seyram | M42: 45716 | N42: Responded — Not a Fit | O42: Data Annotation | P42: GenAI Annotation | Q42: Direct | Y42: Not a fit! | Z42: =IF(C42="","",(IF(OR(P42="Data Annotation",P42="GenAI / LLM Eval",P42="Medical Annotation"),25,IF(OR(P42="AI Consulting",P42="Data Collection"),18,IF(P42<>"",10,0)))+IF(AND(K42<>"",LEN(K42)>50,T42<>""),20,IF(AND(K42<>"",LEN(K42)>20),12,IF(K42<>"",5,0)))+IF(OR(U42="$100k–$500k",U42="$500k+"),20,IF(OR(U42="$25k–$100k"),15,IF(OR(U42="$5k–$25k"),10,IF(U42="$1k–$5k",5,0))))+IF(AND(G42<>"",G42<>"-"),15,IF(G42<>"",8,0))+IF(V42="Immediate (this month)",10,IF(V42="Short-term (1–3 months)",7,IF(V42="Medium (3–6 months)",4,0)))+IF(W42="Yes",10,IF(W42="Unclear",5,0)))) -> 37 | AA42: =IF(Z42="","",IF(Z42>=75,"A",IF(Z42>=50,"B",IF(Z42>=25,"C","D")))) -> C | AB42: =IF(C42="","",IF(AND(R42<>"",S42<>"",U42<>"",V42<>"",W42<>""),"✓ Complete","⚠ MISSING: "&IF(R42="","Call Date, ","")&IF(S42="","Modality, ","")&IF(U42="","Budget, ","")&IF(V42="","Timeline, ","")&IF(W42="","Decision Maker",""))) -> ⚠ MISSING: Call Date, Modality, Budget, Timeline, Decision Maker | AC42: Dead — Not a Fit | AD42: Not a Fit
A43: =IF(C43<>"","AYA-"&TEXT(ROW()-5,"000"),"") -> AYA-038 | B43: 45720 | C43: Tamanna | D43: Chatterjee | F43: tamanna.chatterjee@pripton.com | G43: Pripton Innovations | J43: Cold Outreach | K43: Partnership opportunities for annotation, STT, etc | L43: Seyram | M43: 45720 | N43: Responded — Not a Fit | O43: Data Annotation | Q43: Direct | Y43: Not a fit! | Z43: =IF(C43="","",(IF(OR(P43="Data Annotation",P43="GenAI / LLM Eval",P43="Medical Annotation"),25,IF(OR(P43="AI Consulting",P43="Data Collection"),18,IF(P43<>"",10,0)))+IF(AND(K43<>"",LEN(K43)>50,T43<>""),20,IF(AND(K43<>"",LEN(K43)>20),12,IF(K43<>"",5,0)))+IF(OR(U43="$100k–$500k",U43="$500k+"),20,IF(OR(U43="$25k–$100k"),15,IF(OR(U43="$5k–$25k"),10,IF(U43="$1k–$5k",5,0))))+IF(AND(G43<>"",G43<>"-"),15,IF(G43<>"",8,0))+IF(V43="Immediate (this month)",10,IF(V43="Short-term (1–3 months)",7,IF(V43="Medium (3–6 months)",4,0)))+IF(W43="Yes",10,IF(W43="Unclear",5,0)))) -> 27 | AA43: =IF(Z43="","",IF(Z43>=75,"A",IF(Z43>=50,"B",IF(Z43>=25,"C","D")))) -> C | AB43: =IF(C43="","",IF(AND(R43<>"",S43<>"",U43<>"",V43<>"",W43<>""),"✓ Complete","⚠ MISSING: "&IF(R43="","Call Date, ","")&IF(S43="","Modality, ","")&IF(U43="","Budget, ","")&IF(V43="","Timeline, ","")&IF(W43="","Decision Maker",""))) -> ⚠ MISSING: Call Date, Modality, Budget, Timeline, Decision Maker | AC43: Dead — Not a Fit | AD43: Not a Fit
A44: =IF(C44<>"","AYA-"&TEXT(ROW()-5,"000"),"") -> AYA-039 | B44: 45723 | C44: Asiedua | D44: Amoah | F44: asiedua.amoah@tomorrownow.org | G44: TomorrowNow | H44: CEO | J44: Referral | K44: Partnership on Climate Tech and bringing to Ghana | O44: Data Annotation | P44: Other Solutions | Q44: Direct | Z44: =IF(C44="","",(IF(OR(P44="Data Annotation",P44="GenAI / LLM Eval",P44="Medical Annotation"),25,IF(OR(P44="AI Consulting",P44="Data Collection"),18,IF(P44<>"",10,0)))+IF(AND(K44<>"",LEN(K44)>50,T44<>""),20,IF(AND(K44<>"",LEN(K44)>20),12,IF(K44<>"",5,0)))+IF(OR(U44="$100k–$500k",U44="$500k+"),20,IF(OR(U44="$25k–$100k"),15,IF(OR(U44="$5k–$25k"),10,IF(U44="$1k–$5k",5,0))))+IF(AND(G44<>"",G44<>"-"),15,IF(G44<>"",8,0))+IF(V44="Immediate (this month)",10,IF(V44="Short-term (1–3 months)",7,IF(V44="Medium (3–6 months)",4,0)))+IF(W44="Yes",10,IF(W44="Unclear",5,0)))) -> 37 | AA44: =IF(Z44="","",IF(Z44>=75,"A",IF(Z44>=50,"B",IF(Z44>=25,"C","D")))) -> C | AB44: =IF(C44="","",IF(AND(R44<>"",S44<>"",U44<>"",V44<>"",W44<>""),"✓ Complete","⚠ MISSING: "&IF(R44="","Call Date, ","")&IF(S44="","Modality, ","")&IF(U44="","Budget, ","")&IF(V44="","Timeline, ","")&IF(W44="","Decision Maker",""))) -> ⚠ MISSING: Call Date, Modality, Budget, Timeline, Decision Maker | AC44: New Lead
A45: =IF(C45<>"","AYA-"&TEXT(ROW()-5,"000"),"") -> AYA-040 | B45: 45727 | C45: Somasundaram | D45: K | F45: datainflo@gmail.com | G45: Datainflo | J45: Cold Outreach | K45: Datainflo is a BPO services company specializing in data annotation solutions. Our team consists of experienced annotators skilled in providing high-quality data labeling services. We have extensive experience working with leading companies in sectors such as ADAS systems, smart construction, and large language models. Our expertise includes tasks like bounding box annotation and text annotation. | L45: Seyram | M45: 45727 | N45: Responded — Not a Fit | O45: Data Annotation | P45: Other Solutions | Q45: Direct | Y45: Not a Fit! | Z45: =IF(C45="","",(IF(OR(P45="Data Annotation",P45="GenAI / LLM Eval",P45="Medical Annotation"),25,IF(OR(P45="AI Consulting",P45="Data Collection"),18,IF(P45<>"",10,0)))+IF(AND(K45<>"",LEN(K45)>50,T45<>""),20,IF(AND(K45<>"",LEN(K45)>20),12,IF(K45<>"",5,0)))+IF(OR(U45="$100k–$500k",U45="$500k+"),20,IF(OR(U45="$25k–$100k"),15,IF(OR(U45="$5k–$25k"),10,IF(U45="$1k–$5k",5,0))))+IF(AND(G45<>"",G45<>"-"),15,IF(G45<>"",8,0))+IF(V45="Immediate (this month)",10,IF(V45="Short-term (1–3 months)",7,IF(V45="Medium (3–6 months)",4,0)))+IF(W45="Yes",10,IF(W45="Unclear",5,0)))) -> 37 | AA45: =IF(Z45="","",IF(Z45>=75,"A",IF(Z45>=50,"B",IF(Z45>=25,"C","D")))) -> C | AB45: =IF(C45="","",IF(AND(R45<>"",S45<>"",U45<>"",V45<>"",W45<>""),"✓ Complete","⚠ MISSING: "&IF(R45="","Call Date, ","")&IF(S45="","Modality, ","")&IF(U45="","Budget, ","")&IF(V45="","Timeline, ","")&IF(W45="","Decision Maker",""))) -> ⚠ MISSING: Call Date, Modality, Budget, Timeline, Decision Maker | AC45: Dead — Not a Fit | AD45: Not a Fit
A46: =IF(C46<>"","AYA-"&TEXT(ROW()-5,"000"),"") -> AYA-041 | B46: 45729 | C46: Sankarsan | D46: Mohanty | F46: sankar@drbreaths.com | G46: Dr. BreathE | J46: Cold Outreach | K46: I am reaching out from Dr. BreathE(https://drbreathe.ai/), and we are interested in your Data Annotation Services for medical imaging projects. I would like to learn more about your pricing, workflow, and quality control processes. Please share further details on how we can collaborate. | L46: Akhil | M46: 45729 | N46: Responded — Not a Fit | O46: Data Annotation | P46: Other Solutions | Q46: Direct | X46: Healthcare/Medical | Y46: POC Performed - Quality was bad and theyd ecided not to proceed with AyaData | Z46: =IF(C46="","",(IF(OR(P46="Data Annotation",P46="GenAI / LLM Eval",P46="Medical Annotation"),25,IF(OR(P46="AI Consulting",P46="Data Collection"),18,IF(P46<>"",10,0)))+IF(AND(K46<>"",LEN(K46)>50,T46<>""),20,IF(AND(K46<>"",LEN(K46)>20),12,IF(K46<>"",5,0)))+IF(OR(U46="$100k–$500k",U46="$500k+"),20,IF(OR(U46="$25k–$100k"),15,IF(OR(U46="$5k–$25k"),10,IF(U46="$1k–$5k",5,0))))+IF(AND(G46<>"",G46<>"-"),15,IF(G46<>"",8,0))+IF(V46="Immediate (this month)",10,IF(V46="Short-term (1–3 months)",7,IF(V46="Medium (3–6 months)",4,0)))+IF(W46="Yes",10,IF(W46="Unclear",5,0)))) -> 37 | AA46: =IF(Z46="","",IF(Z46>=75,"A",IF(Z46>=50,"B",IF(Z46>=25,"C","D")))) -> C | AB46: =IF(C46="","",IF(AND(R46<>"",S46<>"",U46<>"",V46<>"",W46<>""),"✓ Complete","⚠ MISSING: "&IF(R46="","Call Date, ","")&IF(S46="","Modality, ","")&IF(U46="","Budget, ","")&IF(V46="","Timeline, ","")&IF(W46="","Decision Maker",""))) -> ⚠ MISSING: Call Date, Modality, Budget, Timeline, Decision Maker | AC46: Dead — Not a Fit | AD46: Not a Fit
A47: =IF(C47<>"","AYA-"&TEXT(ROW()-5,"000"),"") -> AYA-042 | B47: 45738 | C47: Vaibhav | D47: Mistry | F47: vaibhav@scribeindia.in | G47: Scribe | H47: Bus Development | J47: Cold Outreach | K47: We’re SCRIBE – a data annotation company with a proven track record in AI/ML support, computer vision, and NLP. We’ve helped companies scale their projects with high-quality annotation and engineering services. Expertise: Image/video annotation, LIDAR, ADAS, NLP (multiple languages), audio annotation, and more. Capacity: Millions of annotations/month across object detection, lane detection, 3D cuboids, and semantic segmentation. | L47: Seyram | M47: 45738 | N47: Responded — Not a Fit | O47: Data Annotation | P47: Other Solutions | Q47: Direct | Y47: Not a Fit! | Z47: =IF(C47="","",(IF(OR(P47="Data Annotation",P47="GenAI / LLM Eval",P47="Medical Annotation"),25,IF(OR(P47="AI Consulting",P47="Data Collection"),18,IF(P47<>"",10,0)))+IF(AND(K47<>"",LEN(K47)>50,T47<>""),20,IF(AND(K47<>"",LEN(K47)>20),12,IF(K47<>"",5,0)))+IF(OR(U47="$100k–$500k",U47="$500k+"),20,IF(OR(U47="$25k–$100k"),15,IF(OR(U47="$5k–$25k"),10,IF(U47="$1k–$5k",5,0))))+IF(AND(G47<>"",G47<>"-"),15,IF(G47<>"",8,0))+IF(V47="Immediate (this month)",10,IF(V47="Short-term (1–3 months)",7,IF(V47="Medium (3–6 months)",4,0)))+IF(W47="Yes",10,IF(W47="Unclear",5,0)))) -> 37 | AA47: =IF(Z47="","",IF(Z47>=75,"A",IF(Z47>=50,"B",IF(Z47>=25,"C","D")))) -> C | AB47: =IF(C47="","",IF(AND(R47<>"",S47<>"",U47<>"",V47<>"",W47<>""),"✓ Complete","⚠ MISSING: "&IF(R47="","Call Date, ","")&IF(S47="","Modality, ","")&IF(U47="","Budget, ","")&IF(V47="","Timeline, ","")&IF(W47="","Decision Maker",""))) -> ⚠ MISSING: Call Date, Modality, Budget, Timeline, Decision Maker | AC47: Dead — Not a Fit | AD47: Not a Fit
A48: =IF(C48<>"","AYA-"&TEXT(ROW()-5,"000"),"") -> AYA-043 | B48: 45741 | C48: Ignacio | D48: Behler | F48: ignaciobehler@gmail.com | J48: Cold Outreach | K48: I would like to access the following dataset: Advanced Retail Security Through AI | L48: Michael | M48: 45741 | N48: No Response | O48: Data Annotation | P48: CV Annotation | Q48: Direct | X48: Other | Y48: Went Quiet! | Z48: =IF(C48="","",(IF(OR(P48="Data Annotation",P48="GenAI / LLM Eval",P48="Medical Annotation"),25,IF(OR(P48="AI Consulting",P48="Data Collection"),18,IF(P48<>"",10,0)))+IF(AND(K48<>"",LEN(K48)>50,T48<>""),20,IF(AND(K48<>"",LEN(K48)>20),12,IF(K48<>"",5,0)))+IF(OR(U48="$100k–$500k",U48="$500k+"),20,IF(OR(U48="$25k–$100k"),15,IF(OR(U48="$5k–$25k"),10,IF(U48="$1k–$5k",5,0))))+IF(AND(G48<>"",G48<>"-"),15,IF(G48<>"",8,0))+IF(V48="Immediate (this month)",10,IF(V48="Short-term (1–3 months)",7,IF(V48="Medium (3–6 months)",4,0)))+IF(W48="Yes",10,IF(W48="Unclear",5,0)))) -> 22 | AA48: =IF(Z48="","",IF(Z48>=75,"A",IF(Z48>=50,"B",IF(Z48>=25,"C","D")))) -> D | AB48: =IF(C48="","",IF(AND(R48<>"",S48<>"",U48<>"",V48<>"",W48<>""),"✓ Complete","⚠ MISSING: "&IF(R48="","Call Date, ","")&IF(S48="","Modality, ","")&IF(U48="","Budget, ","")&IF(V48="","Timeline, ","")&IF(W48="","Decision Maker",""))) -> ⚠ MISSING: Call Date, Modality, Budget, Timeline, Decision Maker | AC48: Dead — No Response | AD48: No Response
A49: =IF(C49<>"","AYA-"&TEXT(ROW()-5,"000"),"") -> AYA-044 | B49: 45743 | C49: Filip | D49: Hatlak | G49: Telus Digital | H49: Procurement Specialist, TIAI Crowdsoursing | J49: Cold Outreach | K49: We are searching for new partners to assist us with our projects. Most of our projects require participants/collaborators/agencies that will help us create/collect data content to improve our clients’ AI platforms, e.g., data collection, data annotation, content creation, transcription, etc. We would like to have you as a partner and include you on our database for future collaboration. Let me know if you are interested, and if you need more details regarding the type of projects we do, do not h | L49: Seyram | M49: 45743 | N49: Responded — Interested | O49: Data Annotation | P49: Speech Solutions | Q49: Direct | Y49: Thrilled to announce a new partnership! We've already received one each data sourcing and annotation projects. | Z49: =IF(C49="","",(IF(OR(P49="Data Annotation",P49="GenAI / LLM Eval",P49="Medical Annotation"),25,IF(OR(P49="AI Consulting",P49="Data Collection"),18,IF(P49<>"",10,0)))+IF(AND(K49<>"",LEN(K49)>50,T49<>""),20,IF(AND(K49<>"",LEN(K49)>20),12,IF(K49<>"",5,0)))+IF(OR(U49="$100k–$500k",U49="$500k+"),20,IF(OR(U49="$25k–$100k"),15,IF(OR(U49="$5k–$25k"),10,IF(U49="$1k–$5k",5,0))))+IF(AND(G49<>"",G49<>"-"),15,IF(G49<>"",8,0))+IF(V49="Immediate (this month)",10,IF(V49="Short-term (1–3 months)",7,IF(V49="Medium (3–6 months)",4,0)))+IF(W49="Yes",10,IF(W49="Unclear",5,0)))) -> 37 | AA49: =IF(Z49="","",IF(Z49>=75,"A",IF(Z49>=50,"B",IF(Z49>=25,"C","D")))) -> C | AB49: =IF(C49="","",IF(AND(R49<>"",S49<>"",U49<>"",V49<>"",W49<>""),"✓ Complete","⚠ MISSING: "&IF(R49="","Call Date, ","")&IF(S49="","Modality, ","")&IF(U49="","Budget, ","")&IF(V49="","Timeline, ","")&IF(W49="","Decision Maker",""))) -> ⚠ MISSING: Call Date, Modality, Budget, Timeline, Decision Maker | AC49: Move to Scoping
A50: =IF(C50<>"","AYA-"&TEXT(ROW()-5,"000"),"") -> AYA-045 | B50: 45743 | C50: Mohamad | D50: Shamly | F50: MShamly@innodata.com | G50: Innodata | J50: Cold Outreach | K50: RFP: We require real-world face image data to train and evaluate a Face Embedding Model. The data will be purchased in batches, allowing for quality assessment, feedback, and iterative improvement. The goal is to build a diverse and high-quality dataset that meets our model’s performance requirements. Attachments for Review To provide a detailed understanding of our requirements, please review the attached document: 1. Face Recognition Data Requirement Document – Outlines project objectives, da | L50: Akhil | M50: 45743 | N50: Responded — Not a Fit | O50: Data Annotation | P50: Other Solutions | Q50: Direct | X50: Other | Y50: Not a Fit! Needed African but also South asian people. | Z50: =IF(C50="","",(IF(OR(P50="Data Annotation",P50="GenAI / LLM Eval",P50="Medical Annotation"),25,IF(OR(P50="AI Consulting",P50="Data Collection"),18,IF(P50<>"",10,0)))+IF(AND(K50<>"",LEN(K50)>50,T50<>""),20,IF(AND(K50<>"",LEN(K50)>20),12,IF(K50<>"",5,0)))+IF(OR(U50="$100k–$500k",U50="$500k+"),20,IF(OR(U50="$25k–$100k"),15,IF(OR(U50="$5k–$25k"),10,IF(U50="$1k–$5k",5,0))))+IF(AND(G50<>"",G50<>"-"),15,IF(G50<>"",8,0))+IF(V50="Immediate (this month)",10,IF(V50="Short-term (1–3 months)",7,IF(V50="Medium (3–6 months)",4,0)))+IF(W50="Yes",10,IF(W50="Unclear",5,0)))) -> 37 | AA50: =IF(Z50="","",IF(Z50>=75,"A",IF(Z50>=50,"B",IF(Z50>=25,"C","D")))) -> C | AB50: =IF(C50="","",IF(AND(R50<>"",S50<>"",U50<>"",V50<>"",W50<>""),"✓ Complete","⚠ MISSING: "&IF(R50="","Call Date, ","")&IF(S50="","Modality, ","")&IF(U50="","Budget, ","")&IF(V50="","Timeline, ","")&IF(W50="","Decision Maker",""))) -> ⚠ MISSING: Call Date, Modality, Budget, Timeline, Decision Maker | AC50: Dead — Not a Fit | AD50: Not a Fit
A51: =IF(C51<>"","AYA-"&TEXT(ROW()-5,"000"),"") -> AYA-046 | B51: 45744 | C51: Kyle | D51: Hamar | F51: kyle@omnirocket.com | G51: OmniRocket | H51: CEO/Co-founder | J51: Collective OS | K51: OmniRocket is dedicated to empowering e-commerce entrepreneurs, particularly those utilizing Shopify, by providing performance coaching, website development, and management services. Their offerings include personalized coaching, a comprehensive training library, and a blog featuring in-depth e-commerce articles. OmniRocket also produces a top-ranked e-commerce podcast and a YouTube channel with weekly tips, aiming to equip online sellers with the tools and knowledge necessary for scaling their | L51: Freddie | M51: 45744 | N51: Responded — Interested | O51: AI Solutions | Q51: Direct | Y51: Freddie to provide update! | Z51: =IF(C51="","",(IF(OR(P51="Data Annotation",P51="GenAI / LLM Eval",P51="Medical Annotation"),25,IF(OR(P51="AI Consulting",P51="Data Collection"),18,IF(P51<>"",10,0)))+IF(AND(K51<>"",LEN(K51)>50,T51<>""),20,IF(AND(K51<>"",LEN(K51)>20),12,IF(K51<>"",5,0)))+IF(OR(U51="$100k–$500k",U51="$500k+"),20,IF(OR(U51="$25k–$100k"),15,IF(OR(U51="$5k–$25k"),10,IF(U51="$1k–$5k",5,0))))+IF(AND(G51<>"",G51<>"-"),15,IF(G51<>"",8,0))+IF(V51="Immediate (this month)",10,IF(V51="Short-term (1–3 months)",7,IF(V51="Medium (3–6 months)",4,0)))+IF(W51="Yes",10,IF(W51="Unclear",5,0)))) -> 27 | AA51: =IF(Z51="","",IF(Z51>=75,"A",IF(Z51>=50,"B",IF(Z51>=25,"C","D")))) -> C | AB51: =IF(C51="","",IF(AND(R51<>"",S51<>"",U51<>"",V51<>"",W51<>""),"✓ Complete","⚠ MISSING: "&IF(R51="","Call Date, ","")&IF(S51="","Modality, ","")&IF(U51="","Budget, ","")&IF(V51="","Timeline, ","")&IF(W51="","Decision Maker",""))) -> ⚠ MISSING: Call Date, Modality, Budget, Timeline, Decision Maker | AC51: Contacted
A52: =IF(C52<>"","AYA-"&TEXT(ROW()-5,"000"),"") -> AYA-047 | B52: 45754 | C52: Neeraj | D52: Bahulekar | F52: neeraj@zogato.com | G52: Zogato | J52: Collective OS | K52: I'd like to introduce you to Neeraj Bahulekar from Zogato. Zogato is a technology consulting firm specializing in product engineering, architecture consulting, performance engineering, UI/UX design, migration and porting, and sustenance and support. They assist businesses in building prototypes, adding features, enhancing scalability, and modernizing products with the latest technologies. Their expertise spans NodeJS, Python, Angular, React, Flutter, Java, .Net, MongoDB, Oracle, SQL Server, MySQ | L52: Akhil | M52: 45754 | N52: No Response | O52: Data Annotation | P52: CV Annotation | Q52: Direct | Y52: No major actions! | Z52: =IF(C52="","",(IF(OR(P52="Data Annotation",P52="GenAI / LLM Eval",P52="Medical Annotation"),25,IF(OR(P52="AI Consulting",P52="Data Collection"),18,IF(P52<>"",10,0)))+IF(AND(K52<>"",LEN(K52)>50,T52<>""),20,IF(AND(K52<>"",LEN(K52)>20),12,IF(K52<>"",5,0)))+IF(OR(U52="$100k–$500k",U52="$500k+"),20,IF(OR(U52="$25k–$100k"),15,IF(OR(U52="$5k–$25k"),10,IF(U52="$1k–$5k",5,0))))+IF(AND(G52<>"",G52<>"-"),15,IF(G52<>"",8,0))+IF(V52="Immediate (this month)",10,IF(V52="Short-term (1–3 months)",7,IF(V52="Medium (3–6 months)",4,0)))+IF(W52="Yes",10,IF(W52="Unclear",5,0)))) -> 37 | AA52: =IF(Z52="","",IF(Z52>=75,"A",IF(Z52>=50,"B",IF(Z52>=25,"C","D")))) -> C | AB52: =IF(C52="","",IF(AND(R52<>"",S52<>"",U52<>"",V52<>"",W52<>""),"✓ Complete","⚠ MISSING: "&IF(R52="","Call Date, ","")&IF(S52="","Modality, ","")&IF(U52="","Budget, ","")&IF(V52="","Timeline, ","")&IF(W52="","Decision Maker",""))) -> ⚠ MISSING: Call Date, Modality, Budget, Timeline, Decision Maker | AC52: Dead — No Response | AD52: No Response
A53: =IF(C53<>"","AYA-"&TEXT(ROW()-5,"000"),"") -> AYA-048 | B53: 45754 | C53: Kevin | D53: Fomengia | F53: Kevin@bridgelabs.tech | G53: Bridge Labs | J53: Collective OS | K53: Allow me to introduce you to Kevin Fomengia from Bridge Labs. Bridge Labs connects American companies with senior-level offshore developers from West Africa, focusing on the technology sector. They offer hiring solutions, including contract-to-hire and direct-to-hire placements, ensuring developers possess the necessary skills and cultural compatibility for collaboration in U.S. time zones. Bridge Labs' rigorous vetting process accepts the top 3% of tech talent in Africa, providing access to ove | L53: Freddie | M53: 45754 | N53: Responded — Interested | O53: Data Annotation | P53: LiDAR Annotation | Q53: Direct | Y53: Freddie to provide update! | Z53: =IF(C53="","",(IF(OR(P53="Data Annotation",P53="GenAI / LLM Eval",P53="Medical Annotation"),25,IF(OR(P53="AI Consulting",P53="Data Collection"),18,IF(P53<>"",10,0)))+IF(AND(K53<>"",LEN(K53)>50,T53<>""),20,IF(AND(K53<>"",LEN(K53)>20),12,IF(K53<>"",5,0)))+IF(OR(U53="$100k–$500k",U53="$500k+"),20,IF(OR(U53="$25k–$100k"),15,IF(OR(U53="$5k–$25k"),10,IF(U53="$1k–$5k",5,0))))+IF(AND(G53<>"",G53<>"-"),15,IF(G53<>"",8,0))+IF(V53="Immediate (this month)",10,IF(V53="Short-term (1–3 months)",7,IF(V53="Medium (3–6 months)",4,0)))+IF(W53="Yes",10,IF(W53="Unclear",5,0)))) -> 37 | AA53: =IF(Z53="","",IF(Z53>=75,"A",IF(Z53>=50,"B",IF(Z53>=25,"C","D")))) -> C | AB53: =IF(C53="","",IF(AND(R53<>"",S53<>"",U53<>"",V53<>"",W53<>""),"✓ Complete","⚠ MISSING: "&IF(R53="","Call Date, ","")&IF(S53="","Modality, ","")&IF(U53="","Budget, ","")&IF(V53="","Timeline, ","")&IF(W53="","Decision Maker",""))) -> ⚠ MISSING: Call Date, Modality, Budget, Timeline, Decision Maker | AC53: Contacted
A54: =IF(C54<>"","AYA-"&TEXT(ROW()-5,"000"),"") -> AYA-049 | B54: 45764 | C54: Jamie | D54: Jose | F54: jamie@aculidessolutions.com | G54: Aculide Solutions | J54: Website Form | K54: We help ambitious tech companies connect directly with the people who matter most: Decision-makers actively sourcing new technologies across high-growth sectors: • AI, Machine Learning & Data Intelligence • Cloud, DevOps & Edge Infrastructure • Cybersecurity & Risk Management • IoT, Smart Mobility & Digital Infrastructure • Fintech, Healthtech & Industry Platforms Our contact lists are verified, customized, and ready to plug into your next campaign—whether you're launching into | L54: Seyram | O54: Data Annotation | P54: Medical AI Annotation | Q54: Direct | Z54: =IF(C54="","",(IF(OR(P54="Data Annotation",P54="GenAI / LLM Eval",P54="Medical Annotation"),25,IF(OR(P54="AI Consulting",P54="Data Collection"),18,IF(P54<>"",10,0)))+IF(AND(K54<>"",LEN(K54)>50,T54<>""),20,IF(AND(K54<>"",LEN(K54)>20),12,IF(K54<>"",5,0)))+IF(OR(U54="$100k–$500k",U54="$500k+"),20,IF(OR(U54="$25k–$100k"),15,IF(OR(U54="$5k–$25k"),10,IF(U54="$1k–$5k",5,0))))+IF(AND(G54<>"",G54<>"-"),15,IF(G54<>"",8,0))+IF(V54="Immediate (this month)",10,IF(V54="Short-term (1–3 months)",7,IF(V54="Medium (3–6 months)",4,0)))+IF(W54="Yes",10,IF(W54="Unclear",5,0)))) -> 37 | AA54: =IF(Z54="","",IF(Z54>=75,"A",IF(Z54>=50,"B",IF(Z54>=25,"C","D")))) -> C | AB54: =IF(C54="","",IF(AND(R54<>"",S54<>"",U54<>"",V54<>"",W54<>""),"✓ Complete","⚠ MISSING: "&IF(R54="","Call Date, ","")&IF(S54="","Modality, ","")&IF(U54="","Budget, ","")&IF(V54="","Timeline, ","")&IF(W54="","Decision Maker",""))) -> ⚠ MISSING: Call Date, Modality, Budget, Timeline, Decision Maker | AC54: New Lead
A55: =IF(C55<>"","AYA-"&TEXT(ROW()-5,"000"),"") -> AYA-050 | B55: 45768 | C55: Elanggovan | D55: Thanggavilo | F55: elanggovan@hiilsedrone.com | G55: Hiilse Drone | J55: Website Form | K55: He booked a Zoom meeting directly with Freddie alongside theh calendly meeting. | L55: Freddie | M55: 45768 | N55: Responded — Interested | O55: Data Annotation | P55: CV Annotation | Q55: Direct | Y55: Freddie to provide update! | Z55: =IF(C55="","",(IF(OR(P55="Data Annotation",P55="GenAI / LLM Eval",P55="Medical Annotation"),25,IF(OR(P55="AI Consulting",P55="Data Collection"),18,IF(P55<>"",10,0)))+IF(AND(K55<>"",LEN(K55)>50,T55<>""),20,IF(AND(K55<>"",LEN(K55)>20),12,IF(K55<>"",5,0)))+IF(OR(U55="$100k–$500k",U55="$500k+"),20,IF(OR(U55="$25k–$100k"),15,IF(OR(U55="$5k–$25k"),10,IF(U55="$1k–$5k",5,0))))+IF(AND(G55<>"",G55<>"-"),15,IF(G55<>"",8,0))+IF(V55="Immediate (this month)",10,IF(V55="Short-term (1–3 months)",7,IF(V55="Medium (3–6 months)",4,0)))+IF(W55="Yes",10,IF(W55="Unclear",5,0)))) -> 37 | AA55: =IF(Z55="","",IF(Z55>=75,"A",IF(Z55>=50,"B",IF(Z55>=25,"C","D")))) -> C | AB55: =IF(C55="","",IF(AND(R55<>"",S55<>"",U55<>"",V55<>"",W55<>""),"✓ Complete","⚠ MISSING: "&IF(R55="","Call Date, ","")&IF(S55="","Modality, ","")&IF(U55="","Budget, ","")&IF(V55="","Timeline, ","")&IF(W55="","Decision Maker",""))) -> ⚠ MISSING: Call Date, Modality, Budget, Timeline, Decision Maker | AC55: Contacted
A56: =IF(C56<>"","AYA-"&TEXT(ROW()-5,"000"),"") -> AYA-051 | B56: 45770 | C56: Oche | D56: Ankeli | F56: oche@yux.design | G56: Yux Design | J56: Website Form | K56: Dear Aya Team, I hope this message finds you well. I’ve been exploring your work on speech technologies, especially your efforts around African language models, and I’m truly impressed. I’m currently working on a project focused on building accurate ASR systems for local languages, with an emphasis on domain-specific use cases like healthcare. I wanted to inquire if your team provides datasets or ASR models that are customized for specific domains—particularly in health—or if there’s any ongo | L56: Olivia | M56: 45770 | N56: Responded — Interested | O56: AI Solutions | P56: Other Solutions | Q56: Direct | X56: Tech/SaaS | Y56: Olivia to provide update! | Z56: =IF(C56="","",(IF(OR(P56="Data Annotation",P56="GenAI / LLM Eval",P56="Medical Annotation"),25,IF(OR(P56="AI Consulting",P56="Data Collection"),18,IF(P56<>"",10,0)))+IF(AND(K56<>"",LEN(K56)>50,T56<>""),20,IF(AND(K56<>"",LEN(K56)>20),12,IF(K56<>"",5,0)))+IF(OR(U56="$100k–$500k",U56="$500k+"),20,IF(OR(U56="$25k–$100k"),15,IF(OR(U56="$5k–$25k"),10,IF(U56="$1k–$5k",5,0))))+IF(AND(G56<>"",G56<>"-"),15,IF(G56<>"",8,0))+IF(V56="Immediate (this month)",10,IF(V56="Short-term (1–3 months)",7,IF(V56="Medium (3–6 months)",4,0)))+IF(W56="Yes",10,IF(W56="Unclear",5,0)))) -> 37 | AA56: =IF(Z56="","",IF(Z56>=75,"A",IF(Z56>=50,"B",IF(Z56>=25,"C","D")))) -> C | AB56: =IF(C56="","",IF(AND(R56<>"",S56<>"",U56<>"",V56<>"",W56<>""),"✓ Complete","⚠ MISSING: "&IF(R56="","Call Date, ","")&IF(S56="","Modality, ","")&IF(U56="","Budget, ","")&IF(V56="","Timeline, ","")&IF(W56="","Decision Maker",""))) -> ⚠ MISSING: Call Date, Modality, Budget, Timeline, Decision Maker | AC56: Contacted
A57: =IF(C57<>"","AYA-"&TEXT(ROW()-5,"000"),"") -> AYA-052 | B57: 45771 | C57: Mahmudul | D57: Hasan | F57: mahmudul.hasan@acotegroup.com | G57: Acote Group | H57: CEO | J57: Website Form | K57: This is Hasan Mahmudul, Vice President of Acote Group. An IT BPO company in Bangladesh run by a seasoned Korean National with 25 Years work experience in LG Electronics including overseas subsidiary and Branch Head. Acote: Your Trusted Partner in Autonomous Vehicle Data Labeling In the rapidly evolving autonomous vehicle (AV) industry, high-quality data labeling is more than just a requirement—it is the cornerstone of innovation and safety. At Acote, we take pride in being a trusted leader in d | L57: Seyram | M57: 45771 | N57: Responded — Interested | O57: Data Annotation | Q57: Direct | Y57: Could be a good partner! Active in Annotaiton market! | Z57: =IF(C57="","",(IF(OR(P57="Data Annotation",P57="GenAI / LLM Eval",P57="Medical Annotation"),25,IF(OR(P57="AI Consulting",P57="Data Collection"),18,IF(P57<>"",10,0)))+IF(AND(K57<>"",LEN(K57)>50,T57<>""),20,IF(AND(K57<>"",LEN(K57)>20),12,IF(K57<>"",5,0)))+IF(OR(U57="$100k–$500k",U57="$500k+"),20,IF(OR(U57="$25k–$100k"),15,IF(OR(U57="$5k–$25k"),10,IF(U57="$1k–$5k",5,0))))+IF(AND(G57<>"",G57<>"-"),15,IF(G57<>"",8,0))+IF(V57="Immediate (this month)",10,IF(V57="Short-term (1–3 months)",7,IF(V57="Medium (3–6 months)",4,0)))+IF(W57="Yes",10,IF(W57="Unclear",5,0)))) -> 27 | AA57: =IF(Z57="","",IF(Z57>=75,"A",IF(Z57>=50,"B",IF(Z57>=25,"C","D")))) -> C | AB57: =IF(C57="","",IF(AND(R57<>"",S57<>"",U57<>"",V57<>"",W57<>""),"✓ Complete","⚠ MISSING: "&IF(R57="","Call Date, ","")&IF(S57="","Modality, ","")&IF(U57="","Budget, ","")&IF(V57="","Timeline, ","")&IF(W57="","Decision Maker",""))) -> ⚠ MISSING: Call Date, Modality, Budget, Timeline, Decision Maker | AC57: Contacted
A58: =IF(C58<>"","AYA-"&TEXT(ROW()-5,"000"),"") -> AYA-053 | B58: 45771 | C58: John | D58: Watson | F58: john.watson@consultant.com / office@loretohs-manchester.org.uk | G58: Loreto Chorlton | J58: Cold Outreach | K58: We’re updating our supplier list and want to check if you provide services to the education sector. If yes, could you send over a brief overview of what you offer? Please send information to office@loretohs-manchester.org.uk Regards J. Watson Loreto Chorlton | L58: Seyram | M58: 45771 | N58: Responded — Not a Fit | O58: Data Annotation | P58: CV Annotation | Q58: Direct | Y58: Not a fit! | Z58: =IF(C58="","",(IF(OR(P58="Data Annotation",P58="GenAI / LLM Eval",P58="Medical Annotation"),25,IF(OR(P58="AI Consulting",P58="Data Collection"),18,IF(P58<>"",10,0)))+IF(AND(K58<>"",LEN(K58)>50,T58<>""),20,IF(AND(K58<>"",LEN(K58)>20),12,IF(K58<>"",5,0)))+IF(OR(U58="$100k–$500k",U58="$500k+"),20,IF(OR(U58="$25k–$100k"),15,IF(OR(U58="$5k–$25k"),10,IF(U58="$1k–$5k",5,0))))+IF(AND(G58<>"",G58<>"-"),15,IF(G58<>"",8,0))+IF(V58="Immediate (this month)",10,IF(V58="Short-term (1–3 months)",7,IF(V58="Medium (3–6 months)",4,0)))+IF(W58="Yes",10,IF(W58="Unclear",5,0)))) -> 37 | AA58: =IF(Z58="","",IF(Z58>=75,"A",IF(Z58>=50,"B",IF(Z58>=25,"C","D")))) -> C | AB58: =IF(C58="","",IF(AND(R58<>"",S58<>"",U58<>"",V58<>"",W58<>""),"✓ Complete","⚠ MISSING: "&IF(R58="","Call Date, ","")&IF(S58="","Modality, ","")&IF(U58="","Budget, ","")&IF(V58="","Timeline, ","")&IF(W58="","Decision Maker",""))) -> ⚠ MISSING: Call Date, Modality, Budget, Timeline, Decision Maker | AC58: Dead — Not a Fit | AD58: Not a Fit
A59: =IF(C59<>"","AYA-"&TEXT(ROW()-5,"000"),"") -> AYA-054 | B59: 45772 | C59: Kevin | D59: Smits | F59: kevin@pixelfarmingrobotics.com | G59: Pixel Farming Robotics | H59: Media & Content Creator | J59: Cold Outreach | K59: Dear team, I am looking for an image annotation service that can help our farmers make solid plant detection models. We use polygons to label weeds and crops. We also set a pose at the center of the plant to train a model that recognizes the plants and is able to send targetting data to our laser. We use the Yolov8 and Yolov11 CV models. We make the annotations in our self-developed Pixelfarming Academy. It is possible to use other image annotation software however we need to process the data | L59: Akhil | M59: 45772 | N59: Responded — Interested | O59: Data Annotation | P59: GenAI Annotation | Q59: Direct | X59: Automotive/AV | Y59: POC Completed! Commercials Shared! Waiting on Feedback! Hold! | Z59: =IF(C59="","",(IF(OR(P59="Data Annotation",P59="GenAI / LLM Eval",P59="Medical Annotation"),25,IF(OR(P59="AI Consulting",P59="Data Collection"),18,IF(P59<>"",10,0)))+IF(AND(K59<>"",LEN(K59)>50,T59<>""),20,IF(AND(K59<>"",LEN(K59)>20),12,IF(K59<>"",5,0)))+IF(OR(U59="$100k–$500k",U59="$500k+"),20,IF(OR(U59="$25k–$100k"),15,IF(OR(U59="$5k–$25k"),10,IF(U59="$1k–$5k",5,0))))+IF(AND(G59<>"",G59<>"-"),15,IF(G59<>"",8,0))+IF(V59="Immediate (this month)",10,IF(V59="Short-term (1–3 months)",7,IF(V59="Medium (3–6 months)",4,0)))+IF(W59="Yes",10,IF(W59="Unclear",5,0)))) -> 37 | AA59: =IF(Z59="","",IF(Z59>=75,"A",IF(Z59>=50,"B",IF(Z59>=25,"C","D")))) -> C | AB59: =IF(C59="","",IF(AND(R59<>"",S59<>"",U59<>"",V59<>"",W59<>""),"✓ Complete","⚠ MISSING: "&IF(R59="","Call Date, ","")&IF(S59="","Modality, ","")&IF(U59="","Budget, ","")&IF(V59="","Timeline, ","")&IF(W59="","Decision Maker",""))) -> ⚠ MISSING: Call Date, Modality, Budget, Timeline, Decision Maker | AC59: Move to Scoping
A60: =IF(C60<>"","AYA-"&TEXT(ROW()-5,"000"),"") -> AYA-055 | B60: 45773 | C60: Pankaj | D60: P | F60: pankaj.p@shaip.com | G60: Shaip | J60: Website Form | K60: services for data annotation, including 2D, 3D point cloud, LiDAR and radar annotation. | L60: Akhil | O60: Data Annotation | P60: Other Solutions | Q60: Direct | X60: Automotive/AV | Z60: =IF(C60="","",(IF(OR(P60="Data Annotation",P60="GenAI / LLM Eval",P60="Medical Annotation"),25,IF(OR(P60="AI Consulting",P60="Data Collection"),18,IF(P60<>"",10,0)))+IF(AND(K60<>"",LEN(K60)>50,T60<>""),20,IF(AND(K60<>"",LEN(K60)>20),12,IF(K60<>"",5,0)))+IF(OR(U60="$100k–$500k",U60="$500k+"),20,IF(OR(U60="$25k–$100k"),15,IF(OR(U60="$5k–$25k"),10,IF(U60="$1k–$5k",5,0))))+IF(AND(G60<>"",G60<>"-"),15,IF(G60<>"",8,0))+IF(V60="Immediate (this month)",10,IF(V60="Short-term (1–3 months)",7,IF(V60="Medium (3–6 months)",4,0)))+IF(W60="Yes",10,IF(W60="Unclear",5,0)))) -> 37 | AA60: =IF(Z60="","",IF(Z60>=75,"A",IF(Z60>=50,"B",IF(Z60>=25,"C","D")))) -> C | AB60: =IF(C60="","",IF(AND(R60<>"",S60<>"",U60<>"",V60<>"",W60<>""),"✓ Complete","⚠ MISSING: "&IF(R60="","Call Date, ","")&IF(S60="","Modality, ","")&IF(U60="","Budget, ","")&IF(V60="","Timeline, ","")&IF(W60="","Decision Maker",""))) -> ⚠ MISSING: Call Date, Modality, Budget, Timeline, Decision Maker | AC60: New Lead
A61: =IF(C61<>"","AYA-"&TEXT(ROW()-5,"000"),"") -> AYA-056 | B61: 45774 | C61: Shubham | D61: Aggarwal | F61: shubham.a@tagfact.com | G61: Tag Fact | J61: Search Engine | K61: We have a client need in Medical Imaging Annotation, specifically for annotation, curation, and storage of multimodal data including pathology (scanned biopsy slides), clinical data, and genomic data. We want to partner with you on this project. Apart from this, we don't have any other information. We have a call scheduled with the client next week, so if possible we would like to go on a call with you tomorrow, which is Monday, April 28th, 2025. If possible, please share the invite for 6:30 PM | L61: Akhil | M61: 45774 | N61: Responded — Interested | O61: Data Annotation | P61: Other Solutions | Q61: Direct | X61: Healthcare/Medical | Y61: Medical Annotaiton Partnership. NDA - In Process! | Z61: =IF(C61="","",(IF(OR(P61="Data Annotation",P61="GenAI / LLM Eval",P61="Medical Annotation"),25,IF(OR(P61="AI Consulting",P61="Data Collection"),18,IF(P61<>"",10,0)))+IF(AND(K61<>"",LEN(K61)>50,T61<>""),20,IF(AND(K61<>"",LEN(K61)>20),12,IF(K61<>"",5,0)))+IF(OR(U61="$100k–$500k",U61="$500k+"),20,IF(OR(U61="$25k–$100k"),15,IF(OR(U61="$5k–$25k"),10,IF(U61="$1k–$5k",5,0))))+IF(AND(G61<>"",G61<>"-"),15,IF(G61<>"",8,0))+IF(V61="Immediate (this month)",10,IF(V61="Short-term (1–3 months)",7,IF(V61="Medium (3–6 months)",4,0)))+IF(W61="Yes",10,IF(W61="Unclear",5,0)))) -> 37 | AA61: =IF(Z61="","",IF(Z61>=75,"A",IF(Z61>=50,"B",IF(Z61>=25,"C","D")))) -> C | AB61: =IF(C61="","",IF(AND(R61<>"",S61<>"",U61<>"",V61<>"",W61<>""),"✓ Complete","⚠ MISSING: "&IF(R61="","Call Date, ","")&IF(S61="","Modality, ","")&IF(U61="","Budget, ","")&IF(V61="","Timeline, ","")&IF(W61="","Decision Maker",""))) -> ⚠ MISSING: Call Date, Modality, Budget, Timeline, Decision Maker | AC61: Discovery Complete
A62: =IF(C62<>"","AYA-"&TEXT(ROW()-5,"000"),"") -> AYA-057 | B62: 45775 | C62: Jamaan | D62: Al-Jamaan | F62: j.aljamaan@tamkeentech.sa | G62: Tamkeen Tech | J62: Search Engine | K62: We are looking for a provider to source data for ML that is suitable for the Saudi market, as well as, outsourcing data annotation services. | L62: Akhil | M62: 45775 | N62: Responded — Interested | O62: Data Annotation | P62: Medical AI Annotation | Q62: Direct | X62: Other | Y62: Data Annotation Bid - Joint RFP Opp! | Z62: =IF(C62="","",(IF(OR(P62="Data Annotation",P62="GenAI / LLM Eval",P62="Medical Annotation"),25,IF(OR(P62="AI Consulting",P62="Data Collection"),18,IF(P62<>"",10,0)))+IF(AND(K62<>"",LEN(K62)>50,T62<>""),20,IF(AND(K62<>"",LEN(K62)>20),12,IF(K62<>"",5,0)))+IF(OR(U62="$100k–$500k",U62="$500k+"),20,IF(OR(U62="$25k–$100k"),15,IF(OR(U62="$5k–$25k"),10,IF(U62="$1k–$5k",5,0))))+IF(AND(G62<>"",G62<>"-"),15,IF(G62<>"",8,0))+IF(V62="Immediate (this month)",10,IF(V62="Short-term (1–3 months)",7,IF(V62="Medium (3–6 months)",4,0)))+IF(W62="Yes",10,IF(W62="Unclear",5,0)))) -> 37 | AA62: =IF(Z62="","",IF(Z62>=75,"A",IF(Z62>=50,"B",IF(Z62>=25,"C","D")))) -> C | AB62: =IF(C62="","",IF(AND(R62<>"",S62<>"",U62<>"",V62<>"",W62<>""),"✓ Complete","⚠ MISSING: "&IF(R62="","Call Date, ","")&IF(S62="","Modality, ","")&IF(U62="","Budget, ","")&IF(V62="","Timeline, ","")&IF(W62="","Decision Maker",""))) -> ⚠ MISSING: Call Date, Modality, Budget, Timeline, Decision Maker | AC62: Contacted
A63: =IF(C63<>"","AYA-"&TEXT(ROW()-5,"000"),"") -> AYA-058 | B63: 45782 | C63: Shiva | D63: Kumar | F63: shivakm@cosol.in | G63: Cosol | J63: Website Form | K63: We have a requirement of AIYA data security management system software module, We need quote for the same. | L63: Akhil | M63: 45782 | N63: Responded — Not a Fit | O63: AI Solutions | P63: CV Annotation | Q63: Direct | Y63: Not a fit! | Z63: =IF(C63="","",(IF(OR(P63="Data Annotation",P63="GenAI / LLM Eval",P63="Medical Annotation"),25,IF(OR(P63="AI Consulting",P63="Data Collection"),18,IF(P63<>"",10,0)))+IF(AND(K63<>"",LEN(K63)>50,T63<>""),20,IF(AND(K63<>"",LEN(K63)>20),12,IF(K63<>"",5,0)))+IF(OR(U63="$100k–$500k",U63="$500k+"),20,IF(OR(U63="$25k–$100k"),15,IF(OR(U63="$5k–$25k"),10,IF(U63="$1k–$5k",5,0))))+IF(AND(G63<>"",G63<>"-"),15,IF(G63<>"",8,0))+IF(V63="Immediate (this month)",10,IF(V63="Short-term (1–3 months)",7,IF(V63="Medium (3–6 months)",4,0)))+IF(W63="Yes",10,IF(W63="Unclear",5,0)))) -> 37 | AA63: =IF(Z63="","",IF(Z63>=75,"A",IF(Z63>=50,"B",IF(Z63>=25,"C","D")))) -> C | AB63: =IF(C63="","",IF(AND(R63<>"",S63<>"",U63<>"",V63<>"",W63<>""),"✓ Complete","⚠ MISSING: "&IF(R63="","Call Date, ","")&IF(S63="","Modality, ","")&IF(U63="","Budget, ","")&IF(V63="","Timeline, ","")&IF(W63="","Decision Maker",""))) -> ⚠ MISSING: Call Date, Modality, Budget, Timeline, Decision Maker | AC63: Dead — Not a Fit | AD63: Not a Fit
A64: =IF(C64<>"","AYA-"&TEXT(ROW()-5,"000"),"") -> AYA-059 | B64: 45783 | C64: Wiktoria | D64: Michalowska-Fairbairn | F64: W.Michalowska-Fairb@lionbridge.com | G64: Lionbridge | H64: AI Data Training Sourcing Manager | J64: Cold Outreach | K64: Hi there, I hope all is fine on your end. I'm contacting you to understand if you offer services related to image data collection. Please see below for a snapshot of the needs and let me know if there's something that you could potentially help us with. **Demographics & Numbers Required:** African (any country) 4,250 participants located in any country across the African continent. 50% Female & 50% Male. Age 18+ However, please let us know if you are able to cover the process for under 18 y/o p | L64: Akhil | M64: 45783 | N64: No Response | O64: Data Annotation | P64: Data Collection | Q64: Direct | X64: Other | Y64: 2 Follow Ups - No response! 3rd Follow Up- 09/06/2025 | Z64: =IF(C64="","",(IF(OR(P64="Data Annotation",P64="GenAI / LLM Eval",P64="Medical Annotation"),25,IF(OR(P64="AI Consulting",P64="Data Collection"),18,IF(P64<>"",10,0)))+IF(AND(K64<>"",LEN(K64)>50,T64<>""),20,IF(AND(K64<>"",LEN(K64)>20),12,IF(K64<>"",5,0)))+IF(OR(U64="$100k–$500k",U64="$500k+"),20,IF(OR(U64="$25k–$100k"),15,IF(OR(U64="$5k–$25k"),10,IF(U64="$1k–$5k",5,0))))+IF(AND(G64<>"",G64<>"-"),15,IF(G64<>"",8,0))+IF(V64="Immediate (this month)",10,IF(V64="Short-term (1–3 months)",7,IF(V64="Medium (3–6 months)",4,0)))+IF(W64="Yes",10,IF(W64="Unclear",5,0)))) -> 45 | AA64: =IF(Z64="","",IF(Z64>=75,"A",IF(Z64>=50,"B",IF(Z64>=25,"C","D")))) -> C | AB64: =IF(C64="","",IF(AND(R64<>"",S64<>"",U64<>"",V64<>"",W64<>""),"✓ Complete","⚠ MISSING: "&IF(R64="","Call Date, ","")&IF(S64="","Modality, ","")&IF(U64="","Budget, ","")&IF(V64="","Timeline, ","")&IF(W64="","Decision Maker",""))) -> ⚠ MISSING: Call Date, Modality, Budget, Timeline, Decision Maker | AC64: Dead — No Response | AD64: No Response
A65: =IF(C65<>"","AYA-"&TEXT(ROW()-5,"000"),"") -> AYA-060 | B65: 45783 | C65: Maheshwaran | D65: Umapathy | F65: maheshwaran.umapathy@key.me | G65: KeyMe | J65: Referral | K65: Hi team, Hope you're doing well. It was great collaborating with you and your team on our last image annotation initiative for KeyMe. We're gearing up to annotate another set of images in the coming weeks and wanted to check your team's availability. Looking forward to your response! Thanks, Mahesh | L65: Akhil | M65: 45783 | N65: No Response | O65: Data Annotation | P65: Other Solutions | Q65: Direct | X65: Automotive/AV | Y65: 2 Follow Ups - No response! 09/06/2025 - Scoping Raised | Z65: =IF(C65="","",(IF(OR(P65="Data Annotation",P65="GenAI / LLM Eval",P65="Medical Annotation"),25,IF(OR(P65="AI Consulting",P65="Data Collection"),18,IF(P65<>"",10,0)))+IF(AND(K65<>"",LEN(K65)>50,T65<>""),20,IF(AND(K65<>"",LEN(K65)>20),12,IF(K65<>"",5,0)))+IF(OR(U65="$100k–$500k",U65="$500k+"),20,IF(OR(U65="$25k–$100k"),15,IF(OR(U65="$5k–$25k"),10,IF(U65="$1k–$5k",5,0))))+IF(AND(G65<>"",G65<>"-"),15,IF(G65<>"",8,0))+IF(V65="Immediate (this month)",10,IF(V65="Short-term (1–3 months)",7,IF(V65="Medium (3–6 months)",4,0)))+IF(W65="Yes",10,IF(W65="Unclear",5,0)))) -> 37 | AA65: =IF(Z65="","",IF(Z65>=75,"A",IF(Z65>=50,"B",IF(Z65>=25,"C","D")))) -> C | AB65: =IF(C65="","",IF(AND(R65<>"",S65<>"",U65<>"",V65<>"",W65<>""),"✓ Complete","⚠ MISSING: "&IF(R65="","Call Date, ","")&IF(S65="","Modality, ","")&IF(U65="","Budget, ","")&IF(V65="","Timeline, ","")&IF(W65="","Decision Maker",""))) -> ⚠ MISSING: Call Date, Modality, Budget, Timeline, Decision Maker | AC65: Dead — No Response | AD65: No Response
A66: =IF(C66<>"","AYA-"&TEXT(ROW()-5,"000"),"") -> AYA-061 | B66: 45784 | C66: Dolly | D66: Singh | F66: dolly.singh@crystalhues.com | G66: Crystal Hues | H66: Project Coordinator | J66: Cold Outreach | K66: We’re excited to share details of an upcoming large-scale annotation project at Crystal Hues Ltd. that includes ASR Transcription and NLP Intent Annotation tasks. We are looking forward to your team’s support to ensure high-quality and timely delivery. 🔊 ASR Transcription – Project Overview: Languages Required: Multiple (English mandatory) Per Annotator Task: 150 audio clips Workflow: Validate if the audio contains English Apply appropriate tags (valid/invalid, <unk>, <spoken_noise>) Transcribe | L66: Akhil | M66: 45784 | N66: No Response | O66: Data Annotation | P66: CV Annotation | Q66: Direct | X66: Tech/SaaS | Y66: Dolly Singh's initial email is to present a large-scale ASR Transcription and NLP Intent Annotation project opportunity to Aya Data, and she emphasizes the need for high-quality and timely delivery. Following this, there have been two follow-up emails from Akhil Singh to Dolly Singh, but no response has been received from Crystal Hues. | Z66: =IF(C66="","",(IF(OR(P66="Data Annotation",P66="GenAI / LLM Eval",P66="Medical Annotation"),25,IF(OR(P66="AI Consulting",P66="Data Collection"),18,IF(P66<>"",10,0)))+IF(AND(K66<>"",LEN(K66)>50,T66<>""),20,IF(AND(K66<>"",LEN(K66)>20),12,IF(K66<>"",5,0)))+IF(OR(U66="$100k–$500k",U66="$500k+"),20,IF(OR(U66="$25k–$100k"),15,IF(OR(U66="$5k–$25k"),10,IF(U66="$1k–$5k",5,0))))+IF(AND(G66<>"",G66<>"-"),15,IF(G66<>"",8,0))+IF(V66="Immediate (this month)",10,IF(V66="Short-term (1–3 months)",7,IF(V66="Medium (3–6 months)",4,0)))+IF(W66="Yes",10,IF(W66="Unclear",5,0)))) -> 37 | AA66: =IF(Z66="","",IF(Z66>=75,"A",IF(Z66>=50,"B",IF(Z66>=25,"C","D")))) -> C | AB66: =IF(C66="","",IF(AND(R66<>"",S66<>"",U66<>"",V66<>"",W66<>""),"✓ Complete","⚠ MISSING: "&IF(R66="","Call Date, ","")&IF(S66="","Modality, ","")&IF(U66="","Budget, ","")&IF(V66="","Timeline, ","")&IF(W66="","Decision Maker",""))) -> ⚠ MISSING: Call Date, Modality, Budget, Timeline, Decision Maker | AC66: Dead — No Response | AD66: No Response
A67: =IF(C67<>"","AYA-"&TEXT(ROW()-5,"000"),"") -> AYA-062 | B67: 45784 | C67: Michael | D67: Rossiter-Thornton | F67: michaelrossiterthornton@gmail.com | G67: Nexus Hospitals (TBD) | J67: Other | K67: Could you please tell me if you an help with a project I am doing? I would like to analyse ~4000 5-minute videos of individual surgical procedures (all variations on the same procedure), looking for techniques used/variations in the procedure, time for each step, instruments used, and tissue resistance as judged by deformation and other visual cues. Thank you | L67: Akhil | M67: 45784 | N67: No Response | O67: AI Solutions | P67: Other Solutions | Q67: Direct | X67: Healthcare/Medical | Y67: No Response | Z67: =IF(C67="","",(IF(OR(P67="Data Annotation",P67="GenAI / LLM Eval",P67="Medical Annotation"),25,IF(OR(P67="AI Consulting",P67="Data Collection"),18,IF(P67<>"",10,0)))+IF(AND(K67<>"",LEN(K67)>50,T67<>""),20,IF(AND(K67<>"",LEN(K67)>20),12,IF(K67<>"",5,0)))+IF(OR(U67="$100k–$500k",U67="$500k+"),20,IF(OR(U67="$25k–$100k"),15,IF(OR(U67="$5k–$25k"),10,IF(U67="$1k–$5k",5,0))))+IF(AND(G67<>"",G67<>"-"),15,IF(G67<>"",8,0))+IF(V67="Immediate (this month)",10,IF(V67="Short-term (1–3 months)",7,IF(V67="Medium (3–6 months)",4,0)))+IF(W67="Yes",10,IF(W67="Unclear",5,0)))) -> 37 | AA67: =IF(Z67="","",IF(Z67>=75,"A",IF(Z67>=50,"B",IF(Z67>=25,"C","D")))) -> C | AB67: =IF(C67="","",IF(AND(R67<>"",S67<>"",U67<>"",V67<>"",W67<>""),"✓ Complete","⚠ MISSING: "&IF(R67="","Call Date, ","")&IF(S67="","Modality, ","")&IF(U67="","Budget, ","")&IF(V67="","Timeline, ","")&IF(W67="","Decision Maker",""))) -> ⚠ MISSING: Call Date, Modality, Budget, Timeline, Decision Maker | AC67: Dead — No Response | AD67: No Response
A68: =IF(C68<>"","AYA-"&TEXT(ROW()-5,"000"),"") -> AYA-063 | B68: 45790 | C68: Dave | D68: Reinhold | F68: dave@venturecpo.com | G68: Venture CPO | H68: Founder | J68: Collective OS | K68: Allow me to introduce you to Dave Reinhold from Venture CPO. Venture CPO is a product management leader and consultancy that helps startups and established companies build, scale, and optimize their products. Specializing in product strategy, market fit, and execution, they offer tailored solutions to accelerate growth and streamline development. With expertise across industries, Venture CPO ensures products meet market demands. They have collaborated with renowned clients such as Fetch Rewards, | L68: Freddie | M68: 45790 | N68: Responded — Interested | O68: AI Solutions | P68: Speech Solutions | Q68: Direct | Y68: Dave has booked meeting with Freddie for Monday, May 19 | Z68: =IF(C68="","",(IF(OR(P68="Data Annotation",P68="GenAI / LLM Eval",P68="Medical Annotation"),25,IF(OR(P68="AI Consulting",P68="Data Collection"),18,IF(P68<>"",10,0)))+IF(AND(K68<>"",LEN(K68)>50,T68<>""),20,IF(AND(K68<>"",LEN(K68)>20),12,IF(K68<>"",5,0)))+IF(OR(U68="$100k–$500k",U68="$500k+"),20,IF(OR(U68="$25k–$100k"),15,IF(OR(U68="$5k–$25k"),10,IF(U68="$1k–$5k",5,0))))+IF(AND(G68<>"",G68<>"-"),15,IF(G68<>"",8,0))+IF(V68="Immediate (this month)",10,IF(V68="Short-term (1–3 months)",7,IF(V68="Medium (3–6 months)",4,0)))+IF(W68="Yes",10,IF(W68="Unclear",5,0)))) -> 37 | AA68: =IF(Z68="","",IF(Z68>=75,"A",IF(Z68>=50,"B",IF(Z68>=25,"C","D")))) -> C | AB68: =IF(C68="","",IF(AND(R68<>"",S68<>"",U68<>"",V68<>"",W68<>""),"✓ Complete","⚠ MISSING: "&IF(R68="","Call Date, ","")&IF(S68="","Modality, ","")&IF(U68="","Budget, ","")&IF(V68="","Timeline, ","")&IF(W68="","Decision Maker",""))) -> ⚠ MISSING: Call Date, Modality, Budget, Timeline, Decision Maker | AC68: Discovery Complete
A69: =IF(C69<>"","AYA-"&TEXT(ROW()-5,"000"),"") -> AYA-064 | B69: 45791 | C69: Nicolas | D69: Pageaud | F69: nicolas.pageaud@raidium.eu | G69: Raidium | J69: Search Engine | K69: Hello, I am reaching out to you because we are looking for a partner to annotate a large dataset of 3D medical images (segmentation of lesions or organs on CT or MRI scans). You can contact me back by sending me an email at Nicolas.pageaud@raidium.eu. We will be pleased to present you the project in more detail and answer any questions you may have in the follow up mails and calls. Best regards, Nicolas | L69: Akhil | M69: 45791 | N69: Responded — Not a Fit | O69: Data Annotation | P69: CV Annotation | Q69: Direct | X69: Healthcare/Medical | Y69: AyaData submitted a proposal for Raidium’s 3D oncology image annotation project on May 31, 2025. Nicolas Pageaud from Raidium provided feedback on June 2, 2025, questioning the pricing assumptions, the profile of medical annotators, and the terminology used for billing (study vs. exam/lesion), and provided sample data for clarification. Akhil Singh responded on June 2, 2025, requesting 48 hours to review the feedback and sample data to revise the proposal. Akhil Singh introduced Marvin Alamu, | Z69: =IF(C69="","",(IF(OR(P69="Data Annotation",P69="GenAI / LLM Eval",P69="Medical Annotation"),25,IF(OR(P69="AI Consulting",P69="Data Collection"),18,IF(P69<>"",10,0)))+IF(AND(K69<>"",LEN(K69)>50,T69<>""),20,IF(AND(K69<>"",LEN(K69)>20),12,IF(K69<>"",5,0)))+IF(OR(U69="$100k–$500k",U69="$500k+"),20,IF(OR(U69="$25k–$100k"),15,IF(OR(U69="$5k–$25k"),10,IF(U69="$1k–$5k",5,0))))+IF(AND(G69<>"",G69<>"-"),15,IF(G69<>"",8,0))+IF(V69="Immediate (this month)",10,IF(V69="Short-term (1–3 months)",7,IF(V69="Medium (3–6 months)",4,0)))+IF(W69="Yes",10,IF(W69="Unclear",5,0)))) -> 37 | AA69: =IF(Z69="","",IF(Z69>=75,"A",IF(Z69>=50,"B",IF(Z69>=25,"C","D")))) -> C | AB69: =IF(C69="","",IF(AND(R69<>"",S69<>"",U69<>"",V69<>"",W69<>""),"✓ Complete","⚠ MISSING: "&IF(R69="","Call Date, ","")&IF(S69="","Modality, ","")&IF(U69="","Budget, ","")&IF(V69="","Timeline, ","")&IF(W69="","Decision Maker",""))) -> ⚠ MISSING: Call Date, Modality, Budget, Timeline, Decision Maker | AC69: Dead — Not a Fit | AD69: Not a Fit
A70: =IF(C70<>"","AYA-"&TEXT(ROW()-5,"000"),"") -> AYA-065 | B70: 45794 | C70: Dong | D70: Huang | F70: dhuang@curvepoint.ai | G70: Curve Point | J70: Search Engine | K70: We're looking for an annotation service that can do the following: 1. Annotate multi-person SMPLX from RGB video frames from top-down and tilt-down (e.g., 45 degree) view points. Each SMPLX has metric translations and metric body sizes in the camera 3D coordinate system, with annotation format similar to the output of (multi-hmr and sat-hmr) 2. Edit individual SMPLX for better quality in the 3D camera coordinate system, including add, delete, adjust global translation/orientation and body limbs | L70: Akhil | M70: 45794 | N70: Responded — Interested | O70: Data Annotation | P70: LiDAR Annotation | Q70: Direct | X70: Automotive/AV | Y70: Sent 3 follow-ups with Dong Huang. Waiting for sample RAW image/frame data and expected annotation format from Dong Huang for POC. Waiting for detailed annotation guidelines from Dong Huang. Waiting for mutual NDA template from Dong Huang's colleagues. | Z70: =IF(C70="","",(IF(OR(P70="Data Annotation",P70="GenAI / LLM Eval",P70="Medical Annotation"),25,IF(OR(P70="AI Consulting",P70="Data Collection"),18,IF(P70<>"",10,0)))+IF(AND(K70<>"",LEN(K70)>50,T70<>""),20,IF(AND(K70<>"",LEN(K70)>20),12,IF(K70<>"",5,0)))+IF(OR(U70="$100k–$500k",U70="$500k+"),20,IF(OR(U70="$25k–$100k"),15,IF(OR(U70="$5k–$25k"),10,IF(U70="$1k–$5k",5,0))))+IF(AND(G70<>"",G70<>"-"),15,IF(G70<>"",8,0))+IF(V70="Immediate (this month)",10,IF(V70="Short-term (1–3 months)",7,IF(V70="Medium (3–6 months)",4,0)))+IF(W70="Yes",10,IF(W70="Unclear",5,0)))) -> 37 | AA70: =IF(Z70="","",IF(Z70>=75,"A",IF(Z70>=50,"B",IF(Z70>=25,"C","D")))) -> C | AB70: =IF(C70="","",IF(AND(R70<>"",S70<>"",U70<>"",V70<>"",W70<>""),"✓ Complete","⚠ MISSING: "&IF(R70="","Call Date, ","")&IF(S70="","Modality, ","")&IF(U70="","Budget, ","")&IF(V70="","Timeline, ","")&IF(W70="","Decision Maker",""))) -> ⚠ MISSING: Call Date, Modality, Budget, Timeline, Decision Maker | AC70: Discovery Complete
A71: =IF(C71<>"","AYA-"&TEXT(ROW()-5,"000"),"") -> AYA-066 | B71: 45798 | C71: Hanwen | D71: Zhang | F71: hanwen6@illinois.edu | G71: MIT & UIUC Joint AI Laboratory | J71: Cold Outreach | K71: Dear Aya Data Team: Hello, we are an AI research laboratory jointly established by top North American universities including MIT and UIUC, dedicated to cutting-edge artificial intelligence application research. Our team consists of researchers from prestigious institutions, and we are looking for suitable data partners to explore potential collaboration opportunities. Project Requirements We are conducting a large-scale research project that requires extensive computer screen recording data, th | L71: Akhil | M71: 45798 | N71: Responded — Interested | O71: Data Annotation | P71: LiDAR Annotation | Q71: Direct | X71: Other | Y71: Paid PIlot - Converted to Client | Z71: =IF(C71="","",(IF(OR(P71="Data Annotation",P71="GenAI / LLM Eval",P71="Medical Annotation"),25,IF(OR(P71="AI Consulting",P71="Data Collection"),18,IF(P71<>"",10,0)))+IF(AND(K71<>"",LEN(K71)>50,T71<>""),20,IF(AND(K71<>"",LEN(K71)>20),12,IF(K71<>"",5,0)))+IF(OR(U71="$100k–$500k",U71="$500k+"),20,IF(OR(U71="$25k–$100k"),15,IF(OR(U71="$5k–$25k"),10,IF(U71="$1k–$5k",5,0))))+IF(AND(G71<>"",G71<>"-"),15,IF(G71<>"",8,0))+IF(V71="Immediate (this month)",10,IF(V71="Short-term (1–3 months)",7,IF(V71="Medium (3–6 months)",4,0)))+IF(W71="Yes",10,IF(W71="Unclear",5,0)))) -> 37 | AA71: =IF(Z71="","",IF(Z71>=75,"A",IF(Z71>=50,"B",IF(Z71>=25,"C","D")))) -> C | AB71: =IF(C71="","",IF(AND(R71<>"",S71<>"",U71<>"",V71<>"",W71<>""),"✓ Complete","⚠ MISSING: "&IF(R71="","Call Date, ","")&IF(S71="","Modality, ","")&IF(U71="","Budget, ","")&IF(V71="","Timeline, ","")&IF(W71="","Decision Maker",""))) -> ⚠ MISSING: Call Date, Modality, Budget, Timeline, Decision Maker | AC71: Move to Scoping
A72: =IF(C72<>"","AYA-"&TEXT(ROW()-5,"000"),"") -> AYA-067 | B72: 45798 | C72: Pearl | D72: Tuling | F72: pearl.tuling@mtn.com | G72: Chenosis | J72: Website Form | K72: My name is Pearl, and I represent Chenosis, an API marketplace dedicated to connecting developers and businesses with cutting-edge data and AI solutions. We are currently expanding our platform’s offerings and are very interested in exploring a potential partnership with AYADATA. We would greatly appreciate the opportunity to review your available APIs with the intention of proxying them onto our marketplace. This would allow us to feature your services to a broader audience while ensuring full | L72: Seyram | O72: AI Solutions | P72: CV Annotation | Q72: Direct | Z72: =IF(C72="","",(IF(OR(P72="Data Annotation",P72="GenAI / LLM Eval",P72="Medical Annotation"),25,IF(OR(P72="AI Consulting",P72="Data Collection"),18,IF(P72<>"",10,0)))+IF(AND(K72<>"",LEN(K72)>50,T72<>""),20,IF(AND(K72<>"",LEN(K72)>20),12,IF(K72<>"",5,0)))+IF(OR(U72="$100k–$500k",U72="$500k+"),20,IF(OR(U72="$25k–$100k"),15,IF(OR(U72="$5k–$25k"),10,IF(U72="$1k–$5k",5,0))))+IF(AND(G72<>"",G72<>"-"),15,IF(G72<>"",8,0))+IF(V72="Immediate (this month)",10,IF(V72="Short-term (1–3 months)",7,IF(V72="Medium (3–6 months)",4,0)))+IF(W72="Yes",10,IF(W72="Unclear",5,0)))) -> 37 | AA72: =IF(Z72="","",IF(Z72>=75,"A",IF(Z72>=50,"B",IF(Z72>=25,"C","D")))) -> C | AB72: =IF(C72="","",IF(AND(R72<>"",S72<>"",U72<>"",V72<>"",W72<>""),"✓ Complete","⚠ MISSING: "&IF(R72="","Call Date, ","")&IF(S72="","Modality, ","")&IF(U72="","Budget, ","")&IF(V72="","Timeline, ","")&IF(W72="","Decision Maker",""))) -> ⚠ MISSING: Call Date, Modality, Budget, Timeline, Decision Maker | AC72: New Lead
A73: =IF(C73<>"","AYA-"&TEXT(ROW()-5,"000"),"") -> AYA-068 | B73: 45799 | C73: Luis | D73: Pazos Outon | F73: luis@degasafrica.com | G73: People are requesting projects related to annotating agricultural field boundaries from high-resolution satellite imagery for smallholder farms in Ghana. They need pricing and timelines for annotating 1,000, 3,000, and 10,000 fields, with each field ranging from 1–8 acres, and require the output in GeoJSON format. They are also inquiring about prior experience in annotating farms, particularly smallholder farms. | J73: Cold Outreach | K73: Hi, We’re building a field segmentation model for smallholder farms in Ghana and are seeking a quote for annotating agricultural field boundaries from high-resolution satellite imagery (≤3m preferred). Specifically, we’d like pricing for: - 1,000 fields - 3,000 fields - 10,000 fields Each field ranges from 1–8 acres. We require field boundary polygons in GeoJSON format. Could you please provide estimated pricing and timelines? Do you have prior experience annotating farms, and in particular sma | L73: Seyram | O73: Data Annotation | P73: LiDAR Annotation | Q73: Direct | Z73: =IF(C73="","",(IF(OR(P73="Data Annotation",P73="GenAI / LLM Eval",P73="Medical Annotation"),25,IF(OR(P73="AI Consulting",P73="Data Collection"),18,IF(P73<>"",10,0)))+IF(AND(K73<>"",LEN(K73)>50,T73<>""),20,IF(AND(K73<>"",LEN(K73)>20),12,IF(K73<>"",5,0)))+IF(OR(U73="$100k–$500k",U73="$500k+"),20,IF(OR(U73="$25k–$100k"),15,IF(OR(U73="$5k–$25k"),10,IF(U73="$1k–$5k",5,0))))+IF(AND(G73<>"",G73<>"-"),15,IF(G73<>"",8,0))+IF(V73="Immediate (this month)",10,IF(V73="Short-term (1–3 months)",7,IF(V73="Medium (3–6 months)",4,0)))+IF(W73="Yes",10,IF(W73="Unclear",5,0)))) -> 37 | AA73: =IF(Z73="","",IF(Z73>=75,"A",IF(Z73>=50,"B",IF(Z73>=25,"C","D")))) -> C | AB73: =IF(C73="","",IF(AND(R73<>"",S73<>"",U73<>"",V73<>"",W73<>""),"✓ Complete","⚠ MISSING: "&IF(R73="","Call Date, ","")&IF(S73="","Modality, ","")&IF(U73="","Budget, ","")&IF(V73="","Timeline, ","")&IF(W73="","Decision Maker",""))) -> ⚠ MISSING: Call Date, Modality, Budget, Timeline, Decision Maker | AC73: New Lead
A74: =IF(C74<>"","AYA-"&TEXT(ROW()-5,"000"),"") -> AYA-069 | B74: 45802 | C74: Patrick | D74: Annor | F74: pannor@rakescompany.com | G74: Rakes Company Ltd | H74: IT | I74: Ghana | J74: Cold Outreach | K74: Rakes Company Limited is seeking to engage an AI consultancy to: Train ten of our managers in AI tools and methodologies. Advise on how we can integrate AI services into our existing workflows to boost overall productivity. | L74: Olivia | M74: 45802 | O74: AI Solutions | P74: Medical AI Annotation | Q74: Direct | Y74: Shared proposal after detailed sscoping meeting. Deal lost based on pricing | Z74: =IF(C74="","",(IF(OR(P74="Data Annotation",P74="GenAI / LLM Eval",P74="Medical Annotation"),25,IF(OR(P74="AI Consulting",P74="Data Collection"),18,IF(P74<>"",10,0)))+IF(AND(K74<>"",LEN(K74)>50,T74<>""),20,IF(AND(K74<>"",LEN(K74)>20),12,IF(K74<>"",5,0)))+IF(OR(U74="$100k–$500k",U74="$500k+"),20,IF(OR(U74="$25k–$100k"),15,IF(OR(U74="$5k–$25k"),10,IF(U74="$1k–$5k",5,0))))+IF(AND(G74<>"",G74<>"-"),15,IF(G74<>"",8,0))+IF(V74="Immediate (this month)",10,IF(V74="Short-term (1–3 months)",7,IF(V74="Medium (3–6 months)",4,0)))+IF(W74="Yes",10,IF(W74="Unclear",5,0)))) -> 37 | AA74: =IF(Z74="","",IF(Z74>=75,"A",IF(Z74>=50,"B",IF(Z74>=25,"C","D")))) -> C | AB74: =IF(C74="","",IF(AND(R74<>"",S74<>"",U74<>"",V74<>"",W74<>""),"✓ Complete","⚠ MISSING: "&IF(R74="","Call Date, ","")&IF(S74="","Modality, ","")&IF(U74="","Budget, ","")&IF(V74="","Timeline, ","")&IF(W74="","Decision Maker",""))) -> ⚠ MISSING: Call Date, Modality, Budget, Timeline, Decision Maker | AC74: Dead — Lost to Competitor | AD74: Lost to Competitor
A75: =IF(C75<>"","AYA-"&TEXT(ROW()-5,"000"),"") -> AYA-070 | B75: 45803 | C75: Sarah | D75: Annam | F75: Sannam2464@gmail.com | G75: Pan African Savings & Loans | H75: Gender Lead | J75: LinkedIn | K75: Book A Demo: I look forward to Knowing how the tool works | L75: Olivia | O75: AI Solutions | P75: GenAI Annotation | Q75: Direct | Z75: =IF(C75="","",(IF(OR(P75="Data Annotation",P75="GenAI / LLM Eval",P75="Medical Annotation"),25,IF(OR(P75="AI Consulting",P75="Data Collection"),18,IF(P75<>"",10,0)))+IF(AND(K75<>"",LEN(K75)>50,T75<>""),20,IF(AND(K75<>"",LEN(K75)>20),12,IF(K75<>"",5,0)))+IF(OR(U75="$100k–$500k",U75="$500k+"),20,IF(OR(U75="$25k–$100k"),15,IF(OR(U75="$5k–$25k"),10,IF(U75="$1k–$5k",5,0))))+IF(AND(G75<>"",G75<>"-"),15,IF(G75<>"",8,0))+IF(V75="Immediate (this month)",10,IF(V75="Short-term (1–3 months)",7,IF(V75="Medium (3–6 months)",4,0)))+IF(W75="Yes",10,IF(W75="Unclear",5,0)))) -> 37 | AA75: =IF(Z75="","",IF(Z75>=75,"A",IF(Z75>=50,"B",IF(Z75>=25,"C","D")))) -> C | AB75: =IF(C75="","",IF(AND(R75<>"",S75<>"",U75<>"",V75<>"",W75<>""),"✓ Complete","⚠ MISSING: "&IF(R75="","Call Date, ","")&IF(S75="","Modality, ","")&IF(U75="","Budget, ","")&IF(V75="","Timeline, ","")&IF(W75="","Decision Maker",""))) -> ⚠ MISSING: Call Date, Modality, Budget, Timeline, Decision Maker | AC75: New Lead
A76: =IF(C76<>"","AYA-"&TEXT(ROW()-5,"000"),"") -> AYA-071 | B76: 45805 | C76: Kilian | D76: Maier | F76: k.maier@plentyco.net | G76: Plentyco | J76: Search Engine | K76: FREE PILOT REQUEST: We have prepared a little data set for the pilot. https://we.tl/t-uTWE0TiWjJ In the ZIP archive we have included 20 sample pictures and a PDF. In those sample pictures we need the entire surface of the gift cards annotated with polygons. The corresponding class names for annotation of the gift cards are also included in the PDF. This is a sample case for us since we are looking for a long term partner in labeling services. If everything works out as expected, we want to ha | L76: Seyram | O76: Data Annotation | P76: Other Solutions | Q76: Direct | Z76: =IF(C76="","",(IF(OR(P76="Data Annotation",P76="GenAI / LLM Eval",P76="Medical Annotation"),25,IF(OR(P76="AI Consulting",P76="Data Collection"),18,IF(P76<>"",10,0)))+IF(AND(K76<>"",LEN(K76)>50,T76<>""),20,IF(AND(K76<>"",LEN(K76)>20),12,IF(K76<>"",5,0)))+IF(OR(U76="$100k–$500k",U76="$500k+"),20,IF(OR(U76="$25k–$100k"),15,IF(OR(U76="$5k–$25k"),10,IF(U76="$1k–$5k",5,0))))+IF(AND(G76<>"",G76<>"-"),15,IF(G76<>"",8,0))+IF(V76="Immediate (this month)",10,IF(V76="Short-term (1–3 months)",7,IF(V76="Medium (3–6 months)",4,0)))+IF(W76="Yes",10,IF(W76="Unclear",5,0)))) -> 37 | AA76: =IF(Z76="","",IF(Z76>=75,"A",IF(Z76>=50,"B",IF(Z76>=25,"C","D")))) -> C | AB76: =IF(C76="","",IF(AND(R76<>"",S76<>"",U76<>"",V76<>"",W76<>""),"✓ Complete","⚠ MISSING: "&IF(R76="","Call Date, ","")&IF(S76="","Modality, ","")&IF(U76="","Budget, ","")&IF(V76="","Timeline, ","")&IF(W76="","Decision Maker",""))) -> ⚠ MISSING: Call Date, Modality, Budget, Timeline, Decision Maker | AC76: New Lead
A77: =IF(C77<>"","AYA-"&TEXT(ROW()-5,"000"),"") -> AYA-072 | B77: 45806 | C77: Chloe | D77: Song | F77: songshujuan@datatang.com | G77: Datang Intelligence Co. Ltd | J77: Website Form | K77: Dear sir/madam, I'm Chloe song from China Datatang , a world-renowned AI training data service company . We're seeking experienced Autonomous driving annotation team now which have experience like #2D #3D#LiDAR #Segmentation #4D We noticed you can provide high-quality autonomous driving data annotation services. so I'm reaching out for collaboration . If it's possible and convenient , you can add my whatsapp for further discussion. +86 15230443742 I am looking forward to further discussing th | L77: Akhil | M77: 45806 | N77: Responded — Interested | O77: Data Annotation | P77: GenAI Annotation | Q77: Direct | X77: Automotive/AV | Y77: Akhil Singh sent an email to Chloe Song on May 29, 2025, introducing Aya Data's experience in autonomous driving data annotation and asking for a convenient time to discuss further. Akhil Singh sent a follow-up email to Chloe Song on May 30, 2025, providing more details about Aya Data's team and experience in autonomous driving and offering to send a case study or sample workflow. | Z77: =IF(C77="","",(IF(OR(P77="Data Annotation",P77="GenAI / LLM Eval",P77="Medical Annotation"),25,IF(OR(P77="AI Consulting",P77="Data Collection"),18,IF(P77<>"",10,0)))+IF(AND(K77<>"",LEN(K77)>50,T77<>""),20,IF(AND(K77<>"",LEN(K77)>20),12,IF(K77<>"",5,0)))+IF(OR(U77="$100k–$500k",U77="$500k+"),20,IF(OR(U77="$25k–$100k"),15,IF(OR(U77="$5k–$25k"),10,IF(U77="$1k–$5k",5,0))))+IF(AND(G77<>"",G77<>"-"),15,IF(G77<>"",8,0))+IF(V77="Immediate (this month)",10,IF(V77="Short-term (1–3 months)",7,IF(V77="Medium (3–6 months)",4,0)))+IF(W77="Yes",10,IF(W77="Unclear",5,0)))) -> 37 | AA77: =IF(Z77="","",IF(Z77>=75,"A",IF(Z77>=50,"B",IF(Z77>=25,"C","D")))) -> C | AB77: =IF(C77="","",IF(AND(R77<>"",S77<>"",U77<>"",V77<>"",W77<>""),"✓ Complete","⚠ MISSING: "&IF(R77="","Call Date, ","")&IF(S77="","Modality, ","")&IF(U77="","Budget, ","")&IF(V77="","Timeline, ","")&IF(W77="","Decision Maker",""))) -> ⚠ MISSING: Call Date, Modality, Budget, Timeline, Decision Maker | AC77: Contacted
A78: =IF(C78<>"","AYA-"&TEXT(ROW()-5,"000"),"") -> AYA-073 | B78: 45806 | C78: Paulius | D78: Rakauskas | F78: paulius@matom.ai | G78: Matom AI | J78: Cold Outreach | K78: Hello, We are searching for point cloud labeling services. Could you please provide me with an offer? Task description in attachment. If you have questions please let me know. Best regards, Paulius www.matom.ai | L78: Akhil | M78: 45806 | N78: Responded — Not a Fit | O78: Data Annotation | P78: Medical AI Annotation | Q78: Direct | X78: Automotive/AV | Y78: Matom.ai decided not to proceed with Aya Data's point cloud labeling service because they decided to move in a different way and the service was no longer needed for the moment. | Z78: =IF(C78="","",(IF(OR(P78="Data Annotation",P78="GenAI / LLM Eval",P78="Medical Annotation"),25,IF(OR(P78="AI Consulting",P78="Data Collection"),18,IF(P78<>"",10,0)))+IF(AND(K78<>"",LEN(K78)>50,T78<>""),20,IF(AND(K78<>"",LEN(K78)>20),12,IF(K78<>"",5,0)))+IF(OR(U78="$100k–$500k",U78="$500k+"),20,IF(OR(U78="$25k–$100k"),15,IF(OR(U78="$5k–$25k"),10,IF(U78="$1k–$5k",5,0))))+IF(AND(G78<>"",G78<>"-"),15,IF(G78<>"",8,0))+IF(V78="Immediate (this month)",10,IF(V78="Short-term (1–3 months)",7,IF(V78="Medium (3–6 months)",4,0)))+IF(W78="Yes",10,IF(W78="Unclear",5,0)))) -> 37 | AA78: =IF(Z78="","",IF(Z78>=75,"A",IF(Z78>=50,"B",IF(Z78>=25,"C","D")))) -> C | AB78: =IF(C78="","",IF(AND(R78<>"",S78<>"",U78<>"",V78<>"",W78<>""),"✓ Complete","⚠ MISSING: "&IF(R78="","Call Date, ","")&IF(S78="","Modality, ","")&IF(U78="","Budget, ","")&IF(V78="","Timeline, ","")&IF(W78="","Decision Maker",""))) -> ⚠ MISSING: Call Date, Modality, Budget, Timeline, Decision Maker | AC78: Dead — Not a Fit | AD78: Not a Fit
A79: =IF(C79<>"","AYA-"&TEXT(ROW()-5,"000"),"") -> AYA-074 | B79: 45807 | C79: Olena | D79: Lejas | F79: olena.lejas@gomotive.com | G79: Gomotive | J79: Website Form | K79: We are looking for service providers for perception annotation in case we need additional help. Our annotation tool is in English so A2 -B1 English skills are required (ability to understand written language even if the person does not speak fluently). We also need real time annotation support for all US time zones and potentially EU. I would appreciate the following information: what would be the hourly rate for an annotator? -how quickly can you provide service in case of an emergency need? -c | L79: Akhil | M79: 45807 | N79: Responded — Interested | O79: Data Annotation | P79: Other Solutions | Q79: Direct | X79: Automotive/AV | Y79: Olena Lejas from GoMotive reached out to Aya Data for perception annotation services, needing 40-50 annotators with English skills (A2-B1) and real-time support for all US and potentially EU time zones. She inquired about hourly rates, emergency service speed, timezone support, and GDPR compliance. Akhil Singh responded, providing answers to her questions: Hourly rates: Typically $6.50 to $9.50/hour, depending on complexity and needs. Emergency support: Resources can be activated within 24-48 h | Z79: =IF(C79="","",(IF(OR(P79="Data Annotation",P79="GenAI / LLM Eval",P79="Medical Annotation"),25,IF(OR(P79="AI Consulting",P79="Data Collection"),18,IF(P79<>"",10,0)))+IF(AND(K79<>"",LEN(K79)>50,T79<>""),20,IF(AND(K79<>"",LEN(K79)>20),12,IF(K79<>"",5,0)))+IF(OR(U79="$100k–$500k",U79="$500k+"),20,IF(OR(U79="$25k–$100k"),15,IF(OR(U79="$5k–$25k"),10,IF(U79="$1k–$5k",5,0))))+IF(AND(G79<>"",G79<>"-"),15,IF(G79<>"",8,0))+IF(V79="Immediate (this month)",10,IF(V79="Short-term (1–3 months)",7,IF(V79="Medium (3–6 months)",4,0)))+IF(W79="Yes",10,IF(W79="Unclear",5,0)))) -> 37 | AA79: =IF(Z79="","",IF(Z79>=75,"A",IF(Z79>=50,"B",IF(Z79>=25,"C","D")))) -> C | AB79: =IF(C79="","",IF(AND(R79<>"",S79<>"",U79<>"",V79<>"",W79<>""),"✓ Complete","⚠ MISSING: "&IF(R79="","Call Date, ","")&IF(S79="","Modality, ","")&IF(U79="","Budget, ","")&IF(V79="","Timeline, ","")&IF(W79="","Decision Maker",""))) -> ⚠ MISSING: Call Date, Modality, Budget, Timeline, Decision Maker | AC79: Contacted
A80: =IF(C80<>"","AYA-"&TEXT(ROW()-5,"000"),"") -> AYA-075 | B80: 45809 | C80: Solomon | D80: Andoh | F80: solomon@wgghana.com | G80: Waltergates Ghana Ltd | H80: CEO | J80: LinkedIn | K80: Want to see demo and take decision [website: wgghana.com] | M80: 45809 | N80: Responded — Interested | O80: AI Solutions | P80: Other Solutions | Q80: Direct | X80: Tech/SaaS | Y80: Client travelled and said he would call back when he is in town | Z80: =IF(C80="","",(IF(OR(P80="Data Annotation",P80="GenAI / LLM Eval",P80="Medical Annotation"),25,IF(OR(P80="AI Consulting",P80="Data Collection"),18,IF(P80<>"",10,0)))+IF(AND(K80<>"",LEN(K80)>50,T80<>""),20,IF(AND(K80<>"",LEN(K80)>20),12,IF(K80<>"",5,0)))+IF(OR(U80="$100k–$500k",U80="$500k+"),20,IF(OR(U80="$25k–$100k"),15,IF(OR(U80="$5k–$25k"),10,IF(U80="$1k–$5k",5,0))))+IF(AND(G80<>"",G80<>"-"),15,IF(G80<>"",8,0))+IF(V80="Immediate (this month)",10,IF(V80="Short-term (1–3 months)",7,IF(V80="Medium (3–6 months)",4,0)))+IF(W80="Yes",10,IF(W80="Unclear",5,0)))) -> 37 | AA80: =IF(Z80="","",IF(Z80>=75,"A",IF(Z80>=50,"B",IF(Z80>=25,"C","D")))) -> C | AB80: =IF(C80="","",IF(AND(R80<>"",S80<>"",U80<>"",V80<>"",W80<>""),"✓ Complete","⚠ MISSING: "&IF(R80="","Call Date, ","")&IF(S80="","Modality, ","")&IF(U80="","Budget, ","")&IF(V80="","Timeline, ","")&IF(W80="","Decision Maker",""))) -> ⚠ MISSING: Call Date, Modality, Budget, Timeline, Decision Maker | AC80: Contacted
A81: =IF(C81<>"","AYA-"&TEXT(ROW()-5,"000"),"") -> AYA-076 | B81: 45812 | C81: Taza | D81: Azzim | F81: taha.azzim@visualbehavior.ai | G81: Visual Behavior | H81: Engineer | K81: I hope you're well. I recently came across your e-scooter dataset (here: https://www.ayadata.ai/case-studies/preparing-self-driving-cars-for-the-rise-of-e-scooters/), and I’m very interested in learning more. Could you please share the following information: Pricing and licensing options Key dataset statistics (e.g., number of images, e-scooter instances, labeling methodology, scene diversity) A few sample images, if possible, to get a better sense of the annotation quality and content Any docum | L81: Akhil | M81: 45812 | N81: Responded — Not a Fit | O81: Data Annotation | P81: CV Annotation | Q81: Direct | X81: Other | Y81: Not a fit. Looking for dataset used in one of our porjects | Z81: =IF(C81="","",(IF(OR(P81="Data Annotation",P81="GenAI / LLM Eval",P81="Medical Annotation"),25,IF(OR(P81="AI Consulting",P81="Data Collection"),18,IF(P81<>"",10,0)))+IF(AND(K81<>"",LEN(K81)>50,T81<>""),20,IF(AND(K81<>"",LEN(K81)>20),12,IF(K81<>"",5,0)))+IF(OR(U81="$100k–$500k",U81="$500k+"),20,IF(OR(U81="$25k–$100k"),15,IF(OR(U81="$5k–$25k"),10,IF(U81="$1k–$5k",5,0))))+IF(AND(G81<>"",G81<>"-"),15,IF(G81<>"",8,0))+IF(V81="Immediate (this month)",10,IF(V81="Short-term (1–3 months)",7,IF(V81="Medium (3–6 months)",4,0)))+IF(W81="Yes",10,IF(W81="Unclear",5,0)))) -> 37 | AA81: =IF(Z81="","",IF(Z81>=75,"A",IF(Z81>=50,"B",IF(Z81>=25,"C","D")))) -> C | AB81: =IF(C81="","",IF(AND(R81<>"",S81<>"",U81<>"",V81<>"",W81<>""),"✓ Complete","⚠ MISSING: "&IF(R81="","Call Date, ","")&IF(S81="","Modality, ","")&IF(U81="","Budget, ","")&IF(V81="","Timeline, ","")&IF(W81="","Decision Maker",""))) -> ⚠ MISSING: Call Date, Modality, Budget, Timeline, Decision Maker | AC81: Dead — Not a Fit | AD81: Not a Fit
A82: =IF(C82<>"","AYA-"&TEXT(ROW()-5,"000"),"") -> AYA-077 | B82: 45813 | C82: Gerard | D82: De Mas | F82: gerard.de.mas@upc.edu | G82: Polytechnical University of Catalonia | H82: PhD Student | K82: This is Gerard De Mas, PhD student at the Polytechnical University of Catalonia, working in a project with multiple imaging sensors installed on a vehicle, 1 LIDAR with high-density point clouds and 6 cameras. We record 30s scenes in driving scenarios, with the focus of detecting ALL traffic agents under ANY condition, in both 3D+2D. Could you give us a quotation for 1 batch of 10 scenes? Our budget is tenths of kilo-€. We are looking forward to your response, wether if ok/not. | L82: Akhil | M82: 45813 | N82: Responded — Interested | O82: Data Annotation | P82: Other Solutions | Q82: Direct | X82: Automotive/AV | Y82: POC Completed. 25th June - Pricing Shared | Z82: =IF(C82="","",(IF(OR(P82="Data Annotation",P82="GenAI / LLM Eval",P82="Medical Annotation"),25,IF(OR(P82="AI Consulting",P82="Data Collection"),18,IF(P82<>"",10,0)))+IF(AND(K82<>"",LEN(K82)>50,T82<>""),20,IF(AND(K82<>"",LEN(K82)>20),12,IF(K82<>"",5,0)))+IF(OR(U82="$100k–$500k",U82="$500k+"),20,IF(OR(U82="$25k–$100k"),15,IF(OR(U82="$5k–$25k"),10,IF(U82="$1k–$5k",5,0))))+IF(AND(G82<>"",G82<>"-"),15,IF(G82<>"",8,0))+IF(V82="Immediate (this month)",10,IF(V82="Short-term (1–3 months)",7,IF(V82="Medium (3–6 months)",4,0)))+IF(W82="Yes",10,IF(W82="Unclear",5,0)))) -> 37 | AA82: =IF(Z82="","",IF(Z82>=75,"A",IF(Z82>=50,"B",IF(Z82>=25,"C","D")))) -> C | AB82: =IF(C82="","",IF(AND(R82<>"",S82<>"",U82<>"",V82<>"",W82<>""),"✓ Complete","⚠ MISSING: "&IF(R82="","Call Date, ","")&IF(S82="","Modality, ","")&IF(U82="","Budget, ","")&IF(V82="","Timeline, ","")&IF(W82="","Decision Maker",""))) -> ⚠ MISSING: Call Date, Modality, Budget, Timeline, Decision Maker | AC82: Move to Scoping
A83: =IF(C83<>"","AYA-"&TEXT(ROW()-5,"000"),"") -> AYA-078 | B83: 45817 | C83: Mervyn | D83: W | F83: niumalw@penzoft.com | G83: Penzoft | J83: Search Engine | K83: Hi, we are doing drone mapping services and currently we have a client that requires us to do Palm Oil counting from the drone imagery. Do you have a solution for palm counting? | L83: Other | O83: Data Annotation | P83: CV Annotation | Q83: Direct | Z83: =IF(C83="","",(IF(OR(P83="Data Annotation",P83="GenAI / LLM Eval",P83="Medical Annotation"),25,IF(OR(P83="AI Consulting",P83="Data Collection"),18,IF(P83<>"",10,0)))+IF(AND(K83<>"",LEN(K83)>50,T83<>""),20,IF(AND(K83<>"",LEN(K83)>20),12,IF(K83<>"",5,0)))+IF(OR(U83="$100k–$500k",U83="$500k+"),20,IF(OR(U83="$25k–$100k"),15,IF(OR(U83="$5k–$25k"),10,IF(U83="$1k–$5k",5,0))))+IF(AND(G83<>"",G83<>"-"),15,IF(G83<>"",8,0))+IF(V83="Immediate (this month)",10,IF(V83="Short-term (1–3 months)",7,IF(V83="Medium (3–6 months)",4,0)))+IF(W83="Yes",10,IF(W83="Unclear",5,0)))) -> 37 | AA83: =IF(Z83="","",IF(Z83>=75,"A",IF(Z83>=50,"B",IF(Z83>=25,"C","D")))) -> C | AB83: =IF(C83="","",IF(AND(R83<>"",S83<>"",U83<>"",V83<>"",W83<>""),"✓ Complete","⚠ MISSING: "&IF(R83="","Call Date, ","")&IF(S83="","Modality, ","")&IF(U83="","Budget, ","")&IF(V83="","Timeline, ","")&IF(W83="","Decision Maker",""))) -> ⚠ MISSING: Call Date, Modality, Budget, Timeline, Decision Maker | AC83: New Lead
A84: =IF(C84<>"","AYA-"&TEXT(ROW()-5,"000"),"") -> AYA-079 | B84: 45817 | C84: Sarah | D84: Romano | F84: sara@myhivescout.com | G84: Hive LLM | J84: Cold Outreach | K84: Hi, I hope this message finds you well. I'm Sara Romano, a scout at HiveLLM, a startup that connects subject matter experts like you with brands to help them find the right people quickly. I'm reaching out to share an exciting opportunity regarding a data annotation project that requires skilled individuals or teams to assist with labeling extensive datasets, focusing on accuracy and precision for machine learning model development. The project budget is set at $75,000. The client hasn't receiv | L84: Akhil | M84: 45817 | N84: No Response | O84: Data Annotation | P84: CV Annotation | Q84: Direct | X84: Tech/SaaS | Y84: Sara Romano's initial email is to present an annotation project opportunity to Aya Data, for machine learning model development, and to connect them with the client. 2 follows up - 1 per week - No Response | Z84: =IF(C84="","",(IF(OR(P84="Data Annotation",P84="GenAI / LLM Eval",P84="Medical Annotation"),25,IF(OR(P84="AI Consulting",P84="Data Collection"),18,IF(P84<>"",10,0)))+IF(AND(K84<>"",LEN(K84)>50,T84<>""),20,IF(AND(K84<>"",LEN(K84)>20),12,IF(K84<>"",5,0)))+IF(OR(U84="$100k–$500k",U84="$500k+"),20,IF(OR(U84="$25k–$100k"),15,IF(OR(U84="$5k–$25k"),10,IF(U84="$1k–$5k",5,0))))+IF(AND(G84<>"",G84<>"-"),15,IF(G84<>"",8,0))+IF(V84="Immediate (this month)",10,IF(V84="Short-term (1–3 months)",7,IF(V84="Medium (3–6 months)",4,0)))+IF(W84="Yes",10,IF(W84="Unclear",5,0)))) -> 37 | AA84: =IF(Z84="","",IF(Z84>=75,"A",IF(Z84>=50,"B",IF(Z84>=25,"C","D")))) -> C | AB84: =IF(C84="","",IF(AND(R84<>"",S84<>"",U84<>"",V84<>"",W84<>""),"✓ Complete","⚠ MISSING: "&IF(R84="","Call Date, ","")&IF(S84="","Modality, ","")&IF(U84="","Budget, ","")&IF(V84="","Timeline, ","")&IF(W84="","Decision Maker",""))) -> ⚠ MISSING: Call Date, Modality, Budget, Timeline, Decision Maker | AC84: Dead — No Response | AD84: No Response
A85: =IF(C85<>"","AYA-"&TEXT(ROW()-5,"000"),"") -> AYA-080 | B85: 45817 | C85: Jonathan | D85: Trinh | F85: jonathan.trinh@elucid.com | G85: Elucid | K85: We are a Boston-based medical technology company with a software product for post-processing CTAs to segment the lumen & wall in a semi-automated manner, followed by automated quantitation of plaque morphology and FFRct. I would like to have a discussion with you regarding your team’s availability and ability to support the manual aspects of the workflow as part of several pending research studies utilizing our cloud-based software system. Please let me know when you have time for a call to di | L85: Akhil | M85: 45817 | N85: Responded — Interested | O85: AI Solutions | P85: Other Solutions | Q85: Direct | X85: Healthcare/Medical | Y85: Thursday, June 12, 2025: Sent an email to Jonathan Trinh outlining a proposal for medical image annotation support, including case studies, POC scenarios and pricing structures. Friday, June 13, 2025: Jonathan Trinh replied, acknowledging receipt of the information and stating that he and his team would review it and get back to Akhil. Wednesday, June 18, 2025: Akhil Singh sent a follow-up email to Jonathan Trinh, stating readiness to proceed with the MNDA and POC. Wednesday, June 25, 2025: A | Z85: =IF(C85="","",(IF(OR(P85="Data Annotation",P85="GenAI / LLM Eval",P85="Medical Annotation"),25,IF(OR(P85="AI Consulting",P85="Data Collection"),18,IF(P85<>"",10,0)))+IF(AND(K85<>"",LEN(K85)>50,T85<>""),20,IF(AND(K85<>"",LEN(K85)>20),12,IF(K85<>"",5,0)))+IF(OR(U85="$100k–$500k",U85="$500k+"),20,IF(OR(U85="$25k–$100k"),15,IF(OR(U85="$5k–$25k"),10,IF(U85="$1k–$5k",5,0))))+IF(AND(G85<>"",G85<>"-"),15,IF(G85<>"",8,0))+IF(V85="Immediate (this month)",10,IF(V85="Short-term (1–3 months)",7,IF(V85="Medium (3–6 months)",4,0)))+IF(W85="Yes",10,IF(W85="Unclear",5,0)))) -> 37 | AA85: =IF(Z85="","",IF(Z85>=75,"A",IF(Z85>=50,"B",IF(Z85>=25,"C","D")))) -> C | AB85: =IF(C85="","",IF(AND(R85<>"",S85<>"",U85<>"",V85<>"",W85<>""),"✓ Complete","⚠ MISSING: "&IF(R85="","Call Date, ","")&IF(S85="","Modality, ","")&IF(U85="","Budget, ","")&IF(V85="","Timeline, ","")&IF(W85="","Decision Maker",""))) -> ⚠ MISSING: Call Date, Modality, Budget, Timeline, Decision Maker | AC85: Discovery Complete
A86: =IF(C86<>"","AYA-"&TEXT(ROW()-5,"000"),"") -> AYA-081 | B86: 45819 | C86: Thomas | D86: Robb | F86: thomas@super.ai | G86: Super AI | J86: Other | K86: I need to extract handwriting from ~185k shipping documents annually. the data needs to stay in EU with <15 minute response time | L86: Akhil | M86: 45819 | N86: Responded — Interested | O86: Data Annotation | P86: Medical AI Annotation | Q86: Direct | X86: Automotive/AV | Y86: Wednesday, 11 June 2025: Responded to Thomas, confirming Aya Data's capability to handle high-volume, time-sensitive annotation workflows with EU compliance. He asked clarifying questions about document size/format, languages/scripts, SLA hours, and data streaming. Wednesday, 25 June 2025: Akhil Singh sent a follow-up email to Thomas, reminding him about the earlier questions and offering a quick call to discuss capabilities and capacity. | Z86: =IF(C86="","",(IF(OR(P86="Data Annotation",P86="GenAI / LLM Eval",P86="Medical Annotation"),25,IF(OR(P86="AI Consulting",P86="Data Collection"),18,IF(P86<>"",10,0)))+IF(AND(K86<>"",LEN(K86)>50,T86<>""),20,IF(AND(K86<>"",LEN(K86)>20),12,IF(K86<>"",5,0)))+IF(OR(U86="$100k–$500k",U86="$500k+"),20,IF(OR(U86="$25k–$100k"),15,IF(OR(U86="$5k–$25k"),10,IF(U86="$1k–$5k",5,0))))+IF(AND(G86<>"",G86<>"-"),15,IF(G86<>"",8,0))+IF(V86="Immediate (this month)",10,IF(V86="Short-term (1–3 months)",7,IF(V86="Medium (3–6 months)",4,0)))+IF(W86="Yes",10,IF(W86="Unclear",5,0)))) -> 37 | AA86: =IF(Z86="","",IF(Z86>=75,"A",IF(Z86>=50,"B",IF(Z86>=25,"C","D")))) -> C | AB86: =IF(C86="","",IF(AND(R86<>"",S86<>"",U86<>"",V86<>"",W86<>""),"✓ Complete","⚠ MISSING: "&IF(R86="","Call Date, ","")&IF(S86="","Modality, ","")&IF(U86="","Budget, ","")&IF(V86="","Timeline, ","")&IF(W86="","Decision Maker",""))) -> ⚠ MISSING: Call Date, Modality, Budget, Timeline, Decision Maker | AC86: Contacted
A87: =IF(C87<>"","AYA-"&TEXT(ROW()-5,"000"),"") -> AYA-082 | B87: 45819 | C87: Andres | D87: Rodriguez | F87: a.rodriguez@floatingrobotics.com | G87: Floating Robotic | J87: Search Engine | K87: We are a Startup in need of annotation services. I have images pre annotated with the current model that we have, but these images need correction of instance segmentation of 5 different objects in the image, usually the correction requires re-doing the mask of 5-10 out of up to 50 elements in the image. Initially we need the annotation for a first dataset that only has 300 images, but over the coming months we will need more datasets with similar conditions, 1000-2000 images. Could you please | L87: Akhil | M87: 45819 | N87: Responded — Interested | O87: Data Annotation | P87: CV Annotation | Q87: Direct | X87: Automotive/AV | Y87: Number of Follow-ups: 2 (Akhil Singh sent the initial reply and then followed up twice, including the latest email). Intent: Andres Rodriguez from Floating Robotics is seeking data annotation services, specifically for correcting instance segmentation masks on images. He initially needs 300 images annotated and expects more datasets (1000-2000 images) in the coming months. Akhil is providing details on their services, pricing, and requesting more information to provide a precise estimate. | Z87: =IF(C87="","",(IF(OR(P87="Data Annotation",P87="GenAI / LLM Eval",P87="Medical Annotation"),25,IF(OR(P87="AI Consulting",P87="Data Collection"),18,IF(P87<>"",10,0)))+IF(AND(K87<>"",LEN(K87)>50,T87<>""),20,IF(AND(K87<>"",LEN(K87)>20),12,IF(K87<>"",5,0)))+IF(OR(U87="$100k–$500k",U87="$500k+"),20,IF(OR(U87="$25k–$100k"),15,IF(OR(U87="$5k–$25k"),10,IF(U87="$1k–$5k",5,0))))+IF(AND(G87<>"",G87<>"-"),15,IF(G87<>"",8,0))+IF(V87="Immediate (this month)",10,IF(V87="Short-term (1–3 months)",7,IF(V87="Medium (3–6 months)",4,0)))+IF(W87="Yes",10,IF(W87="Unclear",5,0)))) -> 37 | AA87: =IF(Z87="","",IF(Z87>=75,"A",IF(Z87>=50,"B",IF(Z87>=25,"C","D")))) -> C | AB87: =IF(C87="","",IF(AND(R87<>"",S87<>"",U87<>"",V87<>"",W87<>""),"✓ Complete","⚠ MISSING: "&IF(R87="","Call Date, ","")&IF(S87="","Modality, ","")&IF(U87="","Budget, ","")&IF(V87="","Timeline, ","")&IF(W87="","Decision Maker",""))) -> ⚠ MISSING: Call Date, Modality, Budget, Timeline, Decision Maker | AC87: Contacted
A88: =IF(C88<>"","AYA-"&TEXT(ROW()-5,"000"),"") -> AYA-083 | B88: 45819 | C88: Daniel | D88: Tofte Schøn | F88: daniel.schon@swarco.com | G88: Swarco | J88: Other | K88: We want 3D Object Detection annotations for Lidar data, we want to know the price of labeling +3000 lidar scans, where only vehicles should be annotated. | L88: Akhil | M88: 45819 | N88: Responded — Interested | O88: Data Annotation | P88: CV Annotation | Q88: Direct | X88: Automotive/AV | Y88: Daniel Tofte Schøn from Swarco reached out for 3D Object Detection annotations for Lidar data, specifically for over 3000 scans focusing on vehicles. Followed up twice, once to provide general hourly rates and ask for sample scans, preferred annotation tools, and expected timelines, and again to remind Daniel and re-offer a call or direct sample data submission. The intent is to get the necessary information to provide an accurate quote and secure the project. | Z88: =IF(C88="","",(IF(OR(P88="Data Annotation",P88="GenAI / LLM Eval",P88="Medical Annotation"),25,IF(OR(P88="AI Consulting",P88="Data Collection"),18,IF(P88<>"",10,0)))+IF(AND(K88<>"",LEN(K88)>50,T88<>""),20,IF(AND(K88<>"",LEN(K88)>20),12,IF(K88<>"",5,0)))+IF(OR(U88="$100k–$500k",U88="$500k+"),20,IF(OR(U88="$25k–$100k"),15,IF(OR(U88="$5k–$25k"),10,IF(U88="$1k–$5k",5,0))))+IF(AND(G88<>"",G88<>"-"),15,IF(G88<>"",8,0))+IF(V88="Immediate (this month)",10,IF(V88="Short-term (1–3 months)",7,IF(V88="Medium (3–6 months)",4,0)))+IF(W88="Yes",10,IF(W88="Unclear",5,0)))) -> 37 | AA88: =IF(Z88="","",IF(Z88>=75,"A",IF(Z88>=50,"B",IF(Z88>=25,"C","D")))) -> C | AB88: =IF(C88="","",IF(AND(R88<>"",S88<>"",U88<>"",V88<>"",W88<>""),"✓ Complete","⚠ MISSING: "&IF(R88="","Call Date, ","")&IF(S88="","Modality, ","")&IF(U88="","Budget, ","")&IF(V88="","Timeline, ","")&IF(W88="","Decision Maker",""))) -> ⚠ MISSING: Call Date, Modality, Budget, Timeline, Decision Maker | AC88: Contacted
A89: =IF(C89<>"","AYA-"&TEXT(ROW()-5,"000"),"") -> AYA-084 | B89: 45820 | C89: Lakshya | D89: Sharma | F89: regmls1@ucl.ac.uk | G89: UCL | J89: Search Engine | K89: I am a resident doctor working within a research team at UCL. We would like to anatomically annotate 500 transvaginal ultrasound images. Would Aya Data be able to have radiologists label this dataset for us? Please could you provide an estimate of the cost for this? | L89: Akhil | M89: 45820 | N89: Responded — Interested | O89: Data Annotation | P89: CV Annotation | Q89: Direct | X89: Healthcare/Medical | Y89: Thursday, June 12, 2025: Replied to Lakshya, confirming Aya Data's ability to support the project and asked for more details regarding the specific structures to be labeled, type of labeling (segmentation, point labeling, or classification), need for full radiologist annotation vs. review/validation, and target timeline. I also offered to set up a call or review sample images. Thursday, June 12, 2025: Lakshya Sharma provided detailed answers to my questions, specifying that they need segmentati | Z89: =IF(C89="","",(IF(OR(P89="Data Annotation",P89="GenAI / LLM Eval",P89="Medical Annotation"),25,IF(OR(P89="AI Consulting",P89="Data Collection"),18,IF(P89<>"",10,0)))+IF(AND(K89<>"",LEN(K89)>50,T89<>""),20,IF(AND(K89<>"",LEN(K89)>20),12,IF(K89<>"",5,0)))+IF(OR(U89="$100k–$500k",U89="$500k+"),20,IF(OR(U89="$25k–$100k"),15,IF(OR(U89="$5k–$25k"),10,IF(U89="$1k–$5k",5,0))))+IF(AND(G89<>"",G89<>"-"),15,IF(G89<>"",8,0))+IF(V89="Immediate (this month)",10,IF(V89="Short-term (1–3 months)",7,IF(V89="Medium (3–6 months)",4,0)))+IF(W89="Yes",10,IF(W89="Unclear",5,0)))) -> 37 | AA89: =IF(Z89="","",IF(Z89>=75,"A",IF(Z89>=50,"B",IF(Z89>=25,"C","D")))) -> C | AB89: =IF(C89="","",IF(AND(R89<>"",S89<>"",U89<>"",V89<>"",W89<>""),"✓ Complete","⚠ MISSING: "&IF(R89="","Call Date, ","")&IF(S89="","Modality, ","")&IF(U89="","Budget, ","")&IF(V89="","Timeline, ","")&IF(W89="","Decision Maker",""))) -> ⚠ MISSING: Call Date, Modality, Budget, Timeline, Decision Maker | AC89: Discovery Complete
A90: =IF(C90<>"","AYA-"&TEXT(ROW()-5,"000"),"") -> AYA-085 | B90: 45826 | C90: Ledington | D90: Karl | F90: karl.nexora@proton.me | G90: Nexora AI Systems | H90: AI Product Manager | J90: Search Engine | K90: Hi AYA Data Team, Nexora AI Systems is an innovative Generative AI startup focused on building instruction-aligned, domain-specialized models for high-impact sectors such as healthcare, finance, and retail. Our capabilities span supervised fine-tuning (SFT), reinforcement learning from human feedback (RLHF), and human-in-the-loop (HITL) optimization, ensuring safe, scalable deployment of generative models in production environments. As we prepare to scale our model training pipelines and enter t | L90: Akhil | M90: 45826 | N90: Responded — Interested | O90: AI Solutions | P90: CV Annotation | Q90: Direct | X90: Tech/SaaS | Y90: Wednesday, June 18, 2025: Replied to Karl, suggesting an exploratory call to discuss their priorities and share Aya Data's methodologies and pricing. Wednesday, June 18, 2025: Karl responded, providing more context about Nexora AI's platform and reiterating the need for standardized documentation on Aya Data's execution methodology (SOPs), quality layers, and pricing models before a call. He mentioned this is time-sensitive as their internal model validation sprints conclude next month. Wednes | Z90: =IF(C90="","",(IF(OR(P90="Data Annotation",P90="GenAI / LLM Eval",P90="Medical Annotation"),25,IF(OR(P90="AI Consulting",P90="Data Collection"),18,IF(P90<>"",10,0)))+IF(AND(K90<>"",LEN(K90)>50,T90<>""),20,IF(AND(K90<>"",LEN(K90)>20),12,IF(K90<>"",5,0)))+IF(OR(U90="$100k–$500k",U90="$500k+"),20,IF(OR(U90="$25k–$100k"),15,IF(OR(U90="$5k–$25k"),10,IF(U90="$1k–$5k",5,0))))+IF(AND(G90<>"",G90<>"-"),15,IF(G90<>"",8,0))+IF(V90="Immediate (this month)",10,IF(V90="Short-term (1–3 months)",7,IF(V90="Medium (3–6 months)",4,0)))+IF(W90="Yes",10,IF(W90="Unclear",5,0)))) -> 37 | AA90: =IF(Z90="","",IF(Z90>=75,"A",IF(Z90>=50,"B",IF(Z90>=25,"C","D")))) -> C | AB90: =IF(C90="","",IF(AND(R90<>"",S90<>"",U90<>"",V90<>"",W90<>""),"✓ Complete","⚠ MISSING: "&IF(R90="","Call Date, ","")&IF(S90="","Modality, ","")&IF(U90="","Budget, ","")&IF(V90="","Timeline, ","")&IF(W90="","Decision Maker",""))) -> ⚠ MISSING: Call Date, Modality, Budget, Timeline, Decision Maker | AC90: Discovery Complete
A91: =IF(C91<>"","AYA-"&TEXT(ROW()-5,"000"),"") -> AYA-086 | B91: 45830 | C91: Rebecca | D91: Goba | F91: rebecca.goba@hec.edu | G91: HEC | H91: Independent Consultant | J91: Search Engine | K91: Good day, I hope you’re well. I’m currently working as an Independent Consultant on a validation exercise with a retail client, for an AI enabled digital platform aimed at informal retailers in South Africa. As part of this, we’re looking to identify a suitable tech partner to build an MVP and I would like to send through an RFP for consideration. Please let me know the best email address to send the RFP to. Thank you, Rebecca | L91: Akhil | M91: 45830 | N91: Responded — Interested | O91: AI Solutions | P91: Medical AI Annotation | Q91: Direct | Y91: Tuesday, June 24, 2025: I sent an email to Rebecca, introducing myself, providing case studies, asking questions about the project, and inviting her to send the RFP or schedule a call. Wednesday, June 25, 2025: I sent a follow-up email to Rebecca, reiterating my interest and confirming my email address for the RFP. | Z91: =IF(C91="","",(IF(OR(P91="Data Annotation",P91="GenAI / LLM Eval",P91="Medical Annotation"),25,IF(OR(P91="AI Consulting",P91="Data Collection"),18,IF(P91<>"",10,0)))+IF(AND(K91<>"",LEN(K91)>50,T91<>""),20,IF(AND(K91<>"",LEN(K91)>20),12,IF(K91<>"",5,0)))+IF(OR(U91="$100k–$500k",U91="$500k+"),20,IF(OR(U91="$25k–$100k"),15,IF(OR(U91="$5k–$25k"),10,IF(U91="$1k–$5k",5,0))))+IF(AND(G91<>"",G91<>"-"),15,IF(G91<>"",8,0))+IF(V91="Immediate (this month)",10,IF(V91="Short-term (1–3 months)",7,IF(V91="Medium (3–6 months)",4,0)))+IF(W91="Yes",10,IF(W91="Unclear",5,0)))) -> 37 | AA91: =IF(Z91="","",IF(Z91>=75,"A",IF(Z91>=50,"B",IF(Z91>=25,"C","D")))) -> C | AB91: =IF(C91="","",IF(AND(R91<>"",S91<>"",U91<>"",V91<>"",W91<>""),"✓ Complete","⚠ MISSING: "&IF(R91="","Call Date, ","")&IF(S91="","Modality, ","")&IF(U91="","Budget, ","")&IF(V91="","Timeline, ","")&IF(W91="","Decision Maker",""))) -> ⚠ MISSING: Call Date, Modality, Budget, Timeline, Decision Maker | AC91: Contacted
A92: =IF(C92<>"","AYA-"&TEXT(ROW()-5,"000"),"") -> AYA-087 | B92: 45837 | C92: Brian | D92: Taylor | F92: briantaylor.nextgen@gmail.com | G92: NextGen Consulting Corp. | H92: Head of Business Development | J92: Cold Outreach | K92: Hi Aya Data, I lead business development at a New York based consulting firm with extensive relationships across healthcare, finance, real-estate and other key industries. Our clients ask us of Gen AI services but since we do not maintain an in-house Gen AI team, we are seeking to collaborate with a proven Gen AI provider specializing in Supervised Fine-Tuning (SFT), Reinforcement Learning from Human Feedback (RLHF), adversarial testing and LLM-driven human feedback workflows. We would welcome | L92: Seyram | O92: AI Solutions | Q92: Direct | Z92: =IF(C92="","",(IF(OR(P92="Data Annotation",P92="GenAI / LLM Eval",P92="Medical Annotation"),25,IF(OR(P92="AI Consulting",P92="Data Collection"),18,IF(P92<>"",10,0)))+IF(AND(K92<>"",LEN(K92)>50,T92<>""),20,IF(AND(K92<>"",LEN(K92)>20),12,IF(K92<>"",5,0)))+IF(OR(U92="$100k–$500k",U92="$500k+"),20,IF(OR(U92="$25k–$100k"),15,IF(OR(U92="$5k–$25k"),10,IF(U92="$1k–$5k",5,0))))+IF(AND(G92<>"",G92<>"-"),15,IF(G92<>"",8,0))+IF(V92="Immediate (this month)",10,IF(V92="Short-term (1–3 months)",7,IF(V92="Medium (3–6 months)",4,0)))+IF(W92="Yes",10,IF(W92="Unclear",5,0)))) -> 27 | AA92: =IF(Z92="","",IF(Z92>=75,"A",IF(Z92>=50,"B",IF(Z92>=25,"C","D")))) -> C | AB92: =IF(C92="","",IF(AND(R92<>"",S92<>"",U92<>"",V92<>"",W92<>""),"✓ Complete","⚠ MISSING: "&IF(R92="","Call Date, ","")&IF(S92="","Modality, ","")&IF(U92="","Budget, ","")&IF(V92="","Timeline, ","")&IF(W92="","Decision Maker",""))) -> ⚠ MISSING: Call Date, Modality, Budget, Timeline, Decision Maker | AC92: New Lead
A93: =IF(C93<>"","AYA-"&TEXT(ROW()-5,"000"),"") -> AYA-088 | B93: 45845 | C93: Sebastien | D93: Delorme | F93: sebastien@scopia.tech | G93: Scopia | J93: Website Form | K93: I would like to have semantic segmentation of anatomy done on videos of laparoscopic surgery. Meeting booked by client via calendly for Wed, Jul 9, 2pm | L93: Akhil | M93: 45845 | O93: Data Annotation | P93: CV Annotation | Q93: Direct | X93: Healthcare/Medical | Y93: Completed PoC and pricing; client selected another vendor but is interested in data sourcing for future projects | Z93: =IF(C93="","",(IF(OR(P93="Data Annotation",P93="GenAI / LLM Eval",P93="Medical Annotation"),25,IF(OR(P93="AI Consulting",P93="Data Collection"),18,IF(P93<>"",10,0)))+IF(AND(K93<>"",LEN(K93)>50,T93<>""),20,IF(AND(K93<>"",LEN(K93)>20),12,IF(K93<>"",5,0)))+IF(OR(U93="$100k–$500k",U93="$500k+"),20,IF(OR(U93="$25k–$100k"),15,IF(OR(U93="$5k–$25k"),10,IF(U93="$1k–$5k",5,0))))+IF(AND(G93<>"",G93<>"-"),15,IF(G93<>"",8,0))+IF(V93="Immediate (this month)",10,IF(V93="Short-term (1–3 months)",7,IF(V93="Medium (3–6 months)",4,0)))+IF(W93="Yes",10,IF(W93="Unclear",5,0)))) -> 37 | AA93: =IF(Z93="","",IF(Z93>=75,"A",IF(Z93>=50,"B",IF(Z93>=25,"C","D")))) -> C | AB93: =IF(C93="","",IF(AND(R93<>"",S93<>"",U93<>"",V93<>"",W93<>""),"✓ Complete","⚠ MISSING: "&IF(R93="","Call Date, ","")&IF(S93="","Modality, ","")&IF(U93="","Budget, ","")&IF(V93="","Timeline, ","")&IF(W93="","Decision Maker",""))) -> ⚠ MISSING: Call Date, Modality, Budget, Timeline, Decision Maker | AC93: Dead — Lost to Competitor | AD93: Lost to Competitor
A94: =IF(C94<>"","AYA-"&TEXT(ROW()-5,"000"),"") -> AYA-089 | B94: 45846 | C94: Ahmed | D94: Farghaly | F94: ahmed.farghaly@qsitint.com | G94: QSI International | H94: Business Development Director | J94: Website Form | K94: Dear Sir/Madam, I hope this message finds you well. We are currently working on a new tender opportunity with the Environment Agency – Abu Dhabi that involves leveraging AI vision technology for waste management and monitoring. We would greatly appreciate your collaboration in providing the required data-related scope for this opportunity. We sincerely apologize for the short notice, as the client’s deadline is Thursday 10/7 evening. Could you kindly confirm if you're able to provide both a tech | L94: Akhil | M94: 45846 | N94: Responded — Interested | O94: AI Solutions | P94: LiDAR Annotation | Q94: Direct | X94: Automotive/AV | Y94: Meeting held to discuss 18k annotations; Aya Data can handle annotation but not image sourcing; detailed proposal to be submitted; procurement process may take months | Z94: =IF(C94="","",(IF(OR(P94="Data Annotation",P94="GenAI / LLM Eval",P94="Medical Annotation"),25,IF(OR(P94="AI Consulting",P94="Data Collection"),18,IF(P94<>"",10,0)))+IF(AND(K94<>"",LEN(K94)>50,T94<>""),20,IF(AND(K94<>"",LEN(K94)>20),12,IF(K94<>"",5,0)))+IF(OR(U94="$100k–$500k",U94="$500k+"),20,IF(OR(U94="$25k–$100k"),15,IF(OR(U94="$5k–$25k"),10,IF(U94="$1k–$5k",5,0))))+IF(AND(G94<>"",G94<>"-"),15,IF(G94<>"",8,0))+IF(V94="Immediate (this month)",10,IF(V94="Short-term (1–3 months)",7,IF(V94="Medium (3–6 months)",4,0)))+IF(W94="Yes",10,IF(W94="Unclear",5,0)))) -> 37 | AA94: =IF(Z94="","",IF(Z94>=75,"A",IF(Z94>=50,"B",IF(Z94>=25,"C","D")))) -> C | AB94: =IF(C94="","",IF(AND(R94<>"",S94<>"",U94<>"",V94<>"",W94<>""),"✓ Complete","⚠ MISSING: "&IF(R94="","Call Date, ","")&IF(S94="","Modality, ","")&IF(U94="","Budget, ","")&IF(V94="","Timeline, ","")&IF(W94="","Decision Maker",""))) -> ⚠ MISSING: Call Date, Modality, Budget, Timeline, Decision Maker | AC94: Discovery Complete
A95: =IF(C95<>"","AYA-"&TEXT(ROW()-5,"000"),"") -> AYA-090 | B95: 45848 | C95: Stefan | D95: Ruijsenaars | F95: stefanr@wave.com | G95: Wave | J95: Website Form | K95: Sharing the blurb I'd sent you via the sales enquiry form: I'm an engineer with Wave (wave.com). We're a large fintech company operating mostly on West Africa. About us: https://open.substack.com/pub/randle/p/wave?r=1dkcs&utm_medium=ios We are interested in gathering some ~1000 hours of labelled Wolof speech data so we can use this for training a speech to text model. We currently have about 100 hours thanks to the help of a local team based in Senegal who work with local linguists. On the longe | L95: Freddie | O95: AI Solutions | P95: GenAI Annotation | Q95: Direct | Z95: =IF(C95="","",(IF(OR(P95="Data Annotation",P95="GenAI / LLM Eval",P95="Medical Annotation"),25,IF(OR(P95="AI Consulting",P95="Data Collection"),18,IF(P95<>"",10,0)))+IF(AND(K95<>"",LEN(K95)>50,T95<>""),20,IF(AND(K95<>"",LEN(K95)>20),12,IF(K95<>"",5,0)))+IF(OR(U95="$100k–$500k",U95="$500k+"),20,IF(OR(U95="$25k–$100k"),15,IF(OR(U95="$5k–$25k"),10,IF(U95="$1k–$5k",5,0))))+IF(AND(G95<>"",G95<>"-"),15,IF(G95<>"",8,0))+IF(V95="Immediate (this month)",10,IF(V95="Short-term (1–3 months)",7,IF(V95="Medium (3–6 months)",4,0)))+IF(W95="Yes",10,IF(W95="Unclear",5,0)))) -> 37 | AA95: =IF(Z95="","",IF(Z95>=75,"A",IF(Z95>=50,"B",IF(Z95>=25,"C","D")))) -> C | AB95: =IF(C95="","",IF(AND(R95<>"",S95<>"",U95<>"",V95<>"",W95<>""),"✓ Complete","⚠ MISSING: "&IF(R95="","Call Date, ","")&IF(S95="","Modality, ","")&IF(U95="","Budget, ","")&IF(V95="","Timeline, ","")&IF(W95="","Decision Maker",""))) -> ⚠ MISSING: Call Date, Modality, Budget, Timeline, Decision Maker | AC95: New Lead
A96: =IF(C96<>"","AYA-"&TEXT(ROW()-5,"000"),"") -> AYA-091 | B96: 45853 | C96: Sarthak | D96: Arora | F96: sarthak@madronus.com | G96: Madronos | J96: Search Engine | K96: Hello AyaData, We are seeking professional image annotation services to support the development of a computer vision model. Our dataset consists of images of various houses, and we require polygon annotations for specific features within each image. Here are the key details of our project: Dataset Description: The dataset contains images of residential properties, showcasing a variety of house styles, environments, and angles. The total number of images is approximately 2500. Annotation Type | L96: Akhil | M96: 45853 | N96: Responded — Interested | O96: Data Annotation | P96: Other Solutions | Q96: Direct | X96: Automotive/AV | Y96: Delivered PoC and pricing; waiting for Sarthak’s feedback on annotation quality. | Z96: =IF(C96="","",(IF(OR(P96="Data Annotation",P96="GenAI / LLM Eval",P96="Medical Annotation"),25,IF(OR(P96="AI Consulting",P96="Data Collection"),18,IF(P96<>"",10,0)))+IF(AND(K96<>"",LEN(K96)>50,T96<>""),20,IF(AND(K96<>"",LEN(K96)>20),12,IF(K96<>"",5,0)))+IF(OR(U96="$100k–$500k",U96="$500k+"),20,IF(OR(U96="$25k–$100k"),15,IF(OR(U96="$5k–$25k"),10,IF(U96="$1k–$5k",5,0))))+IF(AND(G96<>"",G96<>"-"),15,IF(G96<>"",8,0))+IF(V96="Immediate (this month)",10,IF(V96="Short-term (1–3 months)",7,IF(V96="Medium (3–6 months)",4,0)))+IF(W96="Yes",10,IF(W96="Unclear",5,0)))) -> 37 | AA96: =IF(Z96="","",IF(Z96>=75,"A",IF(Z96>=50,"B",IF(Z96>=25,"C","D")))) -> C | AB96: =IF(C96="","",IF(AND(R96<>"",S96<>"",U96<>"",V96<>"",W96<>""),"✓ Complete","⚠ MISSING: "&IF(R96="","Call Date, ","")&IF(S96="","Modality, ","")&IF(U96="","Budget, ","")&IF(V96="","Timeline, ","")&IF(W96="","Decision Maker",""))) -> ⚠ MISSING: Call Date, Modality, Budget, Timeline, Decision Maker | AC96: Move to Scoping
A97: =IF(C97<>"","AYA-"&TEXT(ROW()-5,"000"),"") -> AYA-092 | B97: 45854 | C97: Jason | D97: Malvarosa | F97: jason.malvarosa@oracle.com | G97: Oracle | H97: Data Researcher | J97: Cold Outreach | K97: Hi, I’m Jason Malvarosa, Data Researcher at Oracle. I'm currently sourcing reliable data partners for upcoming projects, particularly, Data Acquisition, Annotation, and Labeling. Would you be open to a quick conversation to explore whether your solutions align with our needs? Looking forward to connecting. Best, Jason Malvarosa Data Researcher Mobile: + (63) 9278657013 Oracle Adaptive Intelligence Applications | L97: Seyram | O97: Data Annotation | P97: Medical AI Annotation | Q97: Direct | Z97: =IF(C97="","",(IF(OR(P97="Data Annotation",P97="GenAI / LLM Eval",P97="Medical Annotation"),25,IF(OR(P97="AI Consulting",P97="Data Collection"),18,IF(P97<>"",10,0)))+IF(AND(K97<>"",LEN(K97)>50,T97<>""),20,IF(AND(K97<>"",LEN(K97)>20),12,IF(K97<>"",5,0)))+IF(OR(U97="$100k–$500k",U97="$500k+"),20,IF(OR(U97="$25k–$100k"),15,IF(OR(U97="$5k–$25k"),10,IF(U97="$1k–$5k",5,0))))+IF(AND(G97<>"",G97<>"-"),15,IF(G97<>"",8,0))+IF(V97="Immediate (this month)",10,IF(V97="Short-term (1–3 months)",7,IF(V97="Medium (3–6 months)",4,0)))+IF(W97="Yes",10,IF(W97="Unclear",5,0)))) -> 37 | AA97: =IF(Z97="","",IF(Z97>=75,"A",IF(Z97>=50,"B",IF(Z97>=25,"C","D")))) -> C | AB97: =IF(C97="","",IF(AND(R97<>"",S97<>"",U97<>"",V97<>"",W97<>""),"✓ Complete","⚠ MISSING: "&IF(R97="","Call Date, ","")&IF(S97="","Modality, ","")&IF(U97="","Budget, ","")&IF(V97="","Timeline, ","")&IF(W97="","Decision Maker",""))) -> ⚠ MISSING: Call Date, Modality, Budget, Timeline, Decision Maker | AC97: New Lead
A98: =IF(C98<>"","AYA-"&TEXT(ROW()-5,"000"),"") -> AYA-093 | B98: 45856 | C98: Ritika | D98: Srivastava | F98: ritika.s@acgence.com | G98: Macgence | H98: Data Annotator | J98: Cold Outreach | K98: I hope this message finds you well. My name is Ritika Srivastava, and I am a Data Annotator at Macgence, a global provider of AI and data solutions. At Macgence, we specialize in delivering high-quality datasets for AI training, including services such as: Data annotation Multilingual data collection Pre-labeled Off-the-Shelf (OTS) datasets We are currently seeking to collaborate with experienced vendors who can provide OTS datasets across the following domains: Image, video, text, and audio dat | L98: Seyram | O98: Data Annotation | P98: CV Annotation | Q98: Direct | Z98: =IF(C98="","",(IF(OR(P98="Data Annotation",P98="GenAI / LLM Eval",P98="Medical Annotation"),25,IF(OR(P98="AI Consulting",P98="Data Collection"),18,IF(P98<>"",10,0)))+IF(AND(K98<>"",LEN(K98)>50,T98<>""),20,IF(AND(K98<>"",LEN(K98)>20),12,IF(K98<>"",5,0)))+IF(OR(U98="$100k–$500k",U98="$500k+"),20,IF(OR(U98="$25k–$100k"),15,IF(OR(U98="$5k–$25k"),10,IF(U98="$1k–$5k",5,0))))+IF(AND(G98<>"",G98<>"-"),15,IF(G98<>"",8,0))+IF(V98="Immediate (this month)",10,IF(V98="Short-term (1–3 months)",7,IF(V98="Medium (3–6 months)",4,0)))+IF(W98="Yes",10,IF(W98="Unclear",5,0)))) -> 37 | AA98: =IF(Z98="","",IF(Z98>=75,"A",IF(Z98>=50,"B",IF(Z98>=25,"C","D")))) -> C | AB98: =IF(C98="","",IF(AND(R98<>"",S98<>"",U98<>"",V98<>"",W98<>""),"✓ Complete","⚠ MISSING: "&IF(R98="","Call Date, ","")&IF(S98="","Modality, ","")&IF(U98="","Budget, ","")&IF(V98="","Timeline, ","")&IF(W98="","Decision Maker",""))) -> ⚠ MISSING: Call Date, Modality, Budget, Timeline, Decision Maker | AC98: New Lead
A99: =IF(C99<>"","AYA-"&TEXT(ROW()-5,"000"),"") -> AYA-094 | B99: 45856 | C99: Jack | D99: Nan | F99: jack@col-media.com | G99: COL Group | J99: Search Engine | L99: Seyram | O99: Data Annotation | P99: GenAI Annotation | Q99: Direct | Z99: =IF(C99="","",(IF(OR(P99="Data Annotation",P99="GenAI / LLM Eval",P99="Medical Annotation"),25,IF(OR(P99="AI Consulting",P99="Data Collection"),18,IF(P99<>"",10,0)))+IF(AND(K99<>"",LEN(K99)>50,T99<>""),20,IF(AND(K99<>"",LEN(K99)>20),12,IF(K99<>"",5,0)))+IF(OR(U99="$100k–$500k",U99="$500k+"),20,IF(OR(U99="$25k–$100k"),15,IF(OR(U99="$5k–$25k"),10,IF(U99="$1k–$5k",5,0))))+IF(AND(G99<>"",G99<>"-"),15,IF(G99<>"",8,0))+IF(V99="Immediate (this month)",10,IF(V99="Short-term (1–3 months)",7,IF(V99="Medium (3–6 months)",4,0)))+IF(W99="Yes",10,IF(W99="Unclear",5,0)))) -> 25 | AA99: =IF(Z99="","",IF(Z99>=75,"A",IF(Z99>=50,"B",IF(Z99>=25,"C","D")))) -> C | AB99: =IF(C99="","",IF(AND(R99<>"",S99<>"",U99<>"",V99<>"",W99<>""),"✓ Complete","⚠ MISSING: "&IF(R99="","Call Date, ","")&IF(S99="","Modality, ","")&IF(U99="","Budget, ","")&IF(V99="","Timeline, ","")&IF(W99="","Decision Maker",""))) -> ⚠ MISSING: Call Date, Modality, Budget, Timeline, Decision Maker | AC99: New Lead
A100: =IF(C100<>"","AYA-"&TEXT(ROW()-5,"000"),"") -> AYA-095 | B100: 45860 | C100: Agnieszka | D100: Zareba | F100: agnieszka.zareba@pwc.com | G100: PWC (Poland) | J100: LinkedIn | K100: Dear Sir/Madam, I hope you are well. My name is Agnieszka Zareba, and I am a remote sensing specialist at PwC Poland. I am reaching out to ask whether your company provides automatic field boundaries capabilities. We are exploring solutions on behalf of the European Commission's Directorate-General for Agriculture and Rural Development (DG AGRI), as this feature is of significant interest for their operations. If you do offer this capability, would it be possible to arrange a meeting to discuss | L100: Other | O100: Data Annotation | P100: CV Annotation | Q100: Direct | Z100: =IF(C100="","",(IF(OR(P100="Data Annotation",P100="GenAI / LLM Eval",P100="Medical Annotation"),25,IF(OR(P100="AI Consulting",P100="Data Collection"),18,IF(P100<>"",10,0)))+IF(AND(K100<>"",LEN(K100)>50,T100<>""),20,IF(AND(K100<>"",LEN(K100)>20),12,IF(K100<>"",5,0)))+IF(OR(U100="$100k–$500k",U100="$500k+"),20,IF(OR(U100="$25k–$100k"),15,IF(OR(U100="$5k–$25k"),10,IF(U100="$1k–$5k",5,0))))+IF(AND(G100<>"",G100<>"-"),15,IF(G100<>"",8,0))+IF(V100="Immediate (this month)",10,IF(V100="Short-term (1–3 months)",7,IF(V100="Medium (3–6 months)",4,0)))+IF(W100="Yes",10,IF(W100="Unclear",5,0)))) -> 37 | AA100: =IF(Z100="","",IF(Z100>=75,"A",IF(Z100>=50,"B",IF(Z100>=25,"C","D")))) -> C | AB100: =IF(C100="","",IF(AND(R100<>"",S100<>"",U100<>"",V100<>"",W100<>""),"✓ Complete","⚠ MISSING: "&IF(R100="","Call Date, ","")&IF(S100="","Modality, ","")&IF(U100="","Budget, ","")&IF(V100="","Timeline, ","")&IF(W100="","Decision Maker",""))) -> ⚠ MISSING: Call Date, Modality, Budget, Timeline, Decision Maker | AC100: New Lead
A101: =IF(C101<>"","AYA-"&TEXT(ROW()-5,"000"),"") -> AYA-096 | B101: 45861 | C101: Jay | D101: Carter | F101: ay.carter@1nhealth.com | G101: 1nheath | J101: Search Engine | K101: We need data labelling services for CVI Ulcers, at least 500 images, we're not sure of the upper limit as yet | L101: Akhil | M101: 45861 | N101: Responded — Interested | O101: Data Annotation | P101: Medical AI Annotation | Q101: Direct | X101: Healthcare/Medical | Y101: Initial request acknowledged; Akhil to follow up with discussion; awaiting further details from client. | Z101: =IF(C101="","",(IF(OR(P101="Data Annotation",P101="GenAI / LLM Eval",P101="Medical Annotation"),25,IF(OR(P101="AI Consulting",P101="Data Collection"),18,IF(P101<>"",10,0)))+IF(AND(K101<>"",LEN(K101)>50,T101<>""),20,IF(AND(K101<>"",LEN(K101)>20),12,IF(K101<>"",5,0)))+IF(OR(U101="$100k–$500k",U101="$500k+"),20,IF(OR(U101="$25k–$100k"),15,IF(OR(U101="$5k–$25k"),10,IF(U101="$1k–$5k",5,0))))+IF(AND(G101<>"",G101<>"-"),15,IF(G101<>"",8,0))+IF(V101="Immediate (this month)",10,IF(V101="Short-term (1–3 months)",7,IF(V101="Medium (3–6 months)",4,0)))+IF(W101="Yes",10,IF(W101="Unclear",5,0)))) -> 37 | AA101: =IF(Z101="","",IF(Z101>=75,"A",IF(Z101>=50,"B",IF(Z101>=25,"C","D")))) -> C | AB101: =IF(C101="","",IF(AND(R101<>"",S101<>"",U101<>"",V101<>"",W101<>""),"✓ Complete","⚠ MISSING: "&IF(R101="","Call Date, ","")&IF(S101="","Modality, ","")&IF(U101="","Budget, ","")&IF(V101="","Timeline, ","")&IF(W101="","Decision Maker",""))) -> ⚠ MISSING: Call Date, Modality, Budget, Timeline, Decision Maker | AC101: Contacted
A102: =IF(C102<>"","AYA-"&TEXT(ROW()-5,"000"),"") -> AYA-097 | B102: 45862 | C102: Yves | D102: Hoppenot | F102: yves.hoppenot@naverlabs.com | G102: Naver Labs | H102: Europe Program Manager Office | J102: Search Engine | K102: I am working for Naver Labs Europe, in France, focus on research in AI for Robotics. It belongs to the Korean company Naver. In this context, we are looking for different type of annotation across a collection of images coming from different videos, in order to train different models. We have already captured several scenes composed of one to seven people, through five 5k synchronized cameras. So we would like to have different annotations on these collection of images: Human skeleton annotati | L102: Akhil | M102: 45862 | N102: Responded — Interested | O102: Data Annotation | P102: CV Annotation | Q102: Direct | X102: Automotive/AV | Y102: Provided service overview and offered free 48-hour PoC; client to review internally and revert. | Z102: =IF(C102="","",(IF(OR(P102="Data Annotation",P102="GenAI / LLM Eval",P102="Medical Annotation"),25,IF(OR(P102="AI Consulting",P102="Data Collection"),18,IF(P102<>"",10,0)))+IF(AND(K102<>"",LEN(K102)>50,T102<>""),20,IF(AND(K102<>"",LEN(K102)>20),12,IF(K102<>"",5,0)))+IF(OR(U102="$100k–$500k",U102="$500k+"),20,IF(OR(U102="$25k–$100k"),15,IF(OR(U102="$5k–$25k"),10,IF(U102="$1k–$5k",5,0))))+IF(AND(G102<>"",G102<>"-"),15,IF(G102<>"",8,0))+IF(V102="Immediate (this month)",10,IF(V102="Short-term (1–3 months)",7,IF(V102="Medium (3–6 months)",4,0)))+IF(W102="Yes",10,IF(W102="Unclear",5,0)))) -> 37 | AA102: =IF(Z102="","",IF(Z102>=75,"A",IF(Z102>=50,"B",IF(Z102>=25,"C","D")))) -> C | AB102: =IF(C102="","",IF(AND(R102<>"",S102<>"",U102<>"",V102<>"",W102<>""),"✓ Complete","⚠ MISSING: "&IF(R102="","Call Date, ","")&IF(S102="","Modality, ","")&IF(U102="","Budget, ","")&IF(V102="","Timeline, ","")&IF(W102="","Decision Maker",""))) -> ⚠ MISSING: Call Date, Modality, Budget, Timeline, Decision Maker | AC102: Contacted
...

Sheet 2. Scoping & PoC
A1: AYA DATA — SCOPING & ACTIVE PIPELINE
A2: Leads that pass discovery call ("Move to Scoping" in Tab 1) are tracked here through scoping, PoC, and into Pilot. Lead ID links back to Tab 1 for full history.
A3: LEAD REFERENCE | E3: SCOPING / PoC | R3: COMMERCIAL | Y3: DEAL STATUS & PIPELINE | AH3: OUTCOME
A4: Lead ID | B4: Account Name | C4: Company | D4: Owner | E4: Date Entered Scoping | F4: Project Description | G4: Service Line | H4: Data Modality | I4: Annotation Type | J4: Platform Required | K4: Volume (units) | L4: Volume (est. hours) | M4: PoC Start Date | N4: PoC End Date | O4: PoC Cost | P4: PoC Outcome | Q4: PoC Feedback | R4: Hourly Rate ($) | S4: Est. Deal Value ($) | T4: Pricing Model | U4: Estimated Gross Margin | V4: Finance Approved Pricing | W4: SOW Status | X4: Date SOW Sent | Y4: Pipeline Stage | Z4: Win Probability (%) | AA4: Weighted Value ($) | AB4: Contract Type | AC4: Days in Scoping | AD4: Blockers | AE4: Next Steps | AF4: Risk / Notes | AG4: Last Updated | AH4: Date Won | AI4: Production Start Date | AJ4: Production End Date | AK4: Win/Loss Reason
A5: From Tab 1 | B5: Deal / project name | C5: From Tab 1 | D5: BD Owner | E5: Date entered | F5: Detailed scope | G5: Select | H5: Select | I5: e.g. BB, Segmentation, NLP | J5: v7, CVAT, Labelbox, etc. | K5: e.g. 50,000 images | L5: Est. annotator hours | M5: Date | N5: Date | P5: Select outcome | Q5: Client feedback notes | R5: Proposed $/hr | S5: Total deal value | T5: Hourly / Per-unit / Fixed | W5: Select | X5: Date | Y5: Select | Z5: 0-100% | AA5: AUTO | AB5: Select type | AC5: AUTO | AD5: Current blockers | AE5: Immediate next action | AF5: Free text | AG5: Date | AH5: When SOW signed | AI5: Actual start | AJ5: Actual/est end | AK5: Select reason
B6: Alegion - Solar (Vehicle & License Plate Annotation) Project | C6: Solar (Vehicle & License Plate Annotation) Project | D6: Seyram | E6: 45566 | F6: Bounding Box Annotation around vehicles, front & rear license plates and Wheel/axle. | G6: Data Annotation | H6: Video | I6: Video (BB) | K6: 195 records | S6: 21000 | W6: Signed | Y6: Won — In Production | Z6: 1 | AA6: =IF(OR(S6="",Z6=""),"",IF(OR(Y6="Won — In Production",Y6="Lost",Y6="On Hold"),"",S6*Z6)) | AB6: One-off Project | AC6: =IF(E6="","",IF(OR(Y6="Won — In Production",Y6="Lost"),"-",TODAY()-E6)) -> - | AD6: Waiting for project scope approval | AE6: Align during next meeting | AF6: Waiting for project scope approval | AG6: 46087
B7: Alegion - Rabona (Dual-Camera Soccer Detection) | C7: Rabona (Dual-Camera Soccer Detection) | D7: Seyram | E7: 45566 | F7: Identify and annotate persons and soccer balls on a soccer pitch with bounding boxes. | G7: Data Annotation | H7: Image | I7: Image (BB) | K7: 5000 Images | S7: 3250 | W7: Sent to Client | Y7: Lost | Z7: 0 | AA7: =IF(OR(S7="",Z7=""),"",IF(OR(Y7="Won — In Production",Y7="Lost",Y7="On Hold"),"",S7*Z7)) | AB7: One-off Project | AC7: =IF(E7="","",IF(OR(Y7="Won — In Production",Y7="Lost"),"-",TODAY()-E7)) -> - | AE7: Aling on produciton | AG7: 46087
B8: Alegion - Video Caption Opportunity | C8: Video Caption Opportunity | D8: Seyram | E8: 45566 | F8: Video captioning of 10s~15s videos | G8: Data Annotation | H8: Video | I8: NLP (Captioning) | K8: 100k - 200k videos | S8: 94000 | Y8: Lost | Z8: 0 | AA8: =IF(OR(S8="",Z8=""),"",IF(OR(Y8="Won — In Production",Y8="Lost",Y8="On Hold"),"",S8*Z8)) | AC8: =IF(E8="","",IF(OR(Y8="Won — In Production",Y8="Lost"),"-",TODAY()-E8)) -> - | AD8: Client is confirming project details, budget and deliverables internally for 2025 | AE8: Align during next meeting
B9: Analog & Verses AI | C9: Analog & Verses AI | D9: Michael | E9: 45566 | F9: Driver, Fleet & Maintainance Data collection | G9: Medical AI Annotation | H9: Image | I9: Data Collection | K9: 4000 Unique Driver Data points | S9: 35000 | W9: Sent to Client | Y9: Lost | Z9: 0 | AA9: =IF(OR(S9="",Z9=""),"",IF(OR(Y9="Won — In Production",Y9="Lost",Y9="On Hold"),"",S9*Z9)) | AB9: One-off Project | AC9: =IF(E9="","",IF(OR(Y9="Won — In Production",Y9="Lost"),"-",TODAY()-E9)) -> - | AD9: Waiting for Client to send SOW. | AE9: SOW signed | AF9: Waiting for Client to send SOW. | AG9: 46087
A10: AYA-065 | B10: MIT | C10: MIT | D10: Michael | E10: 45566 | F10: Crop Classification | G10: Data Annotation | I10: Crop Classification | K10: 20,000 images | S10: 6600 | Y10: Won — In Production | Z10: 1 | AA10: =IF(OR(S10="",Z10=""),"",IF(OR(Y10="Won — In Production",Y10="Lost",Y10="On Hold"),"",S10*Z10)) | AB10: One-off Project | AC10: =IF(E10="","",IF(OR(Y10="Won — In Production",Y10="Lost"),"-",TODAY()-E10)) -> - | AD10: Waiting feedback on proposal | AE10: Await response from client | AF10: Waiting feedback on proposal | AG10: 46087
B11: AUBA | C11: AUBA | D11: Michael | E11: 45566 | F11: PDF & XLSX-Classification | G11: Data Annotation | I11: Data labelling and Classification | K11: 12,000 pages | S11: 334 | W11: Signed | Y11: Won — In Production | Z11: 1 | AA11: =IF(OR(S11="",Z11=""),"",IF(OR(Y11="Won — In Production",Y11="Lost",Y11="On Hold"),"",S11*Z11)) | AB11: One-off Project | AC11: =IF(E11="","",IF(OR(Y11="Won — In Production",Y11="Lost"),"-",TODAY()-E11)) -> - | AD11: Yet to sign the SOW (They are a returning Client) | AE11: Arrange a call with their tech lead and Co-founder to discuss their project pipeline | AF11: Yet to sign the SOW (They are a returning Client) | AG11: 46087
B12: NorPalm Limited Confidence: (70%) | C12: NorPalm Limited Confidence: (70%) | D12: Other | E12: 45566 | F12: Digitizing manual farm operations & providing insights using AI & Drones | G12: Data Annotation | I12: AyaGrow | K12: 4,000 Hectares | S12: 13000 | Y12: Lost | Z12: 0 | AA12: =IF(OR(S12="",Z12=""),"",IF(OR(Y12="Won — In Production",Y12="Lost",Y12="On Hold"),"",S12*Z12)) | AB12: One-off Project | AC12: =IF(E12="","",IF(OR(Y12="Won — In Production",Y12="Lost"),"-",TODAY()-E12)) -> - | AD12: Delayed feedback from client on revised pricing | AE12: Awaiting response from client | AF12: Delayed feedback from client on revised pricing | AG12: 46087
